Workbook
Name nonparticipating_forecastzone_scale_factor: #REF!
Name nonparticipating_forecastzone_scale_factor: 'Energy Usage'!#REF!
Name Space_Function: Data!$A$2:$A$76

Sheet Notes
A1: Data Sources
A2: Dataset | B2: Dodge 2023
B3: Commercial End-Use Survey (CEUS) 2022 | C3: https://www.energy.ca.gov/publications/2023/2022-california-commercial-end-use-survey-ceus-final-report
B4: Commercial Buildings Energy Consumption Survey (CBECS) 2018 | C4: https://www.eia.gov/consumption/commercial/data/2018/index.php?view=microdata
B5: Comstock 2023 | C5: https://data.openei.org/s3_viewer?bucket=oedi-data-lake&prefix=nrel-pds-building-stock%2Fend-use-load-profiles-for-us-building-stock%2F2023%2Fcomstock_amy2018_release_2%2Fmetadata_and_annual_results%2Fby_state%2Fstate%3DCA%2F
A6: Prototype | B6: Pacific Northwest National Laboratory (PNNL) Large Hotel prototype (ASHRAE 90.1-2022) | C6: https://www.energycodes.gov/prototype-building-models#Commercial
B7: Database for Energy Efficient Resources (DEER) Hotel prototype (June 2024) | C7: https://github.com/sound-data/DEER-Prototypes-EnergyPlus
B8: Department of Energy (DOE) Large Hotel 2004 Prototype | C8: https://www.energy.gov/eere/buildings/new-construction-commercial-reference-buildings
B9: California Energy Commission (CEC) Small Hotel prototype (CBECC 2022.3.1) | C9: https://bees.noresco.com/software2022.html
A10: Codes | B10: Title 24, part 6, referred to as T24 (1984, 1992,1998, 2001, 2005, 2008, 2013, 2016,2019, 2022, 2025) | C10: https://www.energy.ca.gov/publications/2025/2025-building-energy-efficiency-standards-residential-and-nonresidential | D10: 2025
C11: https://codes.iccsafe.org/codes/united-states/california | D11: 2010+
B12: American Society of Heating, Refrigerating and Air-Conditioning Engineers (ASHRAE) 90.1 (2022) | C12: https://www.ashrae.org/technical-resources/standards-and-guidelines/read-only-versions-of-ashrae-standards
B13: Title 20 | C13: https://govt.westlaw.com/calregs/Document/I270DCA634B4011EFA8F7F119BAF97AD6?viewType=FullText&originationContext=documenttoc&transitionType=CategoryPageItem&contextData=(sc.Default)
A15: Others | B15: Alternative Calculation Method (ACM) (2022) | C15: https://www.energy.ca.gov/publications/2022/2022-nonresidential-and-multifamily-alternative-calculation-method-reference
B16: ACM (2025) | C16: https://www.energy.ca.gov/publications/2025/2025-nonresidential-and-multifamily-alternative-calculation-method-reference
B17: Nonres ACM 2022, Appendix 5.4A and Appendix 5.4B | C17: https://www.energy.ca.gov/publications/2022/2022-nonresidential-and-multifamily-alternative-calculation-method-reference
B18: 2022 Reduced infiltration Codes and Standards Enhancement (CASE) report | C18: https://title24stakeholders.com/wp-content/uploads/2020/10/2022-T24-Final-CASE-Report_Reduce-Infiltration.pdf
B19: Honeywell, INNCOM e7 Thermostat User Guide, 2017 | C19: https://prod-edam.honeywell.com/content/dam/honeywell-edam/hbt/en-us/documents/manuals-and-guides/installation-guides/inncom/hbt-bms-INNCOM-e7-USER-GUIDE.pdf?download=false
B20: 2019 Outdoor Lighting CASE Report | C20: https://title24stakeholders.com/wp-content/uploads/2016/10/T24-2019-CASE-Study-Results-Report-Outdoor-Sources_Final_with-Attachments.pdf
B21: 2024 California Lodging forecast | C21: https://assets.visitcalifornia.com/media/?mediaId=D0CF4716-DD37-4678-852AB388768DE451&viewType=grid
B22: 2025 State of the Industry Report | C22: https://www.ahla.com/sites/default/files/25_SOTI.pdf
B23: PNNL 20405, 2011 | C23: https://www.pnnl.gov/main/publications/external/technical_reports/PNNL-20405.pdf
B24: Air leakage Memo, NORESCO, 2025 | C24: Infiltration_rate_report_14May2025-Short-Version.docx
B25: Yousefi, F., Athalye, R., (2025), "Determining Vintage Bins for Prototype Development: An Analysis of California Commercial Buildings," ASHRAE Annual Conference | C25: https://www.thefreelibrary.com/Determining+Vintage+Bins+for+Prototype+Development%3a+An+Analysis+of...-a0879271125
B26: Proposed Updates to Equipment Power Densities and Building Schedules for the 2028 Energy Code, referred to as "Plug load and schedules project with CEC, 2025" (Docket Number =25-BSTD-03 & TN=265693) | C26: https://efiling.energy.ca.gov/GetDocument.aspx?tn=265693&DocumentContentId=102545
B27: ENERGY STAR certified commercial water heaters | C27: https://www.energystar.gov/productfinder/product/certified-commercial-water-heaters/results?fuel_filter=Gas&markets_filter=United+States
... B29: Grainger electric tank water heaters | C29: https://www.grainger.com/category/plumbing/water-heaters/electric-tank-water-heaters
A31: Construction Rate
B43: Source:Dodge Construction Data, 2023 ( NEW Hotels above 60,000 sf built after 1967) (STC refers to building types in Dodge terminology).
A44: Notes
A45: HotelLarge Prototype | B45: The HotelLarge prototype was developed to represent California large hotels with floor area above 60,000 ft² , no matter of their number of stories. According to Dodge (2023), the average large hotel in California is described as a 9‑story building with a total floor area of 150,000 sf and a footprint of 16,600 sf. In comparison, the PNNL large hotel prototype is characterized as a 7‑story building with a total floor area of 122,000 sf and a 17,400 sf footprint, placing its footprint within 5% of the California average. Because the prototype is considered well established and has defined zoning, it is selected as the basis for the model and modified through the addition of two floors. With this modification, alignment with the California building stock assessment is achieved, and the percentage of guest rooms is increased.
A72: "NUMPRO=1" refers to Dodge records with only one building per record, while "All extended" includes all the records.
A73: Source:Dodge Construction Data, 2023 ( NEW Hotels above 60,000 sf built after 1967) (STC refers to building types in Dodge terminology).
A75: 1984 is the representative year for the 1984-1997 vintage bin | B75: "Most large hotels in this vintage bin were built after 1984 (more than 53% ) and the CA energy code did not noticeably changed between 1984 to 1992) Also "Heat Capacity" for external wall is considered between 10.0 to 14.99 (Btu/F/ft²) Package A was selected for the thermal properties, and the prescriptive criteria of high-rise office buildings were also applied to the large hotel.
A76: 2001 is the representative year for the 1998-2007 vintage bin | B76: Wall and roof prescriptive criteria from 1998 to 2005 remain unchanged except for CZ2 and 6 in 2001 code (the percentage of change is less than 10%).
B77: Since the construction rate between 1998-2005 is greater than the 2006-2007 period, the envelope properties of 1998 -2005 were chosen for envelope properties. Since the windows requirement considerably changed in the 2001 code, the nominated year for this vintage is 2001.
A78: 2013 is the representative year for the 2008-2018 vintage bin | B78: Wall properties remain unchanged from the 2008 code to the 2016 code but the roof did changed. Although the 2016 code introduced improvement for roof in nearly all CZ and for wall in a few CZ, and construction activity surged between 2017 and 2018, the extended period from 2008 to 2016 resulted in a higher construction rate during that time . As a result, it was decided to select the code that was effective during 2008-2016.
B79: Construction activity from 2014-2018 was higher compared to 2008-2013 period. Therefore, the 2013 code was chosen as the representative code. Additionally, the 2013 code modified the solar reflectance requirement for low-sloped roof products ( by approximately 15%), and enhanced window properties.

Sheet Prototype
A1: NORESCO, Updated September 2026
A2: HotelLarge
A3: Characteristic | B3: Value | C3: Data Sources
A4: Building Type | B4: Large Hotel
A5: Building Category | B5: Nonresidential
A6: Version | B6: v2-0
A7: Vintages | B7: 4 Vintages: Pre-1978 , 1978-1997 ,1998-2007 , 2008-2018 New Construction (2019+) | C7: Based on the vintage bin analysis. A summary of the findings is presented in the following paper, with a link provided in the Notes tab: Yousefi, F., Athalye, R. (2025). “Determining Vintage Bins for Prototype Development: An Analysis of California Commercial Buildings.” ASHRAE Annual Conference.
A8: Shape | C8: PNNL Hotel Large 2022 prototype, modified by adding two additional living floors, based on Dodge 2023 data analysis and update zoning of the basement and ground floor.
A9: Total Floor Area (ft²) | B9: 153,921 (284 ft x 75 ft) | C9: Total floor area : Dodge 2023 data, Footprint :PNNL Hotel Large 2022
A10: Aspect Ratio | B10: Ground floor: 3.79 (284 ft x 75 ft) All other floors: 5.07 (284 ft x 56 ft) | C10: Assumption: PNNL Hotel Large 2022
A11: Number of Floors | B11: 8 above-ground floors plus one basement | C11: Dodge 2023 data,
A12: Surface to Floor Area Ratio
A13: Number of Guestrooms | B13: 263 (accounting for about 48% of the total floor area)
A14: Roof type | B14: Flat roof
A15: WWR | B15: South: 36.7%, East: 24.5%, North: 26.0%, West: 24.5% Total: 30.2% | C15: Assumption: PNNL Hotel Large 2022
A16: Shading Geometry | B16: -
A17: Floor to floor height (ft) | B17: Basement: 13 ft Ground floor: 13 ft 2nd - 6th floors: 10 ft | C17: Assumptions: PNNL Hotel Large 2022 Basement height: assumed based on the average basement height of typical large hotels, considering associated space requirements
A18: Floor to ceiling height (ft) | B18: Basement: 13 ft Ground floor: 13 ft 2nd - 8th floors: 10 ft | C18: Assumptions: PNNL Hotel Large 2022 Basement height: assumed based on the average basement height of typical large hotels, considering associated space requirements
A19: Glazing sill height (ft) | B19: 6 in.(in ground floor), 3.6 ft. (in upper floors) | C19: Assumptions:PNNL Hotel Large 2022
A23: Above grade wall area (ft²) | B23: 43333.6
A24: Gross wall area (ft²) | B24: 49079.02
A25: Roof area (ft²) | B25: 21300.06
A26: Underground Gross Wall Area (ft²) | B26: 5745.5
A35: Background Data
A38: Existing Public Prototypes:
B39: CPUC | C39: PNNL | E39: Zone | F39: CPUC | J39: PNNL
A40: Geometry | F40: Area share (%) | G40: People (ft² per person) | H40: Lighting (W/ft²) | I40: Plug and Process (W/ft²) | J40: Area share | K40: People (ft² per person) | L40: Lighting (W/ft²) | M40: Plug and Process (W/ft²) | N40: Electric Load (W/ft²) | O40: Gas Load (W/ft²)
A41: Stories | B41: 4 stories | C41: 6 Stories + Basement | E41: Small Guest room | F41: 0.1597292 | G41: 399.98691 | H41: 0.50000416 | I41: 0.50000416 | J41: 0.34809077 | K41: 175.98994 | L41: 0.40970241 | M41: 0.97733998 | N41: 0.97733998 | O41: 0
A42: Total floor area (ft²) | B42: =CONVERT(6369.28,"m2","ft2") -> 68558.359 | C42: =CONVERT(11345.29,"m2","ft2") -> 122119.69 | E42: Large Guest room | F42: 0.47920644 | G42: 399.98691 | H42: 0.50000416 | I42: 0.50000416 | J42: 0.061905446 | K42: 279.96931 | L42: 0.40970241 | M42: 0.62709552 | N42: 0.62709552 | O42: 0
A43: Planus (ft²) | B43: Yes: 68,558 | C43: No | E43: Corridor | F43: 0.080467494 | G43: 199.99346 | H43: 0.40000333 | I43: 0 | J43: 0.17360954 | K43: 199.99346 | L43: 0.41806368 | M43: 0 | N43: 0 | O43: 0
A44: Multiplier | B44: No | C44: Yes | E44: Dining | F44: 0.011665369 | G44: 30.03131 | H44: 0.40000333 | I44: 0.50000416 | J44: 0.029232246 | K44: 14.316001 | L44: 0.72185662 | M44: 6.3006842 | N44: 6.3006842 | O44: 0
A45: Number of Guest room | B45: 12 | C45: 179 | E45: Kitchen | F45: 0.014568366 | G45: 399.98691 | H45: 0.94999862 | I45: 7.7591225 | J45: 0.009104779 | K45: 50.052183 | L45: 1.1305371 | M45: 272.34526 | N45: 47.588932 | O45: 224.75661
A46: Above Ground WWR | B46: 0.2228 | C46: 0.3015 | E46: Lobby | F46: 0.11990366 | G46: 30.03131 | H46: 0.69999654 | I46: 0.50000416 | J46: 0.11530282 | K46: 33.368122 | L46: 0.75994687 | M46: 0.74972753 | N46: 0.74972753 | O46: 0
A47: Areas: | E47: Laundry | F47: 0.059948691 | G47: 199.99346 | H47: 0.45000375 | I47: 3.2200008 | J47: 0.0068783829 | K47: 99.996728 | L47: 0.48402484 | M47: 55.512353 | N47: 5.7302595 | O47: 49.782094
A48: Window Opening Area (ft²) | B48: 6744.9892 | C48: 13065.127 | E48: Office | F48: 0.059948691 | G48: 199.99346 | H48: 0.5999957 | I48: 1.5000032
A49: Skylight Area (ft²) | B49: 0 | C49: 0 | E49: Barcasino | F49: 0.014568366 | G49: 30.03131 | H49: 0.40000333 | I49: 0.50000416
A50: Gross Roof Area (ft²) | B50: 239.81992 | C50: 21300.056 | E50: Basement | J50: 0.17441249 | K50: 199.99346 | L50: 0.57599885 | M50: 0.49981836 | N50: 0.49981836 | O50: 0
A51: Gross Wall Area (ft²) | B51: 30277.696 | C51: 49079.018 | E51: Retail | J51: 0.012757267 | K51: 66.628605 | L51: 0.70234698 | M51: 0.99963671 | N51: 0.49981836 | O51: 0
A52: Above Ground Wall Area (ft²) | B52: 30277.696 | C52: 43333.566 | E52: Mech | J52: 0.014475982 | K52: 666.60897 | L52: 0.67447607 | M52: 0.49981836 | N52: 0.49981836 | O52: 0
A53: Loads | E53: Storage | J53: 0.0083520703 | K53: 499.98364 | L53: 0.35117349 | M53: 0.24990918 | N53: 0.24990918 | O53: 0
A54: People (m² per person) | B54: Guest room: 37.2 | C54: Larger Guest room: 16.3 smaller Guest room: 26.0 | E54: Café | J54: 0.016645969 | K54: 14.316001 | L54: 0.72185662 | M54: 0.49981836 | N54: 0.49981836 | O54: 0
A55: Lights (w/m²) | B55: Guest room: 5.38 | C55: Guest room: 4.41 | E55: Banquet | J55: 0.029232246 | K55: 14.316001 | L55: 0.72185662 | M55: 6.3006842 | N55: 6.3006842 | O55: 0
A56: Equipment (w/m²) | B56: Guest room: 5.38 | C56: Larger Guest room: 6.75 smaller Guest room: 10.52
A57: Water heater system | B57: Gas | C57: Gas (main) / Elec
A58: Refrigeration | B58: No | C58: Yes
A59: Generators | B59: No | C59: No
A60: Humidification | B60: No | C60: No
A61: Heat Recovery | B61: No | C61: No
A62: Heat Rejection | B62: No | C62: No
A64: HVAC | B64: - Guest rooms: SZ VAV No Reheat + DX cooling + Gas heating - Kitchen: SZ VAV No Reheat + DX cooling + Gas heating - All other zones: MZ VAV Reheat per floor + DX cooling + water heating coil from boiler | C64: - Guest rooms: 4PFC + water cooling coil from chiller + water heating coil from Boiler + DOAS with (CAV) -All other zones: MZ VAV with Reheat + water cooling coil from chiller + water heating coil from boiler
A65: Fan simulation | B65: "Fan: System Model" | C65: "Fan:ConstantVolume" &"Fan:VariableVolume"
A66: Exhaust fan | C66: Laundry, Lobby, Banquet, Dining, Kitchen

Sheet Zones
A1: ="Proposed Layout - "&Prototype!A2 -> Proposed Layout - HotelLarge | P1: N
A2: Building | B2: Space/ Thermal Zone | C2: Space Type [Primarily from: T24, 2022 Appendix 5.4A] - See Notes column | D2: HVAC System Name/AHU Name | E2: Schedule Category | F2: Conditioned (Y/N) | G2: Area Fraction | H2: Area (ft²) | I2: Volume (ft³) | J2: Multipliers | K2: Number of People | L2: People (Persons/1,000 ft²) [T24, 2025,Table 120.1-A] | M2: Notes
A3: HotelLarge | B3: BasementConference | C3: Convention, Conference, Multipurpose and Meeting Area | E3: Office | F3: Yes | G3: =H3/$H$30 -> 0.048433613 | H3: 7454.9371 | I3: =H3*13 -> 96914.183 | J3: 1 | K3: =L3*H3/1000 -> 246.01293 | L3: 33
A4: HotelLarge | B4: BasementOffice | C4: Office Area (>250 square feet) | E4: Office | F4: Yes | G4: =H4/$H$30 -> 0.010733444 | H4: 1652.0996 | I4: =H4*13 -> 21477.295 | J4: 1 | K4: =L4*H4/1000 -> 8.2604979 | L4: 5
A5: HotelLarge | B5: BasementMechanical | C5: Electrical, Mechanical, Telephone Rooms | E5: Ancillary | F5: Yes | G5: =H5/$H$30 -> 0.011485483 | H5: 1767.854 | I5: =H5*13 -> 22982.102 | J5: 1 | K5: =L5*H5/1000 -> 0 | L5: 0
A6: HotelLarge | B6: BasementLaundry | C6: Laundry Area | E6: Assembly | F6: Yes | G6: =H6/$H$30 -> 0.0054574228 | H6: 840.0105 | I6: =H6*13 -> 10920.137 | J6: 1 | K6: =L6*H6/1000 -> 4.2000525 | L6: 5 | N6: Basement: 6 zones including Storage, service, storage, laundry, mechanical rooms, Office, and conference
A7: HotelLarge | B7: BasementService | C7: Service and back up prep | E7: ServiceAndBackUpPrep | F7: Yes | G7: =H7/$H$30 -> 0.041514526 | H7: 6389.9461 | I7: =H7*13 -> 83069.299 | J7: 1 | K7: =L7*H7/1000 -> 19.169838 | L7: 3
A8: HotelLarge | B8: BasementStorage | C8: Storage (General) | E8: Assembly | F8: Yes | G8: =H8/$H$30 -> 0.020757263 | H8: 3194.9731 | I8: =H8*13 -> 41534.65 | J8: 1 | K8: =L8*H8/1000 -> 0 | L8: 0
A9: HotelLarge | B9: Retail_1_FloorG | C9: Retail Sales Area (Retail Merchandise Sales) | E9: Retail | F9: Yes | G9: =H9/$H$30 -> 0.0046902787 | H9: 721.93112 | I9: =H9*13 -> 9385.1045 | J9: 1 | K9: =L9*H9/1000 -> 12.272829 | L9: 17
A10: HotelLarge | B10: Retail_2_FloorG | C10: Retail Sales Area (Retail Merchandise Sales) | E10: Retail | F10: Yes | G10: =H10/$H$30 -> 0.0054315483 | H10: 836.02788 | I10: =H10*13 -> 10868.362 | J10: 1 | K10: =L10*H10/1000 -> 14.212474 | L10: 17
A11: HotelLarge | B11: Office_FloorG | C11: Office Area (>250 square feet) | E11: Office | F11: Yes | G11: =H11/$H$30 -> 0.011485483 | H11: 1767.854 | I11: =H11*13 -> 22982.102 | J11: 1 | K11: =L11*H11/1000 -> 8.8392699 | L11: 5
A12: HotelLarge | B12: Storage_FloorG | C12: Storage (General) | E12: Assembly | F12: Yes | G12: =H12/$H$30 -> 0.0066266707 | H12: 1019.982 | I12: =H12*13 -> 13259.766 | J12: 1 | K12: =L12*H12/1000 -> 0 | L12: 0
A13: HotelLarge | B13: Kitchen_FloorG | C13: Kitchen/Food Preparation Area | E13: Kitchen | F13: Yes | G13: =H13/$H$30 -> 0.0054574228 | H13: 840.0105 | I13: =H13*13 -> 10920.137 | J13: 1 | K13: =L13*H13/1000 -> 2.5200315 | L13: 3 | N13: FloorG (Ground floor): 7 zones including retails, lobby, cafe, Kitchen, storage and Office;
A14: HotelLarge | B14: Cafe_FloorG | C14: Dining Area (Cafeteria/Fast Food) | E14: =E27 -> Restaurant | F14: Yes | G14: =H14/$H$30 -> 0.013207187 | H14: 2032.8599 | I14: =H14*13 -> 26427.178 | J14: 1 | K14: =L14*H14/1000 -> 67.084375 | L14: 33
A15: HotelLarge | B15: Lobby_FloorG | C15: Lobby, Main Entry | E15: ResidentialCommon | F15: Yes | G15: =H15/$H$30 -> 0.091483162 | H15: 14081.155 | I15: =H15*13 -> 183055.02 | J15: 1 | K15: =L15*H15/1000 -> 140.81155 | L15: 10 | M15: For entrance lobbies, 10 persons per 1,000 ft² are assumed based on ASHRAE 62.1 Table 6‑1 (Office Entrance). The Title 24 assumptions for main entry lobbies result in an unrealistically high total occupant count and therefore was not used. Title 24 specifies 33 persons per 1,000 ft² for main entry lobbies and 5 persons per 1,000 ft² for reception areas.
A16: HotelLarge | B16: GuestRoom_1_FloorM | C16: Hotel/Motel Guest Room | E16: ResidentialLiving | F16: Yes | G16: =H16/$H$30 -> 0.0027287114 | H16: 420.00525 | I16: =H16*10 -> 4200.0525 | J16: 6 | K16: =L16*H16/1000 -> 1.2600158 | L16: 3
A17: HotelLarge | B17: GuestRoom_2_FloorM | C17: Hotel/Motel Guest Room | E17: =E16 -> ResidentialLiving | F17: Yes | G17: =H17/$H$30 -> 0.0027287114 | H17: 420.00525 | I17: =H17*10 -> 4200.0525 | J17: 6 | K17: =L17*H17/1000 -> 1.2600158 | L17: 3
A18: HotelLarge | B18: GuestRoom_3_Multi19_FloorM | C18: Hotel/Motel Guest Room | E18: =E16 -> ResidentialLiving | F18: Yes | G18: =H18/$H$30 -> 0.0017147105 | H18: 263.92949 | I18: =H18*10 -> 2639.2949 | J18: =6*19 -> 114 | K18: =L18*H18/1000 -> 0.79178847 | L18: 3
A19: HotelLarge | B19: GuestRoom_4_Multi19_FloorM | C19: Hotel/Motel Guest Room | E19: =E16 -> ResidentialLiving | F19: Yes | G19: =H19/$H$30 -> 0.0017154098 | H19: 264.03713 | I19: =H19*10 -> 2640.3713 | J19: =6*19 -> 114 | K19: =L19*H19/1000 -> 0.79211139 | L19: 3 | S19: Full view of FloorM
A20: HotelLarge | B20: GuestRoom_5_FloorM | C20: Hotel/Motel Guest Room | E20: =E16 -> ResidentialLiving | F20: Yes | G20: =H20/$H$30 -> 0.0027287114 | H20: 420.00525 | I20: =H20*10 -> 4200.0525 | J20: 6 | K20: =L20*H20/1000 -> 1.2600158 | L20: 3 | N20: FloorM (Middle floors): 2nd to 7th Floor : 7 zones per floor, including guest rooms and corridor. Each floor has 42 guest rooms;
A21: HotelLarge | B21: GuestRoom_6_FloorM | C21: Hotel/Motel Guest Room | E21: =E16 -> ResidentialLiving | F21: Yes | G21: =H21/$H$30 -> 0.0027287114 | H21: 420.00525 | I21: =H21*10 -> 4200.0525 | J21: 6 | K21: =L21*H21/1000 -> 1.2600158 | L21: 3
A22: HotelLarge | B22: Corridor_FloorM | C22: Corridor Area | E22: ResidentialCommon | F22: Yes | G22: =H22/$H$30 -> 0.027231169 | H22: 4191.4414 | I22: =H22*10 -> 41914.414 | J22: 6 | K22: =L22*H22/1000 -> 20.957207 | L22: 5
A23: HotelLarge | B23: GuestRoom_1_FloorT | C23: Hotel/Motel Guest Room | E23: =E16 -> ResidentialLiving | F23: Yes | G23: =H23/$H$30 -> 0.0027287114 | H23: 420.00525 | I23: =H23*10 -> 4200.0525 | J23: 1 | K23: =L23*H23/1000 -> 1.2600158 | L23: 3
A24: HotelLarge | B24: GuestRoom_2_FloorT | C24: Hotel/Motel Guest Room | E24: =E16 -> ResidentialLiving | F24: Yes | G24: =H24/$H$30 -> 0.0027287114 | H24: 420.00525 | I24: =H24*10 -> 4200.0525 | J24: 1 | K24: =L24*H24/1000 -> 1.2600158 | L24: 3
A25: HotelLarge | B25: GuestRoom_3_Multi9_FloorT | C25: Hotel/Motel Guest Room | E25: =E16 -> ResidentialLiving | F25: Yes | G25: =H25/$H$30 -> 0.0017154098 | H25: 264.03713 | I25: =H25*10 -> 2640.3713 | J25: 9 | K25: =L25*H25/1000 -> 0.79211139 | L25: 3
A26: HotelLarge | B26: Banquet_FloorT | C26: Hotel Function Area | E26: Assembly | F26: Yes | G26: =H26/$H$30 -> 0.023193348 | H26: 3569.937 | I26: =H26*10 -> 35699.37 | J26: 1 | K26: =L26*H26/1000 -> 117.80792 | L26: 33 | M26: Occupancy based on "Restaurant Dining Area"
A27: HotelLarge | B27: Dining_FloorT | C27: Dining Area (Bar/Lounge and Fine Dining) | E27: Restaurant | F27: Yes | G27: =H27/$H$30 -> 0.023193348 | H27: 3569.937 | I27: =H27*10 -> 35699.37 | J27: 1 | K27: =L27*H27/1000 -> 117.80792 | L27: 33
A28: HotelLarge | B28: Kitchen_FloorT | C28: Kitchen/Food Preparation Area | E28: Kitchen | F28: Yes | G28: =H28/$H$30 -> 0.0072238823 | H28: 1111.9052 | I28: =H28*10 -> 11119.052 | J28: 1 | K28: =L28*H28/1000 -> 3.3357157 | L28: 3
A29: HotelLarge | B29: Corridor_FloorT | C29: Corridor Area | E29: =E22 -> ResidentialCommon | F29: Yes | G29: =H29/$H$30 -> 0.028820004 | H29: 4435.996 | I29: =H29*10 -> 44359.96 | J29: 1 | K29: =L29*H29/1000 -> 22.17998 | L29: 5 | S29: Full view of FloorT
A30: Total (1 Building) | B30: Total (286 Space/Thermal Zones) | C30: Total (14 Space Types) | E30: Total (9 Schedule categories) | F30: Total (286 Conditioned zones) | G30: =SUMPRODUCT(G3:G29,J3:J29) -> 1 | H30: =SUMPRODUCT(H3:H29,J3:J29) -> 153920.73 | I30: =SUMPRODUCT(I3:I29,J3:J29) -> 1667006.2 | N30: FloorT (Top floor): 9th Floor: 7 zones including guest rooms, banquet room, dining, kitchen and corridor.
B32: Ref for layout and zoning: PNNL Large Hotel prototypes (ASHRAE 90.1 2022)
B35: Occupancy Rate
B36: % of occupied guest rooms | C36: Source
B37: 0.65 | C37: California Lodging Forecast (April 2025)
C38: 2025 State of the industry report
C41: Number of Guest room | D41: =SUM(J16:J21,J23:J25) -> 263
C42: Guest room (ft²) | D42: =SUMPRODUCT(H16:H21,J16:J21)+SUMPRODUCT(H23:H25,J23:J25) -> 73484.666
C43: Guest room % ( all floors except basement) | D43: =D42/(H30-SUM(H3:H8)) -> 0.55409562
C44: Guest room % ( all floors) | D44: =D42/H30 -> 0.4774189

Sheet Envelope
A1: ="Envelope - "&Prototype!A2 -> Envelope - HotelLarge
A2: Element | B2: Prototype | C2: Assembly Type | D2: Construction | E2: Thermal Properties | F2: Vintage | G2: Selected T24 | H2: Notes | I2: CZ1 | J2: CZ2 | K2: CZ3 | L2: CZ4 | M2: CZ5 | N2: CZ6 | O2: CZ7 | P2: CZ8 | Q2: CZ9 | R2: CZ10 | S2: CZ11 | T2: CZ12 | U2: CZ13 | V2: CZ14 | W2: CZ15 | X2: CZ16
A3: External Wall_ Guest Room (FloorM and FloorT) | B3: HotelLarge | C3: ExtWall_MetalFramed_GuestRooms | D3: Metal framed wall: Stucco + Metal frame + insulation + Gypsum board | E3: U-factor IP | F3: Pre 1978 | G3: N/A | H3: ASHRAE 90.1, 2022, Table A3.3.3.1, 3.5", R-0 | I3: 0.352 | J3: 0.352 | K3: 0.352 | L3: 0.352 | M3: 0.352 | N3: 0.352 | O3: 0.352 | P3: 0.352 | Q3: 0.352 | R3: 0.352 | S3: 0.352 | T3: 0.352 | U3: 0.352 | V3: 0.352 | W3: 0.352 | X3: 0.352
F4: 1978-1997 | G4: 1986 | H4: Copied from High-rise office alternative requirements (Table 2-53W): Package A with heat capacity between 10-14.99 (Btu/F-ft²) *T24, 1986, Table 2-53B presents U-factors less than the next vintage (for wall density of 26-40 lb/ft² & Degree day<3500)! | I4: =1/4.7 -> 0.21276596 | J4: =1/4.4 -> 0.22727273 | K4: =1/4.4 -> 0.22727273 | L4: =1/4.6 -> 0.2173913 | M4: =1/4.6 -> 0.2173913 | N4: =1/3.9 -> 0.25641026 | O4: =1/3.9 -> 0.25641026 | P4: =1/3.9 -> 0.25641026 | Q4: =1/3.9 -> 0.25641026 | R4: =1/3.9 -> 0.25641026 | S4: =1/4.2 -> 0.23809524 | T4: =1/4.2 -> 0.23809524 | U4: =1/4.2 -> 0.23809524 | V4: =1/4.8 -> 0.20833333 | W4: =1/4.8 -> 0.20833333 | X4: =1/4.7 -> 0.21276596 | Y4: * Heat capacity might be close to 4-9.99 categories for mix of steel frame and concrete (concrete for fist floor) . However, selecting this category will result in U values lower than the next vintage to both REs and Nonres! (for HC below 4 Btu/F-ft², all CZ is 1/7.4)
F5: 1998-2007 | G5: 2001 | H5: Table 1-I | I5: 0.14 | J5: 0.175 | K5: 0.181 | L5: 0.181 | M5: 0.181 | N5: 0.181 | O5: 0.181 | P5: 0.181 | Q5: 0.181 | R5: 0.175 | S5: 0.175 | T5: 0.175 | U5: 0.175 | V5: 0.175 | W5: 0.175 | X5: 0.14
F6: 2008-2018 | G6: 2013 | H6: Table 140.3-C | I6: 0.105 | J6: 0.105 | K6: 0.105 | L6: 0.105 | M6: 0.105 | N6: 0.105 | O6: 0.105 | P6: 0.105 | Q6: 0.105 | R6: 0.105 | S6: 0.105 | T6: 0.105 | U6: 0.105 | V6: 0.105 | W6: 0.105 | X6: 0.105
F7: 2019+ | G7: 2025 | H7: Table 140.3-C | I7: 0.069 | J7: 0.069 | K7: 0.069 | L7: 0.069 | M7: 0.069 | N7: 0.069 | O7: 0.105 | P7: 0.069 | Q7: 0.069 | R7: 0.069 | S7: 0.069 | T7: 0.069 | U7: 0.069 | V7: 0.069 | W7: 0.048 | X7: 0.069
A8: External Wall_ Nonres (FloorG) | B8: HotelLarge | C8: ExtWall_MassHeavy_NonRes | D8: Heavy mass wall: Stucco + 8 in Concrete + insulation + Gypsum board | E8: U-factor IP | F8: Pre 1978 | G8: N/A | H8: ASHRAE 90.1, 2022, Table A3.1-1, R-0 | I8: 0.74 | J8: 0.74 | K8: 0.74 | L8: 0.74 | M8: 0.74 | N8: 0.74 | O8: 0.74 | P8: 0.74 | Q8: 0.74 | R8: 0.74 | S8: 0.74 | T8: 0.74 | U8: 0.74 | V8: 0.74 | W8: 0.74 | X8: 0.74
F9: 1978-1997 | G9: 1992 | H9: Same as 1992. No direct regulation was found in 1986 for concrete walls. Also, T24, 1986, Table 2-53B and Equation 2-53E presents U-factors more than the previous vintage (for wall density of >81 lb/ft² & Degree day<3000). | I9: 0.36 | J9: 0.65 | K9: 0.65 | L9: 0.65 | M9: 0.65 | N9: 0.69 | O9: 0.69 | P9: 0.69 | Q9: 0.69 | R9: 0.69 | S9: 0.65 | T9: 0.65 | U9: 0.65 | V9: 0.4 | W9: 0.4 | X9: 0.36
F10: 1998-2007 | G10: 2001 | H10: Table 1-H | I10: 0.36 | J10: 0.65 | K10: 0.65 | L10: 0.65 | M10: 0.65 | N10: 0.69 | O10: 0.69 | P10: 0.69 | Q10: 0.69 | R10: 0.65 | S10: 0.65 | T10: 0.65 | U10: 0.65 | V10: 0.4 | W10: 0.4 | X10: 0.36
F11: 2008-2018 | G11: 2013 | H11: Table 140.3-B | I11: 0.253 | J11: 0.65 | K11: 0.65 | L11: 0.65 | M11: 0.65 | N11: 0.69 | O11: 0.69 | P11: 0.69 | Q11: 0.69 | R11: 0.65 | S11: 0.184 | T11: 0.253 | U11: 0.211 | V11: 0.184 | W11: 0.184 | X11: 0.16
F12: 2019+ | G12: 2025 | H12: Table 140.3-B (Nonres) | I12: 0.211 | J12: 0.65 | K12: 0.65 | L12: 0.65 | M12: 0.65 | N12: 0.69 | O12: 0.69 | P12: 0.69 | Q12: 0.69 | R12: 0.65 | S12: 0.16 | T12: 0.211 | U12: 0.184 | V12: 0.16 | W12: 0.16 | X12: 0.153
A13: Roof_Guest Room (FloorT) | B13: HotelLarge | C13: FlatRoof_WoodFramedAndOther_GuestRooms | D13: Metal deck roof: Roof membrane + insulation + Metal Deck | E13: U-factor IP | F13: Pre 1978 | G13: N/A | H13: Considering 30 years for roof/ insulation replacement. ( Guest room requirement) | I13: =I14 -> 0.037 | J13: =J14 -> 0.051 | K13: =K14 -> 0.051 | L13: =L14 -> 0.051 | M13: =M14 -> 0.051 | N13: =N14 -> 0.051 | O13: =O14 -> 0.051 | P13: =P14 -> 0.051 | ... X13: =X14 -> 0.037
F14: 1978-1997 | G14: 1992 | I14: 0.037 | J14: 0.051 | K14: 0.051 | L14: 0.051 | M14: 0.051 | N14: 0.051 | O14: 0.051 | P14: 0.051 | Q14: 0.051 | R14: 0.051 | S14: 0.037 | T14: 0.037 | U14: 0.037 | V14: 0.037 | W14: 0.037 | X14: 0.037
F15: 1998-2007 | G15: 2001 | H15: Table 1-I (the lowest U-factor between Nonres and Guest room was considered) | I15: 0.037 | J15: 0.037 | K15: 0.051 | L15: 0.051 | M15: 0.051 | N15: 0.051 | O15: 0.051 | P15: 0.051 | Q15: 0.051 | R15: 0.037 | S15: 0.037 | T15: 0.037 | U15: 0.037 | V15: 0.037 | W15: 0.037 | X15: 0.037
F16: 2008-2018 | G16: 2013 | H16: Table 140.3-C (the lowest U-factor between Nonres and Guest room was considered) | I16: 0.034 | J16: 0.028 | K16: 0.039 | L16: 0.028 | M16: 0.039 | N16: 0.039 | O16: 0.039 | P16: 0.028 | Q16: 0.028 | R16: 0.028 | S16: 0.028 | T16: 0.028 | U16: 0.028 | V16: 0.028 | W16: 0.028 | X16: 0.028
F17: 2019+ | G17: 2025 | H17: Table 140.3-C (the lowest U-factor between Nonres and Guest room was considered) | I17: 0.028 | J17: 0.028 | K17: 0.028 | L17: 0.028 | M17: 0.034 | N17: 0.034 | O17: 0.039 | P17: 0.028 | Q17: 0.028 | R17: 0.028 | S17: 0.028 | T17: 0.028 | U17: 0.028 | V17: 0.028 | W17: 0.028 | X17: 0.028
A18: Roof_Nonres (FloorG) | B18: HotelLarge | C18: FlatRoof_WoodFramedAndOther_NonRes | D18: Metal deck roof: Roof membrane + insulation + Metal Deck | E18: U-factor IP | F18: Pre 1978 | G18: N/A | H18: Considering 30 years for roof/ insulation replacement. ( Guest room requirement) | I18: 0.057 | J18: 0.057 | K18: 0.057 | L18: 0.057 | M18: 0.057 | N18: 0.078 | O18: 0.078 | P18: 0.078 | Q18: 0.078 | R18: 0.078 | S18: 0.057 | T18: 0.057 | U18: 0.057 | V18: 0.057 | W18: 0.057 | X18: 0.057
F19: 1978-1997 | G19: 1992 | I19: 0.057 | J19: 0.057 | K19: 0.057 | L19: 0.057 | M19: 0.057 | N19: 0.078 | O19: 0.078 | P19: 0.078 | Q19: 0.078 | R19: 0.078 | S19: 0.057 | T19: 0.057 | U19: 0.057 | V19: 0.057 | W19: 0.057 | X19: 0.057
F20: 1998-2007 | G20: 2001 | H20: Table 1-H | I20: 0.057 | J20: 0.057 | K20: 0.057 | L20: 0.057 | M20: 0.057 | N20: 0.078 | O20: 0.078 | P20: 0.078 | Q20: 0.078 | R20: 0.057 | S20: 0.057 | T20: 0.057 | U20: 0.057 | V20: 0.057 | W20: 0.057 | X20: 0.057
F21: 2008-2018 | G21: 2013 | H21: Table 140.3-B | I21: 0.049 | J21: 0.039 | K21: 0.039 | L21: 0.039 | M21: 0.049 | N21: 0.075 | O21: 0.067 | P21: 0.067 | Q21: 0.039 | R21: 0.039 | S21: 0.039 | T21: 0.039 | U21: 0.039 | V21: 0.039 | W21: 0.039 | X21: 0.039
F22: 2019+ | G22: 2025 | H22: Table 140.3-B | I22: 0.028 | J22: 0.028 | K22: 0.028 | L22: 0.028 | M22: 0.028 | N22: 0.047 | O22: 0.047 | P22: 0.047 | Q22: 0.028 | R22: 0.028 | S22: 0.028 | T22: 0.028 | U22: 0.028 | V22: 0.028 | W22: 0.028 | X22: 0.028
A23: Windows_ Guest Room (FloorM and FloorT) | B23: HotelLarge | C23: FixedWindow_GuestRoom | D23: CBECS 2018 shows that ~43% of Large Hotels that were built before 2000 are single pane | E23: U-factor IP | F23: Pre 1978 | G23: N/A | H23: ASHRAE Handbook of Fundamentals for single pane (Table 4-Ch15)& T24, 2013 for double pane (43%-57%) | I23: 0.6868 | J23: 0.6868 | K23: 0.6868 | L23: 0.6868 | M23: 0.6868 | N23: 0.6868 | O23: 0.6868 | P23: 0.6868 | Q23: 0.6868 | R23: 0.6868 | S23: 0.6868 | T23: 0.6868 | U23: 0.6868 | V23: 0.6868 | W23: 0.6868 | X23: 0.6868
F24: 1978-1997 | G24: N/A | I24: 0.6868 | J24: 0.6868 | K24: 0.6868 | L24: 0.6868 | M24: 0.6868 | N24: 0.6868 | O24: 0.6868 | P24: 0.6868 | Q24: 0.6868 | R24: 0.6868 | S24: 0.6868 | T24: 0.6868 | U24: 0.6868 | V24: 0.6868 | W24: 0.6868 | X24: 0.6868
D25: Double pane | F25: 1998-2007 | G25: 2001 | H25: Table 1-I | I25: 0.49 | J25: 0.49 | K25: 0.49 | L25: 0.49 | M25: 0.49 | N25: 0.49 | O25: 0.49 | P25: 0.49 | Q25: 0.49 | R25: 0.49 | S25: 0.49 | T25: 0.49 | U25: 0.49 | V25: 0.49 | W25: 0.49 | X25: 0.49
F26: 2008-2018 | G26: 2013 | H26: Table 140.3-C | I26: 0.36 | J26: 0.36 | K26: 0.36 | L26: 0.36 | M26: 0.36 | N26: 0.36 | O26: 0.36 | P26: 0.36 | Q26: 0.36 | R26: 0.36 | S26: 0.36 | T26: 0.36 | U26: 0.36 | V26: 0.36 | W26: 0.36 | X26: 0.36
F27: 2019+ | G27: 2025 | H27: Table 140.3-C | I27: 0.36 | J27: 0.36 | K27: 0.36 | L27: 0.36 | M27: 0.36 | N27: 0.36 | O27: 0.36 | P27: 0.36 | Q27: 0.36 | R27: 0.36 | S27: 0.36 | T27: 0.36 | U27: 0.36 | V27: 0.36 | W27: 0.36 | X27: 0.36
D28: CBECS 2018 shows that ~43% of Large Hotels that were built before 2000 are single pane | E28: SHGC | F28: Pre 1978 | G28: N/A | H28: ASHRAE Handbook of Fundamentals for single pane (Table 10-Ch15) & T24, 2013 for double pane (43%-57%) | I28: 0.4822 | J28: 0.4822 | K28: 0.4822 | L28: 0.4822 | M28: 0.4822 | N28: 0.4822 | O28: 0.4822 | P28: 0.4822 | Q28: 0.4822 | R28: 0.4822 | S28: 0.4822 | T28: 0.4822 | U28: 0.4822 | V28: 0.4822 | W28: 0.4822 | X28: 0.4822
F29: 1978-1997 | G29: N/A | I29: 0.4822 | J29: 0.4822 | K29: 0.4822 | L29: 0.4822 | M29: 0.4822 | N29: 0.4822 | O29: 0.4822 | P29: 0.4822 | Q29: 0.4822 | R29: 0.4822 | S29: 0.4822 | T29: 0.4822 | U29: 0.4822 | V29: 0.4822 | W29: 0.4822 | X29: 0.4822
D30: Double pane | F30: 1998-2007 | G30: 2001 | H30: TABLE 1-I (based on non north with WWR 30-40%) | I30: 0.3 | J30: 0.26 | K30: 0.26 | L30: 0.26 | M30: 0.26 | N30: 0.31 | O30: 0.31 | P30: 0.31 | Q30: 0.31 | R30: 0.26 | S30: 0.26 | T30: 0.26 | U30: 0.26 | V30: 0.26 | W30: 0.26 | X30: 0.3
F31: 2008-2018 | G31: 2013 | H31: Table 140.3-C | I31: 0.25 | J31: 0.25 | K31: 0.25 | L31: 0.25 | M31: 0.25 | N31: 0.25 | O31: 0.25 | P31: 0.25 | Q31: 0.25 | R31: 0.25 | S31: 0.25 | T31: 0.25 | U31: 0.25 | V31: 0.25 | W31: 0.25 | X31: 0.25
F32: 2019+ | G32: 2025 | H32: Table 140.3-C | I32: 0.25 | J32: 0.25 | K32: 0.25 | L32: 0.25 | M32: 0.25 | N32: 0.25 | O32: 0.25 | P32: 0.25 | Q32: 0.25 | R32: 0.25 | S32: 0.25 | T32: 0.25 | U32: 0.25 | V32: 0.25 | W32: 0.25 | X32: 0.25
A33: Windows_ Nonres (FloorG) | B33: HotelLarge | C33: FixedWindow_NonRes | D33: CBECS 2018 shows that ~43% of Large Hotels that were built before 2000 are single pane | E33: U-factor IP | F33: Pre 1978 | G33: N/A | H33: ASHRAE Handbook of Fundamentals for single pane (Table 4-Ch15)& T24, 2013 for double pane (43%-57%) | I33: 0.6868 | J33: 0.6868 | K33: 0.6868 | L33: 0.6868 | M33: 0.6868 | N33: 0.6868 | O33: 0.6868 | P33: 0.6868 | Q33: 0.6868 | R33: 0.6868 | S33: 0.6868 | T33: 0.6868 | U33: 0.6868 | V33: 0.6868 | W33: 0.6868 | X33: 0.6868
F34: 1978-1997 | G34: N/A | I34: 0.6868 | J34: 0.6868 | K34: 0.6868 | L34: 0.6868 | M34: 0.6868 | N34: 0.6868 | O34: 0.6868 | P34: 0.6868 | Q34: 0.6868 | R34: 0.6868 | S34: 0.6868 | T34: 0.6868 | U34: 0.6868 | V34: 0.6868 | W34: 0.6868 | X34: 0.6868
D35: Double pane | F35: 1998-2007 | G35: 2001 | H35: Table1-H | I35: 0.49 | J35: 0.49 | K35: 0.81 | L35: 0.81 | M35: 0.81 | N35: 0.81 | O35: 0.81 | P35: 0.81 | Q35: 0.81 | R35: 0.49 | S35: 0.49 | T35: 0.49 | U35: 0.49 | V35: 0.49 | W35: 0.49 | X35: 0.49
F36: 2008-2018 | G36: 2013 | H36: Table 140.3-B | I36: 0.36 | J36: 0.36 | K36: 0.36 | L36: 0.36 | M36: 0.36 | N36: 0.36 | O36: 0.36 | P36: 0.36 | Q36: 0.36 | R36: 0.36 | S36: 0.36 | T36: 0.36 | U36: 0.36 | V36: 0.36 | W36: 0.36 | X36: 0.36
F37: 2019+ | G37: 2025 | H37: Table 140.3-B | I37: 0.36 | J37: 0.36 | K37: 0.36 | L37: 0.36 | M37: 0.36 | N37: 0.36 | O37: 0.36 | P37: 0.36 | Q37: 0.34 | R37: 0.36 | S37: 0.34 | T37: 0.34 | U37: 0.34 | V37: 0.34 | W37: 0.34 | X37: 0.36
D38: CBECS 2018 shows that ~43% of Large Hotels that were built before 2000 are single pane | E38: SHGC | F38: Pre 1978 | G38: N/A | H38: ASHRAE Handbook of Fundamentals for single pane (Table 10-Ch15) & T24, 2013 for double pane (43%-57%) | I38: 0.4822 | J38: 0.4822 | K38: 0.4822 | L38: 0.4822 | M38: 0.4822 | N38: 0.4822 | O38: 0.4822 | P38: 0.4822 | Q38: 0.4822 | R38: 0.4822 | S38: 0.4822 | T38: 0.4822 | U38: 0.4822 | V38: 0.4822 | W38: 0.4822 | X38: 0.4822
F39: 1978-1997 | G39: N/A | I39: 0.4822 | J39: 0.4822 | K39: 0.4822 | L39: 0.4822 | M39: 0.4822 | N39: 0.4822 | O39: 0.4822 | P39: 0.4822 | Q39: 0.4822 | R39: 0.4822 | S39: 0.4822 | T39: 0.4822 | U39: 0.4822 | V39: 0.4822 | W39: 0.4822 | X39: 0.4822
D40: Double pane | F40: 1998-2007 | G40: 2001 | H40: Table 1-H (based on non north with WWR 30-40% ) | I40: 0.43 | J40: 0.31 | K40: 0.41 | L40: 0.41 | M40: 0.41 | N40: 0.34 | O40: 0.34 | P40: 0.34 | Q40: 0.34 | R40: 0.31 | S40: 0.31 | T40: 0.31 | U40: 0.31 | V40: 0.31 | W40: 0.31 | X40: 0.43
F41: 2008-2018 | G41: 2013 | H41: Table 140.3-B (100% fixed, 0% operable) | I41: 0.25 | J41: 0.25 | K41: 0.25 | L41: 0.25 | M41: 0.25 | N41: 0.25 | O41: 0.25 | P41: 0.25 | Q41: 0.25 | R41: 0.25 | S41: 0.25 | T41: 0.25 | U41: 0.25 | V41: 0.25 | W41: 0.25 | X41: 0.25
F42: 2019+ | G42: 2025 | H42: Table 140.3-B (100% fixed, 0% operable) | I42: 0.25 | J42: 0.25 | K42: 0.25 | L42: 0.25 | M42: 0.25 | N42: 0.25 | O42: 0.25 | P42: 0.25 | Q42: 0.22 | R42: 0.25 | S42: 0.22 | T42: 0.22 | U42: 0.22 | V42: 0.22 | W42: 0.22 | X42: 0.25
C44: Infiltration
D45: Building | E45: Zones | F45: Vintage | G45: I_75 (cfm/ft²) 6-sided Infiltration rate @ 75 pa | H45: Source | I45: I-design (cfm/ft²) (4-sided Infiltration rate at normal pressure) (Design flow rate approach and Flow/Exterior Wall Area calculation method)
C46: Infiltration | D46: HotelLarge | F46: Pre 1978 | G46: 1.1 | H46: 2022 CASE report (Table 38) | I46: 0.2606 | Z46: Floor or roof area (ft2) | AA46: 21300.06
F47: 1978-1997 | G47: 1.1 | H47: 2022 CASE report (Table 38) | I47: 0.2606 | Z47: Walls area (ft2) | AA47: 49079.02
F48: 1998-2007 | G48: 1.1 | H48: 2022 CASE report (Table 38) | I48: 0.2606 | Z48: Building 4 sided area (ft2) | AA48: 43333.57
F49: 2008-2018 | G49: 1* | H49: 2022 CASE report (Table 38) & T24, 2008-2016 (Table 140.3-C) | I49: 0.237 | Z49: Building 6 sided area (ft2) | AA49: =AA47+(2*AA46) -> 91679.14
F50: 2019+ | G50: 0.6** | H50: 2022 CASE report (Table 38) & T24,140.3(a)9Cii & T24, 2025 (Table 140.3-C) | I50: 0.1422
E51: Infiltration_rate_report_14May2025-Short-Version.docx
E52: * An air barrier was not required for guest rooms under T24, until the 2019 edition. However, to reflect typical construction practices, we assumed that all exterior walls are equipped with an air barrier where it was required for nonresidential walls.
E53: *** T24 require 0.4 cfm/ft² for tested condition but it also in section 140.3(a)9Cii says that if the air leakage requirements are not met, a visual inspection and diagnostic evaluation shall be completed , all observed leaks shall be sealed where such sealing can be made without destruction of existing building components, and buildings where the tested leakage rate exceeded 0.6 cfm/ft² of building shell area at 75 Pa have been retested to confirm leakage is below 0.6 cfm/ft² of building shell at 75 Pa. Although T24,2025 does not require guest rooms in Climate Zone 7 to have an air barrier, we assumed that all CZs are equipped with one. According to Dodge 2023 CAS data CZ 7 accounts for ~ 6% of hotel floor area in CA. Therefore, we have decided to ignore the exemption for CZ7 and treated all CZs as having an air barrier for consistency and ease of simulation.
E55: ACM 2025, 5.4.2: For Standard Design, I-design shall be 0.2352 cfm/ft². .Hotel/Motel Buildings in climate zone 7 and for relocatable public school buildings I-design shall be 0.3696 cfm/ft²

Sheet HVAC System
A1: ="HVAC System - "&Prototype!A2 -> HVAC System - HotelLarge
A2: Vintage | B2: Spaces | C2: Heating | D2: Cooling | E2: Air Distribution | F2: Other Systems | G2: Source | H2: Note
A3: Existing | B3: Common spaces | C3: Gas Boiler | D3: Air-cooled Chiller | E3: VAV + Hydronic reheat | F3: Economizer (only 2008-2018) No DOAS - OA through main VAV air handler | G3: CEUS 2022 (Other system based on T24 and Engineering judgement) | H3: Chiller is air cooled if the chiller capacity if below 300 ton as T24, 2025, section 170.2(c)4H (Page 563) banned having more than 300 ton of cooling provide by air cooled chiller.
B4: Guest rooms | C4: Gas Boiler | D4: Air-cooled Chiller | E4: FPFC (single speed fan) | F4: Exhaust-Only Ventilation | G4: CEUS 2022 (Other system based on Engineering judgement)
A5: New Construction | B5: Common spaces | C5: Gas Boiler | D5: Air-cooled Chiller | E5: VAV + Hydronic reheat | F5: Economizer No DOAS - OA through main VAV air handler | G5: ACM 2025, Table 2 and 3 (Other system based on Engineering judgement)
B6: Guest rooms | C6: Gas Boiler | D6: Air-cooled Chiller | E6: FPFC (multi speed fan) | F6: DOAS | G6: Engineering judgement with considering CEUS data
A11: Efficiency of HVAC System (Efficiency is capacity-dependent. The following table provides a general estimate of system efficiency based on preliminary simulations in one climate zone, or assuming cooling load based on rule of thumb)
A12: Vintage | B12: Upgrade/Installed year | C12: Gas Boiler | D12: Air Cooled Chiller | E12: Source | G12: Note
A13: Pre 1978 | B13: 2008 | C13: Thermal Efficiency of 80% Et | D13: EER=9.56 (COP=2.8) | E13: T24, 2008 Table 112-D (for chiller COP of 2.8 , then converted to EER of 9.56) - T24, 2013 Table 110.2-K (for boiler efficiency with capacity between 300,000-2,500,000 Btu/hr). T24 2008 doesn't has requirement for Et
A14: 1978-1997
A15: 1998-2007
A16: 2008-2018 | B16: 2013 | C16: Thermal Efficiency of 80% Et | D16: EER=9.56 | E16: T24, 2013 Table 110.2-D ( for air cooled chiller) T24, 2013 Table 110.2-K (for boiler efficiency with capacity between 300,000-2,500,000 Btu/hr)
A17: New Construction | B17: 2025 | C17: CZ: 7, 8, 15: Thermal Efficiency of 80% Et ; All other CZ: Thermal Efficiency of 90% Et and return water temp of 120F | D17: EER=9.7 | E17: T24, 2025 Table 110.2-D (path B) (for chiller) ACM, 2025, section (5.8.1) for number of boiler (2 boilers), and section (5.8.1) and 10CFR § 431.87 (for boiler efficiency in CZ 7, 8, 15) and Title 24, 2025 section 140.4(k)8 (for boiler efficiency in other CZs). The boiler capacity is assumed to be over 1 MMBtu based on engineering judgment, considering that the PNNL prototype in San Diego (CZ7, a mild climate) lists a boiler capacity of 0.85 MMBtu. Therefore, it is reasonable to expect a larger capacity—above 1 MMBtu—for CZ12, which has colder winters. | G17: According to T24, 2025 140.4(k)8 and ACM 2025, "Gas-fired boilers in climate zones 1 through 6, 9 through 14 and 16 with rated capacity above 1 MMBtu/h and less than 10 MMBtu/h have a standard design efficiency of 90 percent" For other climate zones, the efficiency of gas fired boiler is 80% following Federal regulation 10CFR § 431.87 *Note: efficiency of gas fired boiler was 84% in T24, 2022, Table 110.2-J for capacity between 300,000-2,500,000 Btu/hr for all CZs. The efficiency will be adjusted based on the results of a sizing simulation run, that shows us what the peak heating capacity requirements are. | O17: COP (2013)= | P17: =9.56/3.412 -> 2.8018757
O18: COP (2025)= | P18: =9.7/3.412 -> 2.8429074
P19: =10/3.412 -> 2.9308324
A22: Fan power
A23: Vintage | B23: Approach | C23: System | D23: Total Static Pressure (TSP) (in w.c.) | E23: Fan Efficiency [ACM 2025] | F23: Motor Efficiency | G23: Fan Power Index (W/cfm) | H23: Data Source | I23: Note
A24: Existing | B24: PNNL 90.1-2011, TSP | C24: VAV System > 4,648 cfm | D24: 5.58 | E24: 0.65 | F24: ASHRAE 90.1, 2004, Table 10.8 * | H24: Fan power formula: PNNL 20405, 2010, section 5.2.2.5 TSP and fan efficiency: PNNL 20405, 2010, Table 5.11, 90.1-04ac values Motor efficiency: ASHRAE 90.1, 2004, Table 10.8
C25: FPFC (on/off) | D25: 1.33 | E25: 0.65
A26: Brake horsepower (bhp) = (Supply cfm × TSP in w.c.) / (6356 × fan efficiency)
A27: Fan power (w/cfm) = (bhp × 746) / ( supply cfm × motor efficiency )
A28: New Construction | B28: ACM 2025 | C28: VAV (System 6), >10,000 cfm | D28: TSP = fan power × motor efficiency × fan efficiency × 6356 / 746 | E28: 0.65 | F28: 2025 ACM Table 12 ** | G28: 0.947 | H28: Fan power index: [ACM 2025, Table 13] Motor efficiency: [ACM 2025, Table 12] | I28: According to ACM, fan power for this cfm is 0.947 W/cfm (VAV >10,000 cfm). FPFC 0.35 and DOAS 0.70 rows are unchanged.
B29: ACM 2025 | C29: FPFC (on/off) | D29: TSP (E+ input) in w.c. = fan power in W/cfm × motor efficiency × fan efficiency × 6356 / 746 | F29: The full‑load efficiency of the motor serving the fan is taken from ACM 2025 Table 12 based on the cfm of the fan. Motor horsepower in hp = (Supply cfm from sizing run × fan power in W/cfm) / 746. | G29: 0.35 | H29: w/cfm: [T24, 2025, Section 140.4(a)3 D] | I29: 0.35 w/cfm for indoor unit fan
C30: DOAS Supply fan | G30: 0.7 | H30: w/cfm: [T24, 2025, Section 140.4(c) and Table 140.4-A] | I30: cfm of DOAS system is already calculated in the Ventilation sheet. Total cfm is more than 10,000 when 10% oversizing factor is applied - Supply 0.7 w/cfm= 0.325 (base allowance, >6 floors)+0.107 (MERV filter upstream of cooling coil) + 0.054 (central hydronic heating coil) + 0.107 (cooling coil) + 0.107 (100% OA allowance) DOAS OA ventilation rate is lower than guestroom's Exhaust fan rate. Therefore only one exhaust fan object will be model to each guestroom and DOAS exhaust fan will be excluded | J30: Total cfm of DOAS | K30: =1.1*Ventilation!J31 -> 14465
A32: * According to PNNL 20405 section 5.2.2.5, the full-load efficiency of the motor serving the fan is taken from ASHRAE 90.1, 2004, Table 10.8, based on motor nameplate and assuming enclosed motors operating at 1,800 rotations per minute (rpm) Motor nameplate size (bhp) = brake horsepower (bhp) × 1.1 ( using a 10% oversizing factor)
A33: ** The full‑load efficiency of the motor serving the fan is taken from ACM 2025 Table 12 based on the cfm of the fan. Brake horsepower (bhp) = (Supply cfm from sizing run × fan power in W/cfm) / 746.

Sheet Thermostat
A1: ="Thermostat Setpoints - "&Prototype!A2 -> Thermostat Setpoints - HotelLarge
A2: Setpoint | B2: CZ1 | C2: CZ2 | D2: CZ3 | E2: CZ4 | F2: CZ5 | G2: CZ6 | H2: CZ7 | I2: CZ8 | J2: CZ9 | K2: CZ10 | L2: CZ11 | M2: CZ12 | N2: CZ13 | O2: CZ14 | P2: CZ15 | Q2: CZ16 | R2: Source
A3: Assembly, Office, Basement, Retail, Dining and Café Heating Setpoint (F) | B3: 70 | C3: 70 | D3: 70 | E3: 70 | F3: 70 | G3: 70 | H3: 70 | I3: 70 | J3: 70 | K3: 70 | L3: 70 | M3: 70 | N3: 70 | O3: 70 | P3: 70 | Q3: 70 | R3: T24 2022 - Appendix 5.4B - “Assembly” tab , "Retail" tab, "Restaurant" Tab * Basement was considered similar to Office area
A4: Assembly, Office, Basement, Retail, Dining and Café Heating Setback (F) | B4: 60 | C4: 60 | D4: 60 | E4: 60 | F4: 60 | G4: 60 | H4: 60 | I4: 60 | J4: 60 | K4: 60 | L4: 60 | M4: 60 | N4: 60 | O4: 60 | P4: 60 | Q4: 60
A5: Assembly, Office, Basement, Retail, Dining and Café Cooling Setpoint (F) | B5: 75 | C5: 75 | D5: 75 | E5: 75 | F5: 75 | G5: 75 | H5: 75 | I5: 75 | J5: 75 | K5: 75 | L5: 75 | M5: 75 | N5: 75 | O5: 75 | P5: 75 | Q5: 75
A6: Assembly, Office, Basement, Retail, Dining and Café Cooling Setback (F) | B6: 85 | C6: 85 | D6: 85 | E6: 85 | F6: 85 | G6: 85 | H6: 85 | I6: 85 | J6: 85 | K6: 85 | L6: 85 | M6: 85 | N6: 85 | O6: 85 | P6: 85 | Q6: 85
A7: ResidentialCommon Heating Setpoint (F) | B7: 68 | C7: 68 | D7: 68 | E7: 68 | F7: 68 | G7: 68 | H7: 68 | I7: 68 | J7: 68 | K7: 68 | L7: 68 | M7: 68 | N7: 68 | O7: 68 | P7: 68 | Q7: 68 | R7: T24 2022 - Appendix 5.4B - “ResidentialCommon” tab
A8: ResidentialCommon Heating Setback (F) | B8: 68 | C8: 68 | D8: 68 | E8: 68 | F8: 68 | G8: 68 | H8: 68 | I8: 68 | J8: 68 | K8: 68 | L8: 68 | M8: 68 | N8: 68 | O8: 68 | P8: 68 | Q8: 68
A9: ResidentialCommon Cooling Setpoint (F) | B9: 78 | C9: 78 | D9: 78 | E9: 78 | F9: 78 | G9: 78 | H9: 68 | I9: 78 | J9: 78 | K9: 78 | L9: 78 | M9: 78 | N9: 78 | O9: 78 | P9: 78 | Q9: 78
A10: ResidentialCommon Cooling Setback (F) | B10: 78 | C10: 78 | D10: 78 | E10: 78 | F10: 78 | G10: 78 | H10: 78 | I10: 78 | J10: 78 | K10: 78 | L10: 78 | M10: 78 | N10: 78 | O10: 78 | P10: 78 | Q10: 78
A11: ResidentialLiving Heating Setpoint (F)* | B11: 70 | C11: 70 | D11: 70 | E11: 70 | F11: 70 | G11: 70 | H11: 70 | I11: 70 | J11: 70 | K11: 70 | L11: 70 | M11: 70 | N11: 70 | O11: 70 | P11: 70 | Q11: 70
A12: ResidentialLiving Heating Setback (F)* | B12: 70 | C12: 70 | D12: 70 | E12: 70 | F12: 70 | G12: 70 | H12: 70 | I12: 70 | J12: 70 | K12: 70 | L12: 70 | M12: 70 | N12: 70 | O12: 70 | P12: 70 | Q12: 70
A13: ResidentialLiving Cooling Setpoint (F)* | B13: 72 | C13: 72 | D13: 72 | E13: 72 | F13: 72 | G13: 72 | H13: 72 | I13: 72 | J13: 72 | K13: 72 | L13: 72 | M13: 72 | N13: 72 | O13: 72 | P13: 72 | Q13: 72 | R13: Honeywell-INNCOM e7 Thermostat User Guide
A14: ResidentialLiving Cooling Setback (F)* | B14: 72 | C14: 72 | D14: 72 | E14: 72 | F14: 72 | G14: 72 | H14: 72 | I14: 72 | J14: 72 | K14: 72 | L14: 72 | M14: 72 | N14: 72 | O14: 72 | P14: 72 | Q14: 72 | R14: & Engineering Judgment
A15: Kitchen Heating Setpoint (F) | B15: 66 | C15: 66 | D15: 66 | E15: 66 | F15: 66 | G15: 66 | H15: 66 | I15: 66 | J15: 66 | K15: 66 | L15: 66 | M15: 66 | N15: 66 | O15: 66 | P15: 66 | Q15: 66 | R15: PNNL 09.1, 2022 Restaurant prototype (Same as Kitchen area in Restaurant scorecards)
A16: Kitchen Heating Setback (F) | B16: 60 | C16: 60 | D16: 60 | E16: 60 | F16: 60 | G16: 60 | H16: 60 | I16: 60 | J16: 60 | K16: 60 | L16: 60 | M16: 60 | N16: 60 | O16: 60 | P16: 60 | Q16: 60
A17: Kitchen Cooling Setpoint (F) | B17: 79 | C17: 79 | D17: 79 | E17: 79 | F17: 79 | G17: 79 | H17: 79 | I17: 79 | J17: 79 | K17: 79 | L17: 79 | M17: 79 | N17: 79 | O17: 79 | P17: 79 | Q17: 79
A18: Kitchen Cooling Setback (F) | B18: 86 | C18: 86 | D18: 86 | E18: 86 | F18: 86 | G18: 86 | H18: 86 | I18: 86 | J18: 86 | K18: 86 | L18: 86 | M18: 86 | N18: 86 | O18: 86 | P18: 86 | Q18: 86
A19: Mechanical Room Heating Setpoint (F) | B19: 60 | C19: 60 | D19: 60 | E19: 60 | F19: 60 | G19: 60 | H19: 60 | I19: 60 | J19: 60 | K19: 60 | L19: 60 | M19: 60 | N19: 60 | O19: 60 | P19: 60 | Q19: 60 | R19: Based on engineering judgment (semi‑conditioned space)
A20: Mechanical Room Heating Setback (F) | B20: 60 | C20: 60 | D20: 60 | E20: 60 | F20: 60 | G20: 60 | H20: 60 | I20: 60 | J20: 60 | K20: 60 | L20: 60 | M20: 60 | N20: 60 | O20: 60 | P20: 60 | Q20: 60
A21: Mechanical Room Cooling Setpoint (F) | B21: 85 | C21: 85 | D21: 85 | E21: 85 | F21: 85 | G21: 85 | H21: 85 | I21: 85 | J21: 85 | K21: 85 | L21: 85 | M21: 85 | N21: 85 | O21: 85 | P21: 85 | Q21: 85
A22: Mechanical Room Cooling Setback (F) | B22: 85 | C22: 85 | D22: 85 | E22: 85 | F22: 85 | G22: 85 | H22: 85 | I22: 85 | J22: 85 | K22: 85 | L22: 85 | M22: 85 | N22: 85 | O22: 85 | P22: 85 | Q22: 85
A24: * 72°F is the default setting for one of the most prominent thermostat (INNCOM) in California hotels. We have chosen to set the heating setpoint close to this value, allowing only a 2°F variance, with no setback applied. Our understanding is that guests rarely change the setpoint when leaving their rooms, as they expect the room to remain conditioned upon their return.
A25: * Another option for the guest rooms would be: set heating and cooling setpoint at 72 F, with +-4F variation for C/H setback. ( based on INNCOM)
A26: ICCCOM has 4F setback temperature variance.
A27: PNNL's comfort range in kitchen is 4 F wider than CEC. CEC uses 70-75 F with setbacks of 60 F and 86 F but PNNL uses 66 -79 F (with setback of 60 F and 86 F)
A29: Existing prototypes:
A30: DEER has 60F for 0-6 am! It's the time that guest room is supposed to be occupied.
A31: PNNL has 70F for both cooling and heating setpoint with +-4 setback.
A43: Background Data [To be deleted prior to publication]
C45: DEER | I45: PNNL
A46: Why DEER had 85 for cooling from 0-5? | C46: Heating: 60 F Cooling: 85 C | E46: Heating: 70 F Cooling: 75 F Setback: +-10 | I46: Heating: 70 F Cooling: 70 F Setback:+-4 | L46: Heating: 60 F Cooling: 80 F | N46: Heating: 70 F Cooling: 75 F
C47: All guest room | E47: Corridors | G47: Lobby, Office, Laundry, Dining, barcasino | I47: Occupied guest room | L47: Vacant guest room | N47: Other space
A48: Heating setpoint | B48: Weekday | C48: 0 -6 ----> 60 6-22 --->68 22-24-->60 | E48: 0 -5 ------> 60 5-24 ----->70 | G48: 0-7----->60 7-23--->70 23-24--->60 | I48: 0:00-7:50 ------> 70 7:50-9:00------->66 9:00-10:50 ----->70 10:50-16:10---->66 16:10-17:50 --->70 17:50-19:00---->66 19:00-24:00---->70 | L48: 0-24 ----> 60 | N48: 0-24 ----> 70
B49: Saturday | E49: 0 -5 ------> 60 5-19------>70 19-24 --->60
B50: Sunday | E50: 60
A51: Cooling Setpoint | B51: Weekday | C51: 78 | E51: 0 -5 -----> 85 5-24 ---->75 | G51: 0-7----->85 7-23--->75 23-24--->85 | I51: 0:00-7:50 ------> 70 7:50-9:00------->74 9:00-10:50 ----->70 10:50-16:10---->74 16:10-17:50 --->70 17:50-19:00---->74 19:00-24:00---->70 | L51: 0-24 ----> 80 | N51: 0-24 ----> 75
B52: Saturday | E52: 0 -5 -----> 85 5-19----->75 19-24 --->85
B53: Sunday | E53: 85
A57: T24, Appendix JA5-4 : Occupant Controlled Smart Thermostat (OCST) | F57: Honeywell-INNCOM e7 Thermostat User Guide
A65: T24, 2025, 120.2 (E)-4
A68: T24, 2025, 120.2 (c).: Guest room occupants cannot adjust the setpoint more than ±5°F (±3°C)

Sheet Ventilation
A1: ="Outdoor Airflow Rate - "&Prototype!A2 -> Outdoor Airflow Rate - HotelLarge
A2: Space/Thermal Zone | B2: Number of People | C2: Floor Area (ft²) | D2: cfm/person (T24, 2025, Equation 120.1-F and Table 120.1-A) (ASHRAE 62.1, 2022, Table 6-1) only for guest rooms | E2: cfm/ft² (T24, 2025, Equation 120.1-F and Table 120.1-A) (ASHRAE 62.1, 2022, Table 6-1) only for guest rooms | F2: Required Exhaust Rate (T24, 2025, Table 120.1-B – Minimum Exhaust Rates) | G2: Total cfm Driven by People | H2: Total cfm Driven by Area | I2: Total cfm Driven by Exhaust | J2: Total cfm | K2: Note
A3: =Zones!B3 -> BasementConference | B3: =Zones!K3 -> 246.01293 | C3: =Zones!H3 -> 7454.9371 | D3: 15 | E3: 0.15 | F3: 2*50/70 per unit | G3: =B3*D3 -> 3690.1939 | H3: =C3*E3 -> 1118.2406 | I3: =2*70 -> 140 | J3: =MAX(G3,H3,I3) -> 3690.1939
A4: =Zones!B4 -> BasementOffice | B4: =Zones!K4 -> 8.2604979 | C4: =Zones!H4 -> 1652.0996 | D4: 15 | E4: 0.15 | G4: =B4*D4 -> 123.90747 | H4: =C4*E4 -> 247.81494 | J4: =MAX(G4,H4,I4) -> 247.81494
A5: =Zones!B5 -> BasementMechanical | B5: =Zones!K5 -> 0 | C5: =Zones!H5 -> 1767.854 | D5: 15 | E5: 0.15 | G5: =B5*D5 -> 0 | H5: =C5*E5 -> 265.1781 | J5: =MAX(G5,H5,I5) -> 265.1781
A6: =Zones!B6 -> BasementLaundry | B6: =Zones!K6 -> 4.2000525 | C6: =Zones!H6 -> 840.0105 | D6: 15 | E6: 0.15 | F6: 1 cfm/ft² for Soiled laundry storage rooms | G6: =B6*D6 -> 63.000788 | H6: =C6*E6 -> 126.00158 | I6: =1*0.2*C6 -> 168.0021 | J6: =MAX(G6,H6,I6) -> 168.0021 | K6: Only 20% of the laundry space is assumed as "Solied laundry storage room"
A7: =Zones!B7 -> BasementService | B7: =Zones!K7 -> 19.169838 | C7: =Zones!H7 -> 6389.9461 | D7: 15 | E7: 0.15 | F7: 0.7 cfm/sf | G7: =B7*D7 -> 287.54757 | H7: =C7*E7 -> 958.49192 | I7: =0.7*C7 -> 4472.9623 | J7: =MAX(G7,H7,I7) -> 4472.9623 | K7: Same as kitchen
A8: =Zones!B8 -> BasementStorage | B8: =Zones!K8 -> 0 | C8: =Zones!H8 -> 3194.9731 | D8: 15 | E8: 0.15 | G8: =B8*D8 -> 0 | H8: =C8*E8 -> 479.24596 | J8: =MAX(G8,H8,I8) -> 479.24596
A9: =Zones!B9 -> Retail_1_FloorG | B9: =Zones!K9 -> 12.272829 | C9: =Zones!H9 -> 721.93112 | D9: 15 | E9: 0.2 | G9: =B9*D9 -> 184.09243 | H9: =C9*E9 -> 144.38622 | J9: =MAX(G9,H9,I9) -> 184.09243
A10: =Zones!B10 -> Retail_2_FloorG | B10: =Zones!K10 -> 14.212474 | C10: =Zones!H10 -> 836.02788 | D10: 15 | E10: 0.2 | G10: =B10*D10 -> 213.18711 | H10: =C10*E10 -> 167.20558 | J10: =MAX(G10,H10,I10) -> 213.18711
A11: =Zones!B11 -> Office_FloorG | B11: =Zones!K11 -> 8.8392699 | C11: =Zones!H11 -> 1767.854 | D11: 15 | E11: 0.15 | G11: =B11*D11 -> 132.58905 | H11: =C11*E11 -> 265.1781 | J11: =MAX(G11,H11,I11) -> 265.1781
A12: =Zones!B12 -> Storage_FloorG | B12: =Zones!K12 -> 0 | C12: =Zones!H12 -> 1019.982 | D12: 15 | E12: 0.15 | G12: =B12*D12 -> 0 | H12: =C12*E12 -> 152.9973 | J12: =MAX(G12,H12,I12) -> 152.9973
A13: =Zones!B13 -> Kitchen_FloorG | B13: =Zones!K13 -> 2.5200315 | C13: =Zones!H13 -> 840.0105 | D13: 15 | E13: 0.15 | F13: 0.7 cfm/ft² for kitchen commercial | G13: =B13*D13 -> 37.800473 | H13: =C13*E13 -> 126.00158 | I13: =0.7*C13 -> 588.00735 | J13: =MAX(G13,H13,I13) -> 588.00735 | K13: 588 cm< hood exhaust cfm . It will be covered under hood cfm
A14: =Zones!B14 -> Cafe_FloorG | B14: =Zones!K14 -> 67.084375 | C14: =Zones!H14 -> 2032.8599 | D14: 15 | E14: 0.15 | G14: =B14*D14 -> 1006.2656 | H14: =C14*E14 -> 304.92898 | J14: =MAX(G14,H14,I14) -> 1006.2656
A15: =Zones!B15 -> Lobby_FloorG | B15: =Zones!K15 -> 140.81155 | C15: =Zones!H15 -> 14081.155 | D15: 15 | E15: 0.15 | G15: =B15*D15 -> 2112.1733 | H15: =C15*E15 -> 2112.1733 | J15: =MAX(G15,H15,I15) -> 2112.1733
A16: =Zones!B16 -> GuestRoom_1_FloorM | B16: =Zones!K16 -> 1.2600158 | C16: =Zones!H16 -> 420.00525 | D16: =5*10/3 -> 16.666667 | E16: 0.06 | F16: 20/50 cfm per unit | G16: =B16*D16 -> 21.000263 | H16: =C16*E16 -> 25.200315 | I16: 50 | J16: =MAX(G16+H16,I16) -> 50 | K16: Ventilation for guest rooms is calculated using the ASHRAE 62.1, as T24's occupancy-only baseline does not capture realistic ventilation design. The total outdoor airflow is calculated as: Ventilation = (Occupancy per 1,000 ft² × cfm/person) + (Floor area in ft² × cfm/ft²) To maintain simulation consistency across tabs and of ease of automation, we retained the T24 occupant rate of 3 occupants per 1,000 sq ft rather than adopting ASHRAE's higher rate of 10 occupants per 1,000 sq ft. To compensate for this, we scaled ASHRAE’s per-person airflow requirement (5 cfm/person) by a factor of 10/3. Although the occupant-based portion of the ventilation load remains almost equivalent across both codes, incorporating ASHRAE’s area-based ventilation component represents the key difference in overall outdoor air rates.
A17: =Zones!B17 -> GuestRoom_2_FloorM | B17: =Zones!K17 -> 1.2600158 | C17: =Zones!H17 -> 420.00525 | D17: =5*10/3 -> 16.666667 | E17: 0.06 | F17: 20/50 cfm per unit | G17: =B17*D17 -> 21.000263 | H17: =C17*E17 -> 25.200315 | I17: 50 | J17: =MAX(G17,H17,I17) -> 50
A18: =Zones!B18 -> GuestRoom_3_Multi19_FloorM | B18: =Zones!K18 -> 0.79178847 | C18: =Zones!H18 -> 263.92949 | D18: =5*10/3 -> 16.666667 | E18: 0.06 | F18: 20/50 cfm per unit | G18: =B18*D18 -> 13.196475 | H18: =C18*E18 -> 15.835769 | I18: 50 | J18: =MAX(G18,H18,I18) -> 50
A19: =Zones!B19 -> GuestRoom_4_Multi19_FloorM | B19: =Zones!K19 -> 0.79211139 | C19: =Zones!H19 -> 264.03713 | D19: =5*10/3 -> 16.666667 | E19: 0.06 | F19: 20/50 cfm per unit | G19: =B19*D19 -> 13.201856 | H19: =C19*E19 -> 15.842228 | I19: 50 | J19: =MAX(G19,H19,I19) -> 50
A20: =Zones!B20 -> GuestRoom_5_FloorM | B20: =Zones!K20 -> 1.2600158 | C20: =Zones!H20 -> 420.00525 | D20: =5*10/3 -> 16.666667 | E20: 0.06 | F20: 20/50 cfm per unit | G20: =B20*D20 -> 21.000263 | H20: =C20*E20 -> 25.200315 | I20: 50 | J20: =MAX(G20,H20,I20) -> 50
A21: =Zones!B21 -> GuestRoom_6_FloorM | B21: =Zones!K21 -> 1.2600158 | C21: =Zones!H21 -> 420.00525 | D21: =5*10/3 -> 16.666667 | E21: 0.06 | F21: 20/50 cfm per unit | G21: =B21*D21 -> 21.000263 | H21: =C21*E21 -> 25.200315 | I21: 50 | J21: =MAX(G21,H21,I21) -> 50
A22: =Zones!B22 -> Corridor_FloorM | B22: =Zones!K22 -> 20.957207 | C22: =Zones!H22 -> 4191.4414 | D22: 15 | E22: 0.15 | G22: =B22*D22 -> 314.35811 | H22: =C22*E22 -> 628.71622 | J22: =MAX(G22,H22,I22) -> 628.71622
A23: =Zones!B23 -> GuestRoom_1_FloorT | B23: =Zones!K23 -> 1.2600158 | C23: =Zones!H23 -> 420.00525 | D23: =5*10/3 -> 16.666667 | E23: 0.06 | F23: 20/50 cfm per unit | G23: =B23*D23 -> 21.000263 | H23: =C23*E23 -> 25.200315 | I23: 50 | J23: =MAX(G23,H23,I23) -> 50 | K23: Same explanation as other guestrooms (see the note above).
A24: =Zones!B24 -> GuestRoom_2_FloorT | B24: =Zones!K24 -> 1.2600158 | C24: =Zones!H24 -> 420.00525 | D24: =5*10/3 -> 16.666667 | E24: 0.06 | F24: 20/50 cfm per unit | G24: =B24*D24 -> 21.000263 | H24: =C24*E24 -> 25.200315 | I24: 50 | J24: =MAX(G24,H24,I24) -> 50
A25: =Zones!B25 -> GuestRoom_3_Multi9_FloorT | B25: =Zones!K25 -> 0.79211139 | C25: =Zones!H25 -> 264.03713 | D25: =5*10/3 -> 16.666667 | E25: 0.06 | F25: 20/50 cfm per unit | G25: =B25*D25 -> 13.201856 | H25: =C25*E25 -> 15.842228 | I25: 50 | J25: =MAX(G25,H25,I25) -> 50
A26: =Zones!B26 -> Banquet_FloorT | B26: =Zones!K26 -> 117.80792 | C26: =Zones!H26 -> 3569.937 | D26: 15 | E26: 0.15 | G26: =B26*D26 -> 1767.1188 | H26: =C26*E26 -> 535.49055 | J26: =MAX(G26,H26,I26) -> 1767.1188
A27: =Zones!B27 -> Dining_FloorT | B27: =Zones!K27 -> 117.80792 | C27: =Zones!H27 -> 3569.937 | D27: 15 | E27: 0.15 | G27: =B27*D27 -> 1767.1188 | H27: =C27*E27 -> 535.49055 | J27: =MAX(G27,H27,I27) -> 1767.1188
A28: =Zones!B28 -> Kitchen_FloorT | B28: =Zones!K28 -> 3.3357157 | C28: =Zones!H28 -> 1111.9052 | D28: 15 | E28: 0.15 | F28: 0.7 cfm/ft² for kitchen commercial | G28: =B28*D28 -> 50.035736 | H28: =C28*E28 -> 166.78579 | I28: =0.7*C28 -> 778.33367 | J28: =MAX(G28,H28,I28) -> 778.33367 | K28: 778 cm< hood exhaust cfm . It will be covered under hood cfm
A29: =Zones!B29 -> Corridor_FloorT | B29: =Zones!K29 -> 22.17998 | C29: =Zones!H29 -> 4435.996 | D29: 15 | E29: 0.15 | G29: =B29*D29 -> 332.6997 | H29: =C29*E29 -> 665.3994 | J29: =MAX(G29,H29,I29) -> 665.3994
I31: Total OA of guest rooms (cfm) | J31: =SUMPRODUCT(J16:J21,Zones!J16:J21)+SUMPRODUCT(J23:J25,Zones!J23:J25) -> 13150
A34: Type of Hood | C34: Max Exhaust Flow Rate (cfm/ft) [T24, 2025, Table 140.9-C] | D34: Hood Length (ft) * | E34: Hood Exhaust Rate (cfm) | F34: Note
A35: Kitchen FloorT: Type I , wall-mounted canopy, medium duty hood | C35: 210 | D35: 16 | E35: =C35*D35 -> 3360 | F35: Over fryers, griddles, broilers, or any equipment that produces grease and vapor
A36: Kitchen FloorG: Type I , wall-mounted canopy, medium duty hood | C36: 210 | D36: 11 | E36: =C36*D36 -> 2310 | F36: Over fryers, griddles, broilers, or any equipment that produces grease and vapor
A37: * Assuming a 6 ft long griddle space right next to a 4 ft long fryer space and a 2 ft Charbroiler and 2 ft range , that would be 6 + 4 + 2 + 2 + (0.5 ft x 2) or 15 ft long hood required, where the 0.5 ft is the 6 inches extending on either side of the cooking equipment. 1 extra ft has also been added as a buffer.
A38: ** Assuming a 4 ft griddle, 2 ft of warming/holding equipment, and 3 ft small fryer or oven . With 6‑inch hood overhangs on each end, the total hood length needed is approximately 10 ft. 1 extra ft has also been added as a buffer.
A40: Exhaust hood
A41: Efficiency of exhaust fan is 50% (according to ACM, 2025,section 5.7.3)
B42: A full‑service hotel kitchen serving a 7,000‑ft² restaurant and banquet space typically includes a multi‑appliance cookline: a griddle (3–6 ft), fryers (2–4 ft), Charbroiler (2–3 ft), range (2–3 ft), and a convection oven or holding equipment (2–3 ft). Placed side‑by‑side, these appliances require approximately 14–18 ft of linear hood coverage, including the mandatory 6‑inch overhang on each side. Therefore, a 16‑ft Type I hood represents a realistic and industry‑standard length for a restaurant/banquet cookline in a 1,100‑ft² hotel kitchen.
A44: Background Data [To be deleted prior to publication]
A47: T24, 2025, Table 140.9-C
A67: ACM 2025, Section 5.7.3, Exhaust fan efficiency
A84: ASHRAE 62.1 2022,
E85: Title 24, 2013 | J85: Title 24, 2008

Sheet Water Heater
A1: ="Water Heater - "&Prototype!A2 -> Water Heater - HotelLarge
A2: Vintage | B2: WH Type | C2: Efficiency | D2: Number of WH | E2: Tank Volume (gal) | F2: Tank Loss | G2: Source
A3: Existing | B3: Gas | C3: 0.8 | D3: =B40 -> 5 | E3: See table below for CZ-specific values: Climate Zone Water Heater Sizing and Loss Coefficients, Storage Volume column (col G) | F3: See table below: Climate Zone Water Heater Sizing and Loss Coefficients, Standby Loss column (col H) | G3: See table below for sources: Climate Zone Water Heater Sizing and Loss Coefficients
A4: New Construction | B4: Gas | C4: 0.8 | D4: 5 | E4: See table below for CZ-specific values: Climate Zone Water Heater Sizing and Loss Coefficients, Storage Volume column (col G) | F4: See table below: Climate Zone Water Heater Sizing and Loss Coefficients, Standby Loss column (col H) | G4: See table below for sources: Climate Zone Water Heater Sizing and Loss Coefficients
A8: Peak Hot Water Consumption
A9: Space Name | B9: Baseline WH Type [T24, 2022, Appendix 5.4A , sheet: "2022 SpaceFuncData-Input"] | C9: Total Area (ft²) | D9: Number of People | E9: Hot Water Usage Specification (gal/hr per person) [T24, 2022, Appendix 5.4A , sheet: "2022 SpaceFuncData-Input"] | F9: Peak Hot Water Usage (gal/hr) | G9: Peak Hot Water Usage (gal/min) | H9: Note
A10: =Zones!B3 -> BasementConference | B10: Gas | C10: =Zones!H3*Zones!J3 -> 7454.9371 | D10: =Zones!K3*Zones!J3 -> 246.01293 | E10: =Data!L84 -> 0.2724 | F10: =D10*E10 -> 67.013921 | G10: =F10/60 -> 1.1168987 | H10: For space types marked with an asterisk (the ‘*’ symbol), the water‑heater type is listed as electric in Appendix 5.4A, sheet ‘2022 SpaceFuncData‑Input.’ However, we modified the value based on CEUS data, which indicates that gas is the primary fuel type.
A11: =Zones!B4 -> BasementOffice | B11: Gas | C11: =Zones!H4*Zones!J4 -> 1652.0996 | D11: =Zones!K4*Zones!J4 -> 8.2604979 | E11: 0.18 | F11: =D11*E11 -> 1.4868896 | G11: =F11/60 -> 0.024781494
A12: =Zones!B5 -> BasementMechanical | B12: Gas | C12: =Zones!H5*Zones!J5 -> 1767.854 | D12: =Zones!K5*Zones!J5 -> 0 | E12: 0.18 | F12: =D12*E12 -> 0 | G12: =F12/60 -> 0
A13: =Zones!B6 -> BasementLaundry | B13: Gas | C13: =Zones!H6*Zones!J6 -> 840.0105 | D13: =Zones!K6*Zones!J6 -> 4.2000525 | E13: 0.58 | F13: =D13*E13 -> 2.4360305 | G13: =F13/60 -> 0.040600508
A14: =Zones!B7 -> BasementService | B14: Gas | C14: =Zones!H7*Zones!J7 -> 6389.9461 | D14: =Zones!K7*Zones!J7 -> 19.169838 | E14: 0.578 | F14: =D14*E14 -> 11.080167 | G14: =F14/60 -> 0.18466944
A15: =Zones!B8 -> BasementStorage | B15: Gas | C15: =Zones!H8*Zones!J8 -> 3194.9731 | D15: =Zones!K8*Zones!J8 -> 0 | E15: 0 | F15: =D15*E15 -> 0 | G15: =F15/60 -> 0
A16: =Zones!B9 -> Retail_1_FloorG | B16: Gas | C16: =Zones!H9*Zones!J9 -> 721.93112 | D16: =Zones!K9*Zones!J9 -> 12.272829 | E16: 0.18 | F16: =D16*E16 -> 2.2091092 | G16: =F16/60 -> 0.036818487
A17: =Zones!B10 -> Retail_2_FloorG | B17: Gas | C17: =Zones!H10*Zones!J10 -> 836.02788 | D17: =Zones!K10*Zones!J10 -> 14.212474 | E17: 0.18 | F17: =D17*E17 -> 2.5582453 | G17: =F17/60 -> 0.042637422
A18: =Zones!B11 -> Office_FloorG | B18: Gas | C18: =Zones!H11*Zones!J11 -> 1767.854 | D18: =Zones!K11*Zones!J11 -> 8.8392699 | E18: 0.18 | F18: =D18*E18 -> 1.5910686 | G18: =F18/60 -> 0.02651781
A19: =Zones!B12 -> Storage_FloorG | B19: - | C19: =Zones!H12*Zones!J12 -> 1019.982 | D19: =Zones!K12*Zones!J12 -> 0 | E19: 0 | F19: =D19*E19 -> 0 | G19: =F19/60 -> 0
A20: =Zones!B13 -> Kitchen_FloorG | B20: Gas | C20: =Zones!H13*Zones!J13 -> 840.0105 | D20: =Zones!K13*Zones!J13 -> 2.5200315 | E20: 0.578 | F20: =D20*E20 -> 1.4565782 | G20: =F20/60 -> 0.024276304
A21: =Zones!B14 -> Cafe_FloorG | B21: Gas | C21: =Zones!H14*Zones!J14 -> 2032.8599 | D21: =Zones!K14*Zones!J14 -> 67.084375 | E21: 0.578 | F21: =D21*E21 -> 38.774769 | G21: =F21/60 -> 0.64624615
A22: =Zones!B15 -> Lobby_FloorG | B22: Gas | C22: =Zones!H15*Zones!J15 -> 14081.155 | D22: =Zones!K15*Zones!J15 -> 140.81155 | E22: 0.09 | F22: =D22*E22 -> 12.67304 | G22: =F22/60 -> 0.21121733
... A35: =Zones!B28 -> Kitchen_FloorT | B35: Gas | C35: =Zones!H28*Zones!J28 -> 1111.9052 | D35: =Zones!K28*Zones!J28 -> 3.3357157 | E35: 0.578 | F35: =D35*E35 -> 1.9280437 | G35: =F35/60 -> 0.032134061
A36: =Zones!B29 -> Corridor_FloorT | C36: =Zones!H29*Zones!J29 -> 4435.996 | D36: =Zones!K29*Zones!J29 -> 22.17998 | E36: 0 | F36: =D36*E36 -> 0 | G36: =F36/60 -> 0
A37: Total | B37: Gas storage | F37: =_xlfn.LET( _xlpm.g,SUMIF($B$10:$B$36,"Gas*",$F$10:$F$36), _xlpm.e,SUMIF($B$10:$B$36,"Electric*",$F$10:$F$36), IF(AND(_xlpm.g>0,_xlpm.e>0),_xlpm.g,IF(_xlpm.g>0,MAX(75,_xlpm.g),0))) -> 1267.0277 | H37: Minimum peak hot water usage is 75 gal according to ACM 2025
A38: Total | B38: Electric resistance | F38: =_xlfn.LET( _xlpm.g,SUMIF($B$10:$B$36,"Gas*",$F$10:$F$36), _xlpm.e,SUMIF($B$10:$B$36,"Electric*",$F$10:$F$36), IF(AND(_xlpm.g>0,_xlpm.e>0),_xlpm.e,IF(_xlpm.e>0,MAX(75,_xlpm.e),0))) -> 0
A40: Number of identical water heaters | B40: =MAX(1,ROUNDUP(MAX(30,$F$37*$B$45)/MAX($E$69:$E$87),0)) -> 5 | C40: N identical catalog heaters. Loss table (D–J) is per heater.
A41: heat capacity of water (BTU/hr-F) | B41: 1 | E41: =F37*(135-C48)*8.3*0.6 -> 549583.41
A42: Design supply temperature (°F) | B42: 135 | C42: CEC-400-2022-009-CMF-REV2-AP5.4B | E42: =110*5 -> 550
A43: WH system factor | B43: 0.6 | C43: 2025 ACM §5.9.2 Rated Capacity
A44: Water mass conversion (lb/gal) | B44: 8.2877 | C44: 2025 ACM §5.9.2 Rated Capacity
A45: Reheat multiplier | B45: 0.4 | C45: 2025 ACM §5.9.2 Storage Volume
A46: Climate Zone Water Heater Sizing and Loss Coefficients (Individual WH)
A47: Water Heater Name | B47: Climate Zone | C47: Minimum Monthly Mains Temp (°F) [T24 2022 - Appendix 5.4B] | D47: Heat Output (Btu/hr) [ACM, 2025, 5.9.2: Rated capacity section] | E47: WH Capacity (Btu/hr) [ACM, 2025, 5.9.2: Rated capacity section] | F47: Required Energy Input (Btu/hr) | G47: Storage Volume (gal) | H47: Standby Loss [Title 20, §1605.1 Table F-4; Appendix B: Water Heating Calculation Method] | J47: Off/On Cycle Loss Coefficient to Ambient Temp | L47: Source/Note
A48: WH_HotelLarge | B48: CZ01 | C48: 47.9 | D48: =$F$37/$B$40*($B$42-C48)*$B$44 -> 182922.99 | E48: =D48*$B$43 -> 109753.79 | F48: =_xlfn.LET(_xlpm.x,_xlfn.XLOOKUP(E48/$C$3,$A$69:$A$99,$A$69:$A$99,"",1),IF(_xlpm.x="",ROUNDUP(E48/$C$3,0),_xlpm.x)) -> 145000 | G48: {=_xlfn.LET(_xlpm.v,MAX(30,$F$37/$B$40*$B$45),_xlpm.x,_xlfn.XLOOKUP(_xlpm.v,$E$69:$E$87,$E$69:$E$87,"",1),IF(_xlpm.x="",ROUNDUP(_xlpm.v,0),_xlpm.x))} -> 110 | H48: =(F48/800)+110*SQRT(G48) -> 1334.9397 | I48: Btu/hr | J48: =H48/70 -> 19.070568 | K48: Btu/h·°F | L48: Required Energy Input: vendor/available catalog size (Market data table). Storage Volume: standard/available catalog tank size (Market data table).
A49: WH_HotelLarge | B49: CZ02 | C49: 50.8 | D49: =$F$37/$B$40*($B$42-C49)*$B$44 -> 176832.56 | E49: =D49*$B$43 -> 106099.53 | F49: =_xlfn.LET(_xlpm.x,_xlfn.XLOOKUP(E49/$C$3,$A$69:$A$99,$A$69:$A$99,"",1),IF(_xlpm.x="",ROUNDUP(E49/$C$3,0),_xlpm.x)) -> 145000 | G49: =_xlfn.LET(_xlpm.v,MAX(30,$F$37/$B$40*$B$45),_xlpm.x,_xlfn.XLOOKUP(_xlpm.v,$E$69:$E$87,$E$69:$E$87,"",1),IF(_xlpm.x="",ROUNDUP(_xlpm.v,0),_xlpm.x)) -> 110 | H49: =(F49/800)+110*SQRT(G49) -> 1334.9397 | I49: Btu/hr | J49: =H49/70 -> 19.070568 | K49: Btu/h·°F
A50: WH_HotelLarge | B50: CZ03 | C50: 52.2 | D50: =$F$37/$B$40*($B$42-C50)*$B$44 -> 173892.35 | E50: =D50*$B$43 -> 104335.41 | F50: =_xlfn.LET(_xlpm.x,_xlfn.XLOOKUP(E50/$C$3,$A$69:$A$99,$A$69:$A$99,"",1),IF(_xlpm.x="",ROUNDUP(E50/$C$3,0),_xlpm.x)) -> 145000 | G50: =_xlfn.LET(_xlpm.v,MAX(30,$F$37/$B$40*$B$45),_xlpm.x,_xlfn.XLOOKUP(_xlpm.v,$E$69:$E$87,$E$69:$E$87,"",1),IF(_xlpm.x="",ROUNDUP(_xlpm.v,0),_xlpm.x)) -> 110 | H50: =(F50/800)+110*SQRT(G50) -> 1334.9397 | I50: Btu/hr | J50: =H50/70 -> 19.070568 | K50: Btu/h·°F
A51: WH_HotelLarge | B51: CZ04 | C51: 52.7 | D51: =$F$37/$B$40*($B$42-C51)*$B$44 -> 172842.27 | E51: =D51*$B$43 -> 103705.36 | F51: =_xlfn.LET(_xlpm.x,_xlfn.XLOOKUP(E51/$C$3,$A$69:$A$99,$A$69:$A$99,"",1),IF(_xlpm.x="",ROUNDUP(E51/$C$3,0),_xlpm.x)) -> 130000 | G51: =_xlfn.LET(_xlpm.v,MAX(30,$F$37/$B$40*$B$45),_xlpm.x,_xlfn.XLOOKUP(_xlpm.v,$E$69:$E$87,$E$69:$E$87,"",1),IF(_xlpm.x="",ROUNDUP(_xlpm.v,0),_xlpm.x)) -> 110 | H51: =(F51/800)+110*SQRT(G51) -> 1316.1897 | I51: Btu/hr | J51: =H51/70 -> 18.80271 | K51: Btu/h·°F
A52: WH_HotelLarge | B52: CZ05 | C52: 51.6 | D52: =$F$37/$B$40*($B$42-C52)*$B$44 -> 175152.44 | E52: =D52*$B$43 -> 105091.46 | F52: =_xlfn.LET(_xlpm.x,_xlfn.XLOOKUP(E52/$C$3,$A$69:$A$99,$A$69:$A$99,"",1),IF(_xlpm.x="",ROUNDUP(E52/$C$3,0),_xlpm.x)) -> 145000 | G52: =_xlfn.LET(_xlpm.v,MAX(30,$F$37/$B$40*$B$45),_xlpm.x,_xlfn.XLOOKUP(_xlpm.v,$E$69:$E$87,$E$69:$E$87,"",1),IF(_xlpm.x="",ROUNDUP(_xlpm.v,0),_xlpm.x)) -> 110 | H52: =(F52/800)+110*SQRT(G52) -> 1334.9397 | I52: Btu/hr | J52: =H52/70 -> 19.070568 | K52: Btu/h·°F
A53: WH_HotelLarge | B53: CZ06 | C53: 56.8 | D53: =$F$37/$B$40*($B$42-C53)*$B$44 -> 164231.66 | E53: =D53*$B$43 -> 98538.997 | F53: =_xlfn.LET(_xlpm.x,_xlfn.XLOOKUP(E53/$C$3,$A$69:$A$99,$A$69:$A$99,"",1),IF(_xlpm.x="",ROUNDUP(E53/$C$3,0),_xlpm.x)) -> 125000 | G53: =_xlfn.LET(_xlpm.v,MAX(30,$F$37/$B$40*$B$45),_xlpm.x,_xlfn.XLOOKUP(_xlpm.v,$E$69:$E$87,$E$69:$E$87,"",1),IF(_xlpm.x="",ROUNDUP(_xlpm.v,0),_xlpm.x)) -> 110 | H53: =(F53/800)+110*SQRT(G53) -> 1309.9397 | I53: Btu/hr | J53: =H53/70 -> 18.713425 | K53: Btu/h·°F
A54: WH_HotelLarge | B54: CZ07 | C54: 58.4 | D54: =$F$37/$B$40*($B$42-C54)*$B$44 -> 160871.42 | E54: =D54*$B$43 -> 96522.854 | F54: =_xlfn.LET(_xlpm.x,_xlfn.XLOOKUP(E54/$C$3,$A$69:$A$99,$A$69:$A$99,"",1),IF(_xlpm.x="",ROUNDUP(E54/$C$3,0),_xlpm.x)) -> 125000 | G54: =_xlfn.LET(_xlpm.v,MAX(30,$F$37/$B$40*$B$45),_xlpm.x,_xlfn.XLOOKUP(_xlpm.v,$E$69:$E$87,$E$69:$E$87,"",1),IF(_xlpm.x="",ROUNDUP(_xlpm.v,0),_xlpm.x)) -> 110 | H54: =(F54/800)+110*SQRT(G54) -> 1309.9397 | I54: Btu/hr | J54: =H54/70 -> 18.713425 | K54: Btu/h·°F
A55: WH_HotelLarge | B55: CZ08 | C55: 58.4 | D55: =$F$37/$B$40*($B$42-C55)*$B$44 -> 160871.42 | E55: =D55*$B$43 -> 96522.854 | F55: =_xlfn.LET(_xlpm.x,_xlfn.XLOOKUP(E55/$C$3,$A$69:$A$99,$A$69:$A$99,"",1),IF(_xlpm.x="",ROUNDUP(E55/$C$3,0),_xlpm.x)) -> 125000 | G55: =_xlfn.LET(_xlpm.v,MAX(30,$F$37/$B$40*$B$45),_xlpm.x,_xlfn.XLOOKUP(_xlpm.v,$E$69:$E$87,$E$69:$E$87,"",1),IF(_xlpm.x="",ROUNDUP(_xlpm.v,0),_xlpm.x)) -> 110 | H55: =(F55/800)+110*SQRT(G55) -> 1309.9397 | I55: Btu/hr | J55: =H55/70 -> 18.713425 | K55: Btu/h·°F
A56: WH_HotelLarge | B56: CZ09 | C56: 57.6 | D56: =$F$37/$B$40*($B$42-C56)*$B$44 -> 162551.54 | E56: =D56*$B$43 -> 97530.926 | F56: =_xlfn.LET(_xlpm.x,_xlfn.XLOOKUP(E56/$C$3,$A$69:$A$99,$A$69:$A$99,"",1),IF(_xlpm.x="",ROUNDUP(E56/$C$3,0),_xlpm.x)) -> 125000 | G56: =_xlfn.LET(_xlpm.v,MAX(30,$F$37/$B$40*$B$45),_xlpm.x,_xlfn.XLOOKUP(_xlpm.v,$E$69:$E$87,$E$69:$E$87,"",1),IF(_xlpm.x="",ROUNDUP(_xlpm.v,0),_xlpm.x)) -> 110 | H56: =(F56/800)+110*SQRT(G56) -> 1309.9397 | I56: Btu/hr | J56: =H56/70 -> 18.713425 | K56: Btu/h·°F
A57: WH_HotelLarge | B57: CZ10 | C57: 57.1 | D57: =$F$37/$B$40*($B$42-C57)*$B$44 -> 163601.62 | E57: =D57*$B$43 -> 98160.97 | F57: =_xlfn.LET(_xlpm.x,_xlfn.XLOOKUP(E57/$C$3,$A$69:$A$99,$A$69:$A$99,"",1),IF(_xlpm.x="",ROUNDUP(E57/$C$3,0),_xlpm.x)) -> 125000 | G57: =_xlfn.LET(_xlpm.v,MAX(30,$F$37/$B$40*$B$45),_xlpm.x,_xlfn.XLOOKUP(_xlpm.v,$E$69:$E$87,$E$69:$E$87,"",1),IF(_xlpm.x="",ROUNDUP(_xlpm.v,0),_xlpm.x)) -> 110 | H57: =(F57/800)+110*SQRT(G57) -> 1309.9397 | I57: Btu/hr | J57: =H57/70 -> 18.713425 | K57: Btu/h·°F
A58: WH_HotelLarge | B58: CZ11 | C58: 50.5 | D58: =$F$37/$B$40*($B$42-C58)*$B$44 -> 177462.6 | E58: =D58*$B$43 -> 106477.56 | F58: =_xlfn.LET(_xlpm.x,_xlfn.XLOOKUP(E58/$C$3,$A$69:$A$99,$A$69:$A$99,"",1),IF(_xlpm.x="",ROUNDUP(E58/$C$3,0),_xlpm.x)) -> 145000 | G58: =_xlfn.LET(_xlpm.v,MAX(30,$F$37/$B$40*$B$45),_xlpm.x,_xlfn.XLOOKUP(_xlpm.v,$E$69:$E$87,$E$69:$E$87,"",1),IF(_xlpm.x="",ROUNDUP(_xlpm.v,0),_xlpm.x)) -> 110 | H58: =(F58/800)+110*SQRT(G58) -> 1334.9397 | I58: Btu/hr | J58: =H58/70 -> 19.070568 | K58: Btu/h·°F
A59: WH_HotelLarge | B59: CZ12 | C59: 51.4 | D59: =$F$37/$B$40*($B$42-C59)*$B$44 -> 175572.47 | E59: =D59*$B$43 -> 105343.48 | F59: =_xlfn.LET(_xlpm.x,_xlfn.XLOOKUP(E59/$C$3,$A$69:$A$99,$A$69:$A$99,"",1),IF(_xlpm.x="",ROUNDUP(E59/$C$3,0),_xlpm.x)) -> 145000 | G59: =_xlfn.LET(_xlpm.v,MAX(30,$F$37/$B$40*$B$45),_xlpm.x,_xlfn.XLOOKUP(_xlpm.v,$E$69:$E$87,$E$69:$E$87,"",1),IF(_xlpm.x="",ROUNDUP(_xlpm.v,0),_xlpm.x)) -> 110 | H59: =(F59/800)+110*SQRT(G59) -> 1334.9397 | I59: Btu/hr | J59: =H59/70 -> 19.070568 | K59: Btu/h·°F
A60: WH_HotelLarge | B60: CZ13 | C60: 51.7 | D60: =$F$37/$B$40*($B$42-C60)*$B$44 -> 174942.42 | E60: =D60*$B$43 -> 104965.45 | F60: =_xlfn.LET(_xlpm.x,_xlfn.XLOOKUP(E60/$C$3,$A$69:$A$99,$A$69:$A$99,"",1),IF(_xlpm.x="",ROUNDUP(E60/$C$3,0),_xlpm.x)) -> 145000 | G60: =_xlfn.LET(_xlpm.v,MAX(30,$F$37/$B$40*$B$45),_xlpm.x,_xlfn.XLOOKUP(_xlpm.v,$E$69:$E$87,$E$69:$E$87,"",1),IF(_xlpm.x="",ROUNDUP(_xlpm.v,0),_xlpm.x)) -> 110 | H60: =(F60/800)+110*SQRT(G60) -> 1334.9397 | I60: Btu/hr | J60: =H60/70 -> 19.070568 | K60: Btu/h·°F
... A63: WH_HotelLarge | B63: CZ16 | C63: 41.4 | D63: =$F$37/$B$40*($B$42-C63)*$B$44 -> 196573.96 | E63: =D63*$B$43 -> 117944.38 | F63: =_xlfn.LET(_xlpm.x,_xlfn.XLOOKUP(E63/$C$3,$A$69:$A$99,$A$69:$A$99,"",1),IF(_xlpm.x="",ROUNDUP(E63/$C$3,0),_xlpm.x)) -> 150000 | G63: =_xlfn.LET(_xlpm.v,MAX(30,$F$37/$B$40*$B$45),_xlpm.x,_xlfn.XLOOKUP(_xlpm.v,$E$69:$E$87,$E$69:$E$87,"",1),IF(_xlpm.x="",ROUNDUP(_xlpm.v,0),_xlpm.x)) -> 110 | H63: =(F63/800)+110*SQRT(G63) -> 1341.1897 | I63: Btu/hr | J63: =H63/70 -> 19.159853 | K63: Btu/h·°F
A67: Market data
A68: Catalog gas input (Btu/h) | B68: Input source | C68: Elec resistance tank (kW) | D68: Elec resistance (Btu/h) | E68: Catalog gas tank (gal) | F68: Tank source | G68: Elec tank (gal) | H68: Elec tank source | I68: =HYPERLINK("#'Note'!A1","Sources and links → Note tab") -> Sources and links → Note tab
A69: 60000 | B69: Grainger | C69: 1.5 | D69: 5118 | E69: 34 | F69: ENERGY STAR | G69: 6 | H69: Grainger
A70: 75100 | B70: Grainger | C70: 2 | D70: 6824 | E70: 35 | F70: Grainger | G70: 10 | H70: Grainger
A71: 76000 | B71: Both | C71: 3 | D71: 10236 | E71: 48 | F71: Grainger | G71: 15 | H71: Grainger
A72: 80000 | B72: Grainger | C72: 4.5 | D72: 15355 | E72: 50 | F72: Both | G72: 20 | H72: Grainger
A73: 99900 | B73: ENERGY STAR | C73: 6 | D73: 20473 | E73: 55 | F73: ENERGY STAR | G73: 28 | H73: Grainger
A74: 100000 | B74: Both | C74: 8 | D74: 27297 | E74: 60 | F74: ENERGY STAR | G74: 30 | H74: Grainger
A75: 120000 | B75: ENERGY STAR | C75: 9 | D75: 30709 | E75: 65 | F75: Both | G75: 36 | H75: Grainger
A76: 125000 | B76: Both | C76: 10 | D76: 34121 | E76: 72 | F76: Grainger | G76: 40 | H76: Grainger
A77: 130000 | B77: Both | C77: 12 | D77: 40946 | E77: 75 | F77: Both | G77: 47
A78: 145000 | B78: ENERGY STAR | C78: 12.1 | D78: 41287 | E78: 76 | F78: Grainger | G78: 50
A79: 150000 | B79: ENERGY STAR | C79: 18 | D79: 61419 | E79: 80 | F79: Both | G79: 65
A80: 156000 | B80: Grainger | C80: 24 | D80: 81891 | E80: 82 | F80: Grainger | G80: 80
A81: 160000 | B81: Both | C81: 27 | D81: 92128 | E81: 85 | F81: Grainger | G81: 85
A82: 175000 | B82: ENERGY STAR | C82: 36 | D82: 122837 | E82: 90 | F82: Both | G82: 105
A83: 180000 | B83: Grainger | C83: 54 | D83: 184256 | E83: 91 | F83: Grainger | G83: 120
A84: 199000 | B84: ENERGY STAR | E84: 100 | F84: Both
A85: 199900 | B85: Both | E85: 110 | F85: ENERGY STAR
A86: 200000 | B86: ENERGY STAR | E86: 119 | F86: Both
A87: 250000 | B87: Both | E87: 125 | F87: ENERGY STAR
A88: 251000 | B88: ENERGY STAR
A89: 270000 | B89: Grainger
A90: 285000 | B90: ENERGY STAR
A91: 300000 | B91: Both
A92: 320000 | B92: ENERGY STAR
A93: 360000 | B93: Grainger
A94: 398000 | B94: ENERGY STAR
A95: 399000 | B95: ENERGY STAR
A96: 399900 | B96: Both
A97: 499900 | B97: Grainger
A98: 550000 | B98: Grainger
A99: 715000 | B99: Grainger
A170: 2023 ASHRAE Handbook—HVAC Applications, section 51.20
A181: 12gal per bath

Sheet Interior Lights
A1: ="Interior Lighting - "&Prototype!A2 -> Interior Lighting - HotelLarge
A2: Space Type | B2: New Construction | E2: Existing | H2: Note
B3: LPD (W/ft²) | C3: Additional LPD for Portable Lighting (W/ft²) | D3: Source | E3: LPD (W/ft²) | F3: Additional LPD for Portable Lighting (W/ft²) | G3: Source
A4: Convention, Conference, Multipurpose and Meeting Area | B4: =Data!I84 -> 0.7275 | C4: 0.25 | D4: T24, 2025, Table 140.6-C PNNL ASHRAE 90.1 2022 for Guest Room, same as ASHRAE 90.1 2025 (Area category method) | E4: =Data!J84 -> 0.7725 | G4: T24, 2019*, Table 140.6-C (Area category method) Guest rooms: ASHRAE 90.1 2016, Table 9.6.1 (It's been assumed that guest rooms have a longer lighting replacement cycle compared to other space types) | H4: Weighted LPD is used as basement is considered to be a mix of multiple spaces.
A5: Office Area (>250 square feet) | B5: 0.6 | C5: 0.1 | E5: 0.7 | H5: Based on engineering judgement as it's being added to general LPD
A6: Service and back up prep | B6: 0.95 | E6: 0.95 | H6: Engineering judgement, same as kitchen lighting
A7: Retail Sales Area (Retail Merchandise Sales) | B7: 0.95 | C7: 0.1 | E7: 1 | H7: Additional Lighting for New construction: General Lighting in the enclosed space of ceiling height > 10’
A8: Electrical, Mechanical, Telephone Rooms | B8: 0.4 | E8: =B8+2 -> 2.4
A9: Storage (General) | B9: 0.4 | E9: 0.4 | H9: LPD of "All other spaces" is considered for storage
A10: Laundry Area | B10: 0.45 | E10: 0.45
A11: Dining Area (Cafeteria/Fast Food) | B11: =B16 -> 0.45 | C11: 0.25 | E11: 0.55 | H11: LPD of "Bar/Lounge and Fine Dining Area"
A12: Lobby, Main Entry | B12: 0.7 | C12: 0.25 | E12: 0.85 | F12: 0.5
A13: Hotel/Motel Guest Room | B13: 0.41 | E13: 0.77 | H13: Originally existing LPD for guest room was 1.27 (according to CBECC 2019) but it then updated to 0.41, to align the LPF of New Construction
A14: Corridor Area | B14: 0.4 | E14: 0.6
A15: Hotel Function Area | B15: 0.85 | E15: 0.85 | H15: Space type: Hotel Function Area
A16: Dining Area (Bar/Lounge and Fine Dining) | B16: 0.45 | E16: =E11 -> 0.55 | H16: LPD of "Bar/Lounge and Fine Dining Area"
A17: Kitchen/Food Preparation Area | B17: 0.95 | E17: 0.95
A19: *Hotels are expected to update their lighting systems more frequently than offices. Therefore code edition of 2019 was considered as the reference for LPD of the existing prototypes.
A25: ASHRAE 90.1 2016

Sheet Ext Lighting
A1: ="Exterior Lighting - "&Prototype!A2 -> Exterior Lighting - HotelLarge
A2: Vintage | B2: Motion Controlled Luminaires (W) | C2: Non-motion Controlled Luminaires (W) | D2: Total (W) | E2: Source
A3: Existing | B3: =J17 -> 4581.8328 | C3: =J18 -> 1184.7445 | D3: =C3+B3 -> 5766.5773 | E3: T24, 2022 & 2025 2019 Outdoor Lighting CASE report PNNL 90.1-2010 TSD
A4: New Construction | B4: =G17 -> 3676.7176 | C4: =G18 -> 1184.7445 | D4: =C4+B4 -> 4861.4621 | E4: T24, 2022 & 2025 2019 Outdoor Lighting CASE report PNNL 90.1-2010 TSD
A8: Exterior Lighting
A9: Items (Assume LZ2) | B9: Assumptions [2019 Outdoor Lighting CASE Report & PNNL 90.1-2010 TSD] | D9: Unit | E9: New Construction | H9: Existing
E10: Lighting Power Allowance [T24, 2025, Table 140.7-A & 140.7-B] | F10: Unit | G10: Exterior Lighting Power (W) New Construction | H10: Lighting Power Allowance [T24, 2019, Table 140.7-A & 140.7-B] | I10: Unit | J10: Exterior Lighting Power (W) Existing
A11: IWA (Initial Wage Allowance) | E11: 200 | F11: (W) | G11: =$E11 -> 200 | H11: 250 | I11: (W) | J11: =$H11 -> 250
A12: Parking area | B12: 400 ft² for every parking space [2019 Lighting CASE report, Appendix H] 1 parking space per 360 ft² of gross building area [2019 Lighting CASE report,Table 38] | C12: =B24/360*400 -> 171023.03 | D12: (ft²) | E12: 0.019 | F12: (W/ft²) | G12: =$E12*C12 -> 3249.4376 | H12: 0.024 | I12: (W/ft²) | J12: =$C12*H12 -> 4104.5528
A13: Building Entrance | B13: 2 building entrance (1 per 10,000 ft² footprint) | C13: =2 -> 2 | D13: (count) | E13: 15 | F13: (W/ea) | G13: =E13*2 -> 30 | H13: 15 | I13: (W/ea) | J13: =$C13*H13 -> 30
A14: Hardscape Ornamental Light | B14: 0.1 ft² per 1 ft² of gross building area [2019 Lighting CASE report,Table 36] | C14: =B24*0.1 -> 15392.073 | D14: (ft²) | E14: 0.007 | F14: (W/ft²) | G14: =E14*C14 -> 107.74451 | H14: 0.007 | I14: (W/ft²) | J14: =$C14*H14 -> 107.74451
A15: Building façade | B15: Façade Area = Perimeter × 0.5 × 30 ft (30 ft is the max height that is lit) * The 0.5 factor assumes that only half of the perimeter walls are lit. -Formula ia developed based on the 2019 Outdoor Lighting CASE report | C15: =B23*0.5*30 -> 10770 | D15: (ft²) | E15: 0.1 | F15: (W/ft²) | G15: =E15*C15 -> 1077 | H15: 0.1 | I15: (W/ft²) | J15: =$C15*H15 -> 1077
A16: Non-sales canopy | B16: Size of the canopy is 60 ft* 24 ft according to the geometry | C16: =60*24 -> 1440 | D16: (ft²) | E16: 0.137 | F16: (W/ft²) | G16: =E16*C16 -> 197.28 | H16: 0.137 | I16: (W/ft²) | J16: =$C16*H16 -> 197.28
A17: Motion controlled Luminaires | G17: =G12+G11+G16+G13 -> 3676.7176 | J17: =J12+J11+J16+J13 -> 4581.8328
A18: Non-motion-controlled Luminaires | G18: =G14+G15 -> 1184.7445 | J18: =J14+J15 -> 1184.7445
A19: Total | G19: =G17+G18 -> 4861.4621 | J19: =J17+J18 -> 5766.5773
A21: *Developed based on 2019 Outdoor Lighting CASE Report
A23: Perimeter (ft) | B23: =(284+75)*2 -> 718
A24: Total floor area (ft²) | B24: =Zones!H30 -> 153920.73
A25: Floors (above ground) | B25: 8

Sheet Equipment
A1: ="Equipment - "&Prototype!A2 -> Equipment - HotelLarge
A2: Space Type | B2: Plug load Power Density (W/ft²) | C2: ReachIn Refrigerator and ReachInFreezer Power (W) - 24/7 | D2: Refrigeration Power Density (W/ft²) | E2: Gas Power Density (Btu/hr-ft²) | F2: Source
A3: Convention, Conference, Multipurpose and Meeting Area | B3: 1 | D3: =Data!H84 -> 0 | E3: =Data!G84 -> 0 | F3: T24 2022 - Appendix 5.4A
A4: Office Area (>250 square feet) | B4: 0.7 | F4: Plug load and schedules project with CEC, 2024
A5: Service and back up prep | B5: 1.5 | F5: Engineering judgement
A6: Retail Sales Area (Retail Merchandise Sales) | B6: 0.4 | F6: Plug load and schedules project with CEC, 2025
A7: Electrical, Mechanical, Telephone Rooms | B7: 3 | F7: T24 2022 - Appendix 5.4A
A8: Storage (General) | B8: 0.2
A9: Laundry Area | B9: 3 | E9: 0.75
A10: Dining Area (Cafeteria/Fast Food) | B10: 0.5 | F10: Plug load and schedules project with CEC, 2025
A11: Lobby, Main Entry | B11: 0.5
A12: Hotel/Motel Guest Room | B12: 0.5
A13: Corridor Area | B13: 0 | F13: T24 2022 - Appendix 5.4A
A14: Hotel Function Area | B14: 0.5 | F14: ReachIn Refrigerator and ReachInFreezer: [PNNL ASHRAE 90.1 2022 HotelLarge Prototype] Other inputs: : T24 2022 - Appendix 5.4A
A15: Dining Area (Bar/Lounge and Fine Dining) | B15: 0.5
A16: Kitchen/Food Preparation Area | B16: 1.5 | C16: =277.5+156.7 -> 434.2 | D16: 1.12 | E16: 17.54
A19: Elevator
A20: Vintage | B20: Class | C20: Number of elevators (ne) | D20: Cab Lighting Power Limit (W/ft2) | E20: Fan Power Limit (W/CFM) | F20: Cab Ventilation Fan & Lighting Shutoff | G20: Design Motor Load (W) | H20: Fan Load (W) | I20: Lighting Load (W) | J20: Total (W) | K20: Note
A21: Existing | B21: F/G | C21: 6 | D21: 1.14 | E21: 0.33 | F21: When stopped and unoccupied with doors closed for over 15 minutes, cab interior lighting and ventilation shall be de-energized until required for operation. | G21: =ROUND(INDEX($C:$C,MATCH("Annual energy consumption of the elevator - Existing",$B:$B,0))/INDEX($C:$C,MATCH("Equivalent full load hours",$B:$B,0))*1000,2) -> 96087.14 | H21: =ROUND(C21*INDEX($C:$C,MATCH("Cab fan airflow",$B:$B,0))*E21,2) -> 495 | I21: =ROUND(C21*INDEX($C:$C,MATCH("Cab floor area",$B:$B,0))*D21,2) -> 204.52 | J21: =ROUND(SUM(G21:I21),2) -> 96786.66 | K21: Design load is calculated according to ISO 25745-2 method using Class F/G. Cab lighting and fan requirements are based on ASHRAE 90.1 2013.
A22: New Construction | B22: E | C22: 6 | D22: 0.6 | E22: 0.33 | F22: When the elevator cab is stopped and unoccupied with doors closed for over 15 minutes, the cab interior lighting and ventilation fans shall be switched off until elevator cab operation resumes. | G22: =ROUND(INDEX($C:$C,MATCH("Annual energy consumption of the elevator - New Construction",$B:$B,0))/INDEX($C:$C,MATCH("Equivalent full load hours",$B:$B,0))*1000,2) -> 58776.2 | H22: =ROUND(C22*INDEX($C:$C,MATCH("Cab fan airflow",$B:$B,0))*E22,2) -> 495 | I22: =ROUND(C22*INDEX($C:$C,MATCH("Cab floor area",$B:$B,0))*D22,2) -> 107.64 | J22: =ROUND(SUM(G22:I22),2) -> 59378.84 | K22: Design load is calculated according to ISO 25745-2 method using Class E. Cab lighting and fan requirements are based on T24 2025 §120.6 (f).
A25: Large Hotel Elevator Calculations
A26: Symbol | B26: Definition | C26: Value | D26: Units | E26: Source
A27: E | B27: Annual energy consumption of the elevator - Existing | C27: 218146.63 | D27: kWh/year | E27: Calculated
B28: Annual energy consumption of the elevator - New Construction | C28: 133439.6 | D28: kWh/year | E28: Calculated
A29: C1 | B29: Running-energy coefficient | C29: 3.65 for Class E; 5.47 for Class F | D29: Coefficient | E29: ISO 25745-2 Table 7
A30: C2 | B30: Idle/standby coefficient | C30: 800 for Class E; 1,600 for Class F | D30: Coefficient | E30: ISO 25745-2 Table 7
A31: Q | B31: Rated load of elevator | C31: 1361 | D31: kg | E31: Assumed for all prototypes
A32: Elevator Size | B32: Cab floor area | C32: 29.9 | D32: ft^2 | E32: W=6.781 ft, L=4.406 ft; assumed based on representative manufacturer
A33: CFM | B33: Cab fan airflow | C33: 250 | D33: cfm | E33: Assumed for multifamily and commercial prototypes
A34: cat | B34: Usage category | C34: 4 | D34: - | E34: ISO 25745-2 Table A.1
A35: d | B35: Operating days per year | C35: 360 | D35: days/year | E35: ISO 25745-2 Table A.1
A36: nf | B36: Number of floors | C36: 9 | D36: floors | E36: Prototype assumptions
A37: h | B37: Floor-to-floor height | C37: 3.05 | D37: m | E37: Prototype assumptions
A38: v | B38: Elevator lift speed | C38: 2.5 | D38: m/s | E38: ISO 25745-2 Table A.1
A39: nd | B39: Number of trips per day | C39: 750 | D39: trips/day | E39: ISO 25745-2 Table A.1
A40: S_pct | B40: Percent of average travel distance | C40: 0.44 | D40: % | E40: ISO 25745-2 Table 2
A41: a | B41: Acceleration | C41: 1 | D41: m/s^2 | E41: Annex B of ISO 25745-2
A42: j | B42: Jerk | C42: 1.25 | D42: m/s^3 | E42: Annex B of ISO 25745-2
... A48: Total light level | B48: Total light level | C48: 40 | D48: lm/ft2 | E48: PNNL Prototypes
A49: EFLH | B49: Equivalent full load hours | C49: =Schedules!AD219 -> 2270.3 | D49: hours | E49: Calculated using the elevator schedule

Sheet Schedules
A1: ="Schedules - "&Prototype!A2 -> Schedules - HotelLarge
A2: Zone | B2: Schedule Category | C2: Schedule | D2: Source | E2: Type | F2: Hour
F3: 1 | G3: 2 | H3: 3 | I3: 4 | J3: 5 | K3: 6 | L3: 7 | M3: 8 | N3: 9 | O3: 10 | P3: 11 | Q3: 12 | R3: 13 | S3: 14 | T3: 15 | U3: 16 | V3: 17 | W3: 18 | X3: 19 | Y3: 20 | Z3: 21 | AA3: 22 | AB3: 23 | AC3: 24
A4: Service and Back Up prep in Basement | B4: ServiceAndBackUpPrep | C4: Occupancy | D4: PNNL 2022 Large Hotel prototype , basement | E4: Weekday | F4: 0.9 | G4: 0.9 | H4: 0.9 | I4: 0.9 | J4: 0.9 | K4: 0.9 | L4: 0.7 | M4: 0.4 | N4: 0.4 | O4: 0.2 | P4: 0.2 | Q4: 0.2 | R4: 0.2 | S4: 0.2 | T4: 0.2 | U4: 0.3 | V4: 0.5 | W4: 0.5 | X4: 0.5 | Y4: 0.7 | Z4: 0.7 | AA4: 0.8 | AB4: 0.9 | AC4: 0.9
E5: Saturday | F5: 0.9 | G5: 0.9 | H5: 0.9 | I5: 0.9 | J5: 0.9 | K5: 0.9 | L5: 0.7 | M5: 0.5 | N5: 0.5 | O5: 0.3 | P5: 0.3 | Q5: 0.3 | R5: 0.3 | S5: 0.3 | T5: 0.3 | U5: 0.3 | V5: 0.3 | W5: 0.5 | X5: 0.6 | Y5: 0.6 | Z5: 0.6 | AA5: 0.7 | AB5: 0.7 | AC5: 0.7
E6: Sunday | F6: 0.7 | G6: 0.7 | H6: 0.7 | I6: 0.7 | J6: 0.7 | K6: 0.7 | L6: 0.7 | M6: 0.7 | N6: 0.5 | O6: 0.5 | P6: 0.5 | Q6: 0.3 | R6: 0.3 | S6: 0.2 | T6: 0.2 | U6: 0.2 | V6: 0.3 | W6: 0.4 | X6: 0.4 | Y6: 0.6 | Z6: 0.6 | AA6: 0.8 | AB6: 0.8 | AC6: 0.8
A7: =A4 -> Service and Back Up prep in Basement | B7: =B4 -> ServiceAndBackUpPrep | C7: Lights | D7: PNNL 2022 Large Hotel prototype , Lights of the Basement zone | E7: Weekday | F7: 0.2 | G7: 0.15 | H7: 0.1 | I7: 0.1 | J7: 0.1 | K7: 0.2 | L7: 0.4 | M7: 0.5 | N7: 0.4 | O7: 0.4 | P7: 0.25 | Q7: 0.25 | R7: 0.25 | S7: 0.25 | T7: 0.25 | U7: 0.25 | V7: 0.25 | W7: 0.25 | X7: 0.6 | Y7: 0.8 | Z7: 0.9 | AA7: 0.8 | AB7: 0.6 | AC7: 0.3
E8: Saturday | F8: 0.2 | G8: 0.2 | H8: 0.1 | I8: 0.1 | J8: 0.1 | K8: 0.1 | L8: 0.3 | M8: 0.3 | N8: 0.4 | O8: 0.4 | P8: 0.3 | Q8: 0.25 | R8: 0.25 | S8: 0.25 | T8: 0.25 | U8: 0.25 | V8: 0.25 | W8: 0.25 | X8: 0.6 | Y8: 0.7 | Z8: 0.7 | AA8: 0.7 | AB8: 0.6 | AC8: 0.3
E9: Sunday | F9: 0.3 | G9: 0.3 | H9: 0.2 | I9: 0.2 | J9: 0.2 | K9: 0.2 | L9: 0.3 | M9: 0.4 | N9: 0.4 | O9: 0.3 | P9: 0.3 | Q9: 0.3 | R9: 0.3 | S9: 0.2 | T9: 0.2 | U9: 0.2 | V9: 0.2 | W9: 0.2 | X9: 0.5 | Y9: 0.7 | Z9: 0.8 | AA9: 0.6 | AB9: 0.5 | AC9: 0.3
A10: =A4 -> Service and Back Up prep in Basement | B10: =B4 -> ServiceAndBackUpPrep | C10: ElecEquipment | E10: Weekday | F10: 0.3 | G10: 0.25 | H10: 0.2 | I10: 0.2 | J10: 0.2 | K10: 0.3 | L10: 0.5 | M10: 0.6 | N10: 0.5 | O10: 0.5 | P10: 0.35 | Q10: 0.35 | R10: 0.35 | S10: 0.35 | T10: 0.35 | U10: 0.35 | V10: 0.35 | W10: 0.35 | X10: 0.7 | Y10: 0.9 | Z10: 0.95 | AA10: 0.9 | AB10: 0.7 | AC10: 0.4
E11: Saturday | F11: 0.3 | G11: 0.3 | H11: 0.2 | I11: 0.2 | J11: 0.2 | K11: 0.2 | L11: 0.4 | M11: 0.4 | N11: 0.5 | O11: 0.5 | P11: 0.4 | Q11: 0.35 | R11: 0.35 | S11: 0.35 | T11: 0.35 | U11: 0.35 | V11: 0.35 | W11: 0.35 | X11: 0.7 | Y11: 0.8 | Z11: 0.8 | AA11: 0.8 | AB11: 0.7 | AC11: 0.4
E12: Sunday | F12: 0.4 | G12: 0.4 | H12: 0.3 | I12: 0.3 | J12: 0.3 | K12: 0.3 | L12: 0.4 | M12: 0.5 | N12: 0.5 | O12: 0.4 | P12: 0.4 | Q12: 0.4 | R12: 0.4 | S12: 0.3 | T12: 0.3 | U12: 0.3 | V12: 0.3 | W12: 0.3 | X12: 0.6 | Y12: 0.8 | Z12: 0.9 | AA12: 0.7 | AB12: 0.6 | AC12: 0.4
A13: =A4 -> Service and Back Up prep in Basement | B13: =B4 -> ServiceAndBackUpPrep | C13: HVACAvail | D13: PNNL 2022 Large Hotel prototype , Basement | E13: Weekday | F13: 1 | G13: 1 | H13: 1 | I13: 1 | J13: 1 | K13: 1 | L13: 1 | M13: 1 | N13: 1 | O13: 1 | P13: 1 | Q13: 1 | R13: 1 | S13: 1 | T13: 1 | U13: 1 | V13: 1 | W13: 1 | X13: 1 | Y13: 1 | Z13: 1 | AA13: 1 | AB13: 1 | AC13: 1
E14: Saturday | F14: 1 | G14: 1 | H14: 1 | I14: 1 | J14: 1 | K14: 1 | L14: 1 | M14: 1 | N14: 1 | O14: 1 | P14: 1 | Q14: 1 | R14: 1 | S14: 1 | T14: 1 | U14: 1 | V14: 1 | W14: 1 | X14: 1 | Y14: 1 | Z14: 1 | AA14: 1 | AB14: 1 | AC14: 1
E15: Sunday | F15: 1 | G15: 1 | H15: 1 | I15: 1 | J15: 1 | K15: 1 | L15: 1 | M15: 1 | N15: 1 | O15: 1 | P15: 1 | Q15: 1 | R15: 1 | S15: 1 | T15: 1 | U15: 1 | V15: 1 | W15: 1 | X15: 1 | Y15: 1 | Z15: 1 | AA15: 1 | AB15: 1 | AC15: 1
A16: =A4 -> Service and Back Up prep in Basement | B16: =B4 -> ServiceAndBackUpPrep | C16: ServiceHotWater | D16: Engineering judgement (Less workers during weekend) * PNNL doesn't have SHW to basement | E16: Weekday | F16: 1 | G16: 1 | H16: 1 | I16: 1 | J16: 1 | K16: 0.75 | L16: 0.75 | M16: 0.75 | N16: 0.4 | O16: 0.4 | P16: 0.4 | Q16: 0.4 | R16: 0.4 | S16: 0.4 | T16: 0.4 | U16: 0.4 | V16: 0.4 | W16: 0.75 | X16: 0.75 | Y16: 0.75 | Z16: 0.75 | AA16: 1 | AB16: 1 | AC16: 1
E17: Saturday | F17: 0.9 | G17: 0.9 | H17: 0.9 | I17: 0.9 | J17: 0.9 | K17: 0.65 | L17: 0.65 | M17: 0.65 | N17: 0.3 | O17: 0.3 | P17: 0.3 | Q17: 0.3 | R17: 0.3 | S17: 0.3 | T17: 0.3 | U17: 0.3 | V17: 0.3 | W17: 0.7 | X17: 0.7 | Y17: 0.7 | Z17: 0.7 | AA17: 0.9 | AB17: 0.9 | AC17: 0.9
E18: Sunday | F18: =F17 -> 0.9 | G18: =G17 -> 0.9 | H18: =H17 -> 0.9 | I18: =I17 -> 0.9 | J18: =J17 -> 0.9 | K18: =K17 -> 0.65 | L18: =L17 -> 0.65 | M18: =M17 -> 0.65 | ... AC18: =AC17 -> 0.9
A19: =A7 -> Service and Back Up prep in Basement | B19: =B7 -> ServiceAndBackUpPrep | C19: Infiltration | E19: Weekday | F19: =IF(F13=1,0.25,1) -> 0.25 | G19: =IF(G13=1,0.25,1) -> 0.25 | H19: =IF(H13=1,0.25,1) -> 0.25 | I19: =IF(I13=1,0.25,1) -> 0.25 | J19: =IF(J13=1,0.25,1) -> 0.25 | K19: =IF(K13=1,0.25,1) -> 0.25 | L19: =IF(L13=1,0.25,1) -> 0.25 | M19: =IF(M13=1,0.25,1) -> 0.25 | ... AC19: =IF(AC13=1,0.25,1) -> 0.25
E20: Saturday | F20: =IF(F14=1,0.25,1) -> 0.25 | G20: =IF(G14=1,0.25,1) -> 0.25 | H20: =IF(H14=1,0.25,1) -> 0.25 | I20: =IF(I14=1,0.25,1) -> 0.25 | J20: =IF(J14=1,0.25,1) -> 0.25 | K20: =IF(K14=1,0.25,1) -> 0.25 | L20: =IF(L14=1,0.25,1) -> 0.25 | M20: =IF(M14=1,0.25,1) -> 0.25 | ... AC20: =IF(AC14=1,0.25,1) -> 0.25
E21: Sunday | F21: =IF(F15=1,0.25,1) -> 0.25 | G21: =IF(G15=1,0.25,1) -> 0.25 | H21: =IF(H15=1,0.25,1) -> 0.25 | I21: =IF(I15=1,0.25,1) -> 0.25 | J21: =IF(J15=1,0.25,1) -> 0.25 | K21: =IF(K15=1,0.25,1) -> 0.25 | L21: =IF(L15=1,0.25,1) -> 0.25 | M21: =IF(M15=1,0.25,1) -> 0.25 | ... AC21: =IF(AC15=1,0.25,1) -> 0.25
A22: =A10 -> Service and Back Up prep in Basement | B22: =B10 -> ServiceAndBackUpPrep | C22: HtgSetpt | E22: Weekday | F22: =IF(F13=1,Thermostat!$B$3,Thermostat!$B$4) -> 70 | G22: =IF(G13=1,Thermostat!$B$3,Thermostat!$B$4) -> 70 | H22: =IF(H13=1,Thermostat!$B$3,Thermostat!$B$4) -> 70 | I22: =IF(I13=1,Thermostat!$B$3,Thermostat!$B$4) -> 70 | J22: =IF(J13=1,Thermostat!$B$3,Thermostat!$B$4) -> 70 | K22: =IF(K13=1,Thermostat!$B$3,Thermostat!$B$4) -> 70 | L22: =IF(L13=1,Thermostat!$B$3,Thermostat!$B$4) -> 70 | M22: =IF(M13=1,Thermostat!$B$3,Thermostat!$B$4) -> 70 | ... AC22: =IF(AC13=1,Thermostat!$B$3,Thermostat!$B$4) -> 70
E23: Saturday | F23: =IF(F14=1,Thermostat!$B$3,Thermostat!$B$4) -> 70 | G23: =IF(G14=1,Thermostat!$B$3,Thermostat!$B$4) -> 70 | H23: =IF(H14=1,Thermostat!$B$3,Thermostat!$B$4) -> 70 | I23: =IF(I14=1,Thermostat!$B$3,Thermostat!$B$4) -> 70 | J23: =IF(J14=1,Thermostat!$B$3,Thermostat!$B$4) -> 70 | K23: =IF(K14=1,Thermostat!$B$3,Thermostat!$B$4) -> 70 | L23: =IF(L14=1,Thermostat!$B$3,Thermostat!$B$4) -> 70 | M23: =IF(M14=1,Thermostat!$B$3,Thermostat!$B$4) -> 70 | ... AC23: =IF(AC14=1,Thermostat!$B$3,Thermostat!$B$4) -> 70
E24: Sunday | F24: =IF(F15=1,Thermostat!$B$3,Thermostat!$B$4) -> 70 | G24: =IF(G15=1,Thermostat!$B$3,Thermostat!$B$4) -> 70 | H24: =IF(H15=1,Thermostat!$B$3,Thermostat!$B$4) -> 70 | I24: =IF(I15=1,Thermostat!$B$3,Thermostat!$B$4) -> 70 | J24: =IF(J15=1,Thermostat!$B$3,Thermostat!$B$4) -> 70 | K24: =IF(K15=1,Thermostat!$B$3,Thermostat!$B$4) -> 70 | L24: =IF(L15=1,Thermostat!$B$3,Thermostat!$B$4) -> 70 | M24: =IF(M15=1,Thermostat!$B$3,Thermostat!$B$4) -> 70 | ... AC24: =IF(AC15=1,Thermostat!$B$3,Thermostat!$B$4) -> 70
A25: =A13 -> Service and Back Up prep in Basement | B25: =B13 -> ServiceAndBackUpPrep | C25: ClgSetpt | E25: Weekday | F25: =IF(F13=1,Thermostat!$B$5,Thermostat!$B$6) -> 75 | G25: =IF(G13=1,Thermostat!$B$5,Thermostat!$B$6) -> 75 | H25: =IF(H13=1,Thermostat!$B$5,Thermostat!$B$6) -> 75 | I25: =IF(I13=1,Thermostat!$B$5,Thermostat!$B$6) -> 75 | J25: =IF(J13=1,Thermostat!$B$5,Thermostat!$B$6) -> 75 | K25: =IF(K13=1,Thermostat!$B$5,Thermostat!$B$6) -> 75 | L25: =IF(L13=1,Thermostat!$B$5,Thermostat!$B$6) -> 75 | M25: =IF(M13=1,Thermostat!$B$5,Thermostat!$B$6) -> 75 | ... AC25: =IF(AC13=1,Thermostat!$B$5,Thermostat!$B$6) -> 75
E26: Saturday | F26: =IF(F14=1,Thermostat!$B$5,Thermostat!$B$6) -> 75 | G26: =IF(G14=1,Thermostat!$B$5,Thermostat!$B$6) -> 75 | H26: =IF(H14=1,Thermostat!$B$5,Thermostat!$B$6) -> 75 | I26: =IF(I14=1,Thermostat!$B$5,Thermostat!$B$6) -> 75 | J26: =IF(J14=1,Thermostat!$B$5,Thermostat!$B$6) -> 75 | K26: =IF(K14=1,Thermostat!$B$5,Thermostat!$B$6) -> 75 | L26: =IF(L14=1,Thermostat!$B$5,Thermostat!$B$6) -> 75 | M26: =IF(M14=1,Thermostat!$B$5,Thermostat!$B$6) -> 75 | ... AC26: =IF(AC14=1,Thermostat!$B$5,Thermostat!$B$6) -> 75
E27: Sunday | F27: =IF(F15=1,Thermostat!$B$5,Thermostat!$B$6) -> 75 | G27: =IF(G15=1,Thermostat!$B$5,Thermostat!$B$6) -> 75 | H27: =IF(H15=1,Thermostat!$B$5,Thermostat!$B$6) -> 75 | I27: =IF(I15=1,Thermostat!$B$5,Thermostat!$B$6) -> 75 | J27: =IF(J15=1,Thermostat!$B$5,Thermostat!$B$6) -> 75 | K27: =IF(K15=1,Thermostat!$B$5,Thermostat!$B$6) -> 75 | L27: =IF(L15=1,Thermostat!$B$5,Thermostat!$B$6) -> 75 | M27: =IF(M15=1,Thermostat!$B$5,Thermostat!$B$6) -> 75 | ... AC27: =IF(AC15=1,Thermostat!$B$5,Thermostat!$B$6) -> 75
A28: Assembly
A29: Storage, Mech, Laundry, Banquet | B29: Assembly | C29: Occupancy | D29: T24 2022 - Appendix 5.4B, [Assembly] | E29: Weekday | F29: 0 | G29: 0 | H29: 0 | I29: 0 | J29: 0 | K29: 0 | L29: 0 | M29: 0 | N29: 0.2 | O29: 0.2 | P29: 0.2 | Q29: 0.8 | R29: 0.8 | S29: 0.8 | T29: 0.8 | U29: 0.8 | V29: 0.8 | W29: 0.8 | X29: 0.2 | Y29: 0.2 | Z29: 0.2 | AA29: 0.2 | AB29: 0.1 | AC29: 0
E30: Saturday | F30: 0 | G30: 0 | H30: 0 | I30: 0 | J30: 0 | K30: 0 | L30: 0 | M30: 0 | N30: 0.2 | O30: 0.2 | P30: 0.2 | Q30: 0.6 | R30: 0.6 | S30: 0.6 | T30: 0.6 | U30: 0.6 | V30: 0.6 | W30: 0.6 | X30: 0.6 | Y30: 0.6 | Z30: 0.6 | AA30: 0.8 | AB30: 0.1 | AC30: 0
E31: Sunday | F31: 0 | G31: 0 | H31: 0 | I31: 0 | J31: 0 | K31: 0 | L31: 0 | M31: 0 | N31: 0.1 | O31: 0.1 | P31: 0.1 | Q31: 0.1 | R31: 0.1 | S31: 0.7 | T31: 0.7 | U31: 0.7 | V31: 0.7 | W31: 0.7 | X31: 0.7 | Y31: 0.7 | Z31: 0.7 | AA31: 0.7 | AB31: 0.2 | AC31: 0
A32: Mech, Laundry, Banquet | B32: =B29 -> Assembly | C32: Lights | D32: =D29 -> T24 2022 - Appendix 5.4B, [Assembly] | E32: Weekday | F32: 0.05 | G32: 0.05 | H32: 0.05 | I32: 0.05 | J32: 0.05 | K32: 0.05 | L32: 0.35 | M32: 0.35 | N32: 0.35 | O32: 0.65 | P32: 0.65 | Q32: 0.65 | R32: 0.65 | S32: 0.65 | T32: 0.65 | U32: 0.65 | V32: 0.65 | W32: 0.65 | X32: 0.65 | Y32: 0.65 | Z32: 0.65 | AA32: 0.65 | AB32: 0.25 | AC32: 0.05
E33: Saturday | F33: 0.05 | G33: 0.05 | H33: 0.05 | I33: 0.05 | J33: 0.05 | K33: 0.05 | L33: 0.05 | M33: 0.3 | N33: 0.3 | O33: 0.4 | P33: 0.4 | Q33: 0.4 | R33: 0.4 | S33: 0.4 | T33: 0.4 | U33: 0.4 | V33: 0.4 | W33: 0.4 | X33: 0.4 | Y33: 0.4 | Z33: 0.4 | AA33: 0.4 | AB33: 0.4 | AC33: 0.05
E34: Sunday | F34: 0.05 | G34: 0.05 | H34: 0.05 | I34: 0.05 | J34: 0.05 | K34: 0.05 | L34: 0.05 | M34: 0.3 | N34: 0.3 | O34: 0.3 | P34: 0.3 | Q34: 0.3 | R34: 0.55 | S34: 0.55 | T34: 0.55 | U34: 0.55 | V34: 0.55 | W34: 0.55 | X34: 0.55 | Y34: 0.55 | Z34: 0.55 | AA34: 0.55 | AB34: 0.05 | AC34: 0.05
A35: =A29 -> Storage, Mech, Laundry, Banquet | B35: =B32 -> Assembly | C35: ElecEquipment | D35: =D32 -> T24 2022 - Appendix 5.4B, [Assembly] | E35: Weekday | F35: 0.05 | G35: 0.05 | H35: 0.05 | I35: 0.05 | J35: 0.05 | K35: 0.05 | L35: 0.4 | M35: 0.4 | N35: 0.4 | O35: 0.75 | P35: 0.75 | Q35: 0.75 | R35: 0.75 | S35: 0.75 | T35: 0.75 | U35: 0.75 | V35: 0.75 | W35: 0.75 | X35: 0.75 | Y35: 0.75 | Z35: 0.75 | AA35: 0.75 | AB35: 0.25 | AC35: 0.05
E36: Saturday | F36: 0.05 | G36: 0.05 | H36: 0.05 | I36: 0.05 | J36: 0.05 | K36: 0.05 | L36: 0.05 | M36: 0.3 | N36: 0.3 | O36: 0.5 | P36: 0.5 | Q36: 0.5 | R36: 0.5 | S36: 0.5 | T36: 0.5 | U36: 0.5 | V36: 0.5 | W36: 0.5 | X36: 0.5 | Y36: 0.5 | Z36: 0.5 | AA36: 0.5 | AB36: 0.5 | AC36: 0.05
E37: Sunday | F37: 0.05 | G37: 0.05 | H37: 0.05 | I37: 0.05 | J37: 0.05 | K37: 0.05 | L37: 0.05 | M37: 0.3 | N37: 0.3 | O37: 0.3 | P37: 0.3 | Q37: 0.3 | R37: 0.65 | S37: 0.65 | T37: 0.65 | U37: 0.65 | V37: 0.65 | W37: 0.65 | X37: 0.65 | Y37: 0.65 | Z37: 0.65 | AA37: 0.65 | AB37: 0.05 | AC37: 0.05
A38: =A29 -> Storage, Mech, Laundry, Banquet | B38: =B35 -> Assembly | C38: HVACAvail | D38: =D35 -> T24 2022 - Appendix 5.4B, [Assembly] | E38: Weekday | F38: 0 | G38: 0 | H38: 0 | I38: 0 | J38: 0 | K38: 0 | L38: 0 | M38: 1 | N38: 1 | O38: 1 | P38: 1 | Q38: 1 | R38: 1 | S38: 1 | T38: 1 | U38: 1 | V38: 1 | W38: 1 | X38: 1 | Y38: 1 | Z38: 1 | AA38: 1 | AB38: 1 | AC38: 0
E39: Saturday | F39: 0 | G39: 0 | H39: 0 | I39: 0 | J39: 0 | K39: 0 | L39: 0 | M39: 1 | N39: 1 | O39: 1 | P39: 1 | Q39: 1 | R39: 1 | S39: 1 | T39: 1 | U39: 1 | V39: 1 | W39: 1 | X39: 1 | Y39: 1 | Z39: 1 | AA39: 1 | AB39: 1 | AC39: 0
E40: Sunday | F40: 0 | G40: 0 | H40: 0 | I40: 0 | J40: 0 | K40: 0 | L40: 0 | M40: 1 | N40: 1 | O40: 1 | P40: 1 | Q40: 1 | R40: 1 | S40: 1 | T40: 1 | U40: 1 | V40: 1 | W40: 1 | X40: 1 | Y40: 1 | Z40: 1 | AA40: 1 | AB40: 1 | AC40: 0
A41: =A29 -> Storage, Mech, Laundry, Banquet | B41: =B38 -> Assembly | C41: ServiceHotWater | D41: =D38 -> T24 2022 - Appendix 5.4B, [Assembly] | E41: Weekday | F41: 0 | G41: 0 | H41: 0 | I41: 0 | J41: 0 | K41: 0 | L41: 0 | M41: 0 | N41: 0 | O41: 0.05 | P41: 0.05 | Q41: 0.35 | R41: 0.05 | S41: 0.05 | T41: 0.05 | U41: 0.05 | V41: 0.05 | W41: 0 | X41: 0 | Y41: 0 | Z41: 0 | AA41: 0 | AB41: 0 | AC41: 0
E42: Saturday | F42: 0 | G42: 0 | H42: 0 | I42: 0 | J42: 0 | K42: 0 | L42: 0 | M42: 0 | N42: 0 | O42: 0.05 | P42: 0.05 | Q42: 0.2 | R42: 0 | S42: 0 | T42: 0 | U42: 0 | V42: 0 | W42: 0 | X42: 0 | Y42: 0.65 | Z42: 0.3 | AA42: 0 | AB42: 0 | AC42: 0
E43: Sunday | F43: 0 | G43: 0 | H43: 0 | I43: 0 | J43: 0 | K43: 0 | L43: 0 | M43: 0 | N43: 0 | O43: 0.05 | P43: 0.05 | Q43: 0.1 | R43: 0 | S43: 0 | T43: 0 | U43: 0 | V43: 0 | W43: 0 | X43: 0 | Y43: 0.65 | Z43: 0.3 | AA43: 0 | AB43: 0 | AC43: 0
A44: =A29 -> Storage, Mech, Laundry, Banquet | B44: =B41 -> Assembly | C44: Infiltration | D44: =D41 -> T24 2022 - Appendix 5.4B, [Assembly] | E44: Weekday | F44: 1 | G44: 1 | H44: 1 | I44: 1 | J44: 1 | K44: 1 | L44: 1 | M44: 0.25 | N44: 0.25 | O44: 0.25 | P44: 0.25 | Q44: 0.25 | R44: 0.25 | S44: 0.25 | T44: 0.25 | U44: 0.25 | V44: 0.25 | W44: 0.25 | X44: 0.25 | Y44: 0.25 | Z44: 0.25 | AA44: 0.25 | AB44: 0.25 | AC44: 1
E45: Saturday | F45: 1 | G45: 1 | H45: 1 | I45: 1 | J45: 1 | K45: 1 | L45: 1 | M45: 0.25 | N45: 0.25 | O45: 0.25 | P45: 0.25 | Q45: 0.25 | R45: 0.25 | S45: 0.25 | T45: 0.25 | U45: 0.25 | V45: 0.25 | W45: 0.25 | X45: 0.25 | Y45: 0.25 | Z45: 0.25 | AA45: 0.25 | AB45: 0.25 | AC45: 1
E46: Sunday | F46: 1 | G46: 1 | H46: 1 | I46: 1 | J46: 1 | K46: 1 | L46: 1 | M46: 0.25 | N46: 0.25 | O46: 0.25 | P46: 0.25 | Q46: 0.25 | R46: 0.25 | S46: 0.25 | T46: 0.25 | U46: 0.25 | V46: 0.25 | W46: 0.25 | X46: 0.25 | Y46: 0.25 | Z46: 0.25 | AA46: 0.25 | AB46: 0.25 | AC46: 1
A47: Laundry | B47: =B44 -> Assembly | C47: GasEquipment | D47: =D44 -> T24 2022 - Appendix 5.4B, [Assembly] | E47: Weekday | F47: 0 | G47: 0 | H47: 0 | I47: 0 | J47: 0 | K47: 0 | L47: 0 | M47: 0 | N47: 0.3 | O47: 0.3 | P47: 0.2 | Q47: 0.9 | R47: 0.9 | S47: 0.9 | T47: 0.2 | U47: 0.2 | V47: 0.2 | W47: 0.5 | X47: 0.5 | Y47: 0.1 | Z47: 0.1 | AA47: 0.1 | AB47: 0 | AC47: 0
E48: Saturday | F48: 0 | G48: 0 | H48: 0 | I48: 0 | J48: 0 | K48: 0 | L48: 0 | M48: 0 | N48: 0.3 | O48: 0.3 | P48: 0.2 | Q48: 0.7 | R48: 0.7 | S48: 0.7 | T48: 0.2 | U48: 0.2 | V48: 0.2 | W48: 0.4 | X48: 0.4 | Y48: 0.1 | Z48: 0.1 | AA48: 0.1 | AB48: 0 | AC48: 0
E49: Sunday | F49: 0 | G49: 0 | H49: 0 | I49: 0 | J49: 0 | K49: 0 | L49: 0 | M49: 0 | N49: 0.2 | O49: 0.2 | P49: 0.1 | Q49: 0.1 | R49: 0.3 | S49: 0.8 | T49: 0.2 | U49: 0.2 | V49: 0.2 | W49: 0.5 | X49: 0.5 | Y49: 0.1 | Z49: 0.1 | AA49: 0.1 | AB49: 0 | AC49: 0
A50: =A29 -> Storage, Mech, Laundry, Banquet | B50: =B47 -> Assembly | C50: HtgSetpt | D50: =D47 -> T24 2022 - Appendix 5.4B, [Assembly] | E50: Weekday | F50: =IF((F38=1),Thermostat!$B$3,Thermostat!$B$4) -> 60 | G50: =IF((G38=1),Thermostat!$B$3,Thermostat!$B$4) -> 60 | H50: =IF((H38=1),Thermostat!$B$3,Thermostat!$B$4) -> 60 | I50: =IF((I38=1),Thermostat!$B$3,Thermostat!$B$4) -> 60 | J50: =IF((J38=1),Thermostat!$B$3,Thermostat!$B$4) -> 60 | K50: =IF((K38=1),Thermostat!$B$3,Thermostat!$B$4) -> 60 | L50: =IF((L38=1),Thermostat!$B$3,Thermostat!$B$4) -> 60 | M50: =IF((M38=1),Thermostat!$B$3,Thermostat!$B$4) -> 70 | ... AC50: =IF((AC38=1),Thermostat!$B$3,Thermostat!$B$4) -> 60
E51: Saturday | F51: =IF((F39=1),Thermostat!$B$3,Thermostat!$B$4) -> 60 | G51: =IF((G39=1),Thermostat!$B$3,Thermostat!$B$4) -> 60 | H51: =IF((H39=1),Thermostat!$B$3,Thermostat!$B$4) -> 60 | I51: =IF((I39=1),Thermostat!$B$3,Thermostat!$B$4) -> 60 | J51: =IF((J39=1),Thermostat!$B$3,Thermostat!$B$4) -> 60 | K51: =IF((K39=1),Thermostat!$B$3,Thermostat!$B$4) -> 60 | L51: =IF((L39=1),Thermostat!$B$3,Thermostat!$B$4) -> 60 | M51: =IF((M39=1),Thermostat!$B$3,Thermostat!$B$4) -> 70 | ... AC51: =IF((AC39=1),Thermostat!$B$3,Thermostat!$B$4) -> 60
E52: Sunday | F52: =IF((F40=1),Thermostat!$B$3,Thermostat!$B$4) -> 60 | G52: =IF((G40=1),Thermostat!$B$3,Thermostat!$B$4) -> 60 | H52: =IF((H40=1),Thermostat!$B$3,Thermostat!$B$4) -> 60 | I52: =IF((I40=1),Thermostat!$B$3,Thermostat!$B$4) -> 60 | J52: =IF((J40=1),Thermostat!$B$3,Thermostat!$B$4) -> 60 | K52: =IF((K40=1),Thermostat!$B$3,Thermostat!$B$4) -> 60 | L52: =IF((L40=1),Thermostat!$B$3,Thermostat!$B$4) -> 60 | M52: =IF((M40=1),Thermostat!$B$3,Thermostat!$B$4) -> 70 | ... AC52: =IF((AC40=1),Thermostat!$B$3,Thermostat!$B$4) -> 60
A53: =A29 -> Storage, Mech, Laundry, Banquet | B53: =B50 -> Assembly | C53: ClgSetpt | D53: =D50 -> T24 2022 - Appendix 5.4B, [Assembly] | E53: Weekday | F53: =IF((F38=1),Thermostat!$B$5,Thermostat!$B$6) -> 85 | G53: =IF((G38=1),Thermostat!$B$5,Thermostat!$B$6) -> 85 | H53: =IF((H38=1),Thermostat!$B$5,Thermostat!$B$6) -> 85 | I53: =IF((I38=1),Thermostat!$B$5,Thermostat!$B$6) -> 85 | J53: =IF((J38=1),Thermostat!$B$5,Thermostat!$B$6) -> 85 | K53: =IF((K38=1),Thermostat!$B$5,Thermostat!$B$6) -> 85 | L53: =IF((L38=1),Thermostat!$B$5,Thermostat!$B$6) -> 85 | M53: =IF((M38=1),Thermostat!$B$5,Thermostat!$B$6) -> 75 | ... AC53: =IF((AC38=1),Thermostat!$B$5,Thermostat!$B$6) -> 85
E54: Saturday | F54: =IF((F39=1),Thermostat!$B$5,Thermostat!$B$6) -> 85 | G54: =IF((G39=1),Thermostat!$B$5,Thermostat!$B$6) -> 85 | H54: =IF((H39=1),Thermostat!$B$5,Thermostat!$B$6) -> 85 | I54: =IF((I39=1),Thermostat!$B$5,Thermostat!$B$6) -> 85 | J54: =IF((J39=1),Thermostat!$B$5,Thermostat!$B$6) -> 85 | K54: =IF((K39=1),Thermostat!$B$5,Thermostat!$B$6) -> 85 | L54: =IF((L39=1),Thermostat!$B$5,Thermostat!$B$6) -> 85 | M54: =IF((M39=1),Thermostat!$B$5,Thermostat!$B$6) -> 75 | ... AC54: =IF((AC39=1),Thermostat!$B$5,Thermostat!$B$6) -> 85
E55: Sunday | F55: =IF((F40=1),Thermostat!$B$5,Thermostat!$B$6) -> 85 | G55: =IF((G40=1),Thermostat!$B$5,Thermostat!$B$6) -> 85 | H55: =IF((H40=1),Thermostat!$B$5,Thermostat!$B$6) -> 85 | I55: =IF((I40=1),Thermostat!$B$5,Thermostat!$B$6) -> 85 | J55: =IF((J40=1),Thermostat!$B$5,Thermostat!$B$6) -> 85 | K55: =IF((K40=1),Thermostat!$B$5,Thermostat!$B$6) -> 85 | L55: =IF((L40=1),Thermostat!$B$5,Thermostat!$B$6) -> 85 | M55: =IF((M40=1),Thermostat!$B$5,Thermostat!$B$6) -> 75 | ... AC55: =IF((AC40=1),Thermostat!$B$5,Thermostat!$B$6) -> 85
A56: ResidentialCommen
A57: Corridors and Lobby | B57: =Zones!E22 -> ResidentialCommon | C57: Occupancy | D57: T24 2022 - Appendix 5.4B, Residentialcommon | E57: Weekday | F57: 0.1 | G57: 0.1 | H57: 0.1 | I57: 0.1 | J57: 0.1 | K57: 0.3 | L57: 0.45 | M57: 0.45 | N57: 0.45 | O57: 0.45 | P57: 0.3 | Q57: 0.3 | R57: 0.3 | S57: 0.3 | T57: 0.3 | U57: 0.3 | V57: 0.3 | W57: 0.3 | X57: 0.6 | Y57: 0.8 | Z57: 0.9 | AA57: 0.8 | AB57: 0.6 | AC57: 0.3
E58: Saturday | F58: 0.1 | G58: 0.1 | H58: 0.1 | I58: 0.1 | J58: 0.1 | K58: 0.3 | L58: 0.45 | M58: 0.45 | N58: 0.45 | O58: 0.45 | P58: 0.3 | Q58: 0.3 | R58: 0.3 | S58: 0.3 | T58: 0.3 | U58: 0.3 | V58: 0.3 | W58: 0.3 | X58: 0.6 | Y58: 0.8 | Z58: 0.9 | AA58: 0.8 | AB58: 0.6 | AC58: 0.3
E59: Sunday | F59: 0.1 | G59: 0.1 | H59: 0.1 | I59: 0.1 | J59: 0.1 | K59: 0.3 | L59: 0.45 | M59: 0.45 | N59: 0.45 | O59: 0.45 | P59: 0.3 | Q59: 0.3 | R59: 0.3 | S59: 0.3 | T59: 0.3 | U59: 0.3 | V59: 0.3 | W59: 0.3 | X59: 0.6 | Y59: 0.8 | Z59: 0.9 | AA59: 0.8 | AB59: 0.6 | AC59: 0.3
A60: =A57 -> Corridors and Lobby | B60: =B57 -> ResidentialCommon | C60: Lights | D60: T24 2022 - Appendix 5.4B, Residentialcommon | E60: Weekday | F60: 1 | G60: 1 | H60: 1 | I60: 1 | J60: 1 | K60: 1 | L60: 1 | M60: 1 | N60: 1 | O60: 1 | P60: 1 | Q60: 1 | R60: 1 | S60: 1 | T60: 1 | U60: 1 | V60: 1 | W60: 1 | X60: 1 | Y60: 1 | Z60: 1 | AA60: 1 | AB60: 1 | AC60: 1
E61: Saturday | F61: 1 | G61: 1 | H61: 1 | I61: 1 | J61: 1 | K61: 1 | L61: 1 | M61: 1 | N61: 1 | O61: 1 | P61: 1 | Q61: 1 | R61: 1 | S61: 1 | T61: 1 | U61: 1 | V61: 1 | W61: 1 | X61: 1 | Y61: 1 | Z61: 1 | AA61: 1 | AB61: 1 | AC61: 1
E62: Sunday | F62: 1 | G62: 1 | H62: 1 | I62: 1 | J62: 1 | K62: 1 | L62: 1 | M62: 1 | N62: 1 | O62: 1 | P62: 1 | Q62: 1 | R62: 1 | S62: 1 | T62: 1 | U62: 1 | V62: 1 | W62: 1 | X62: 1 | Y62: 1 | Z62: 1 | AA62: 1 | AB62: 1 | AC62: 1
A63: =A60 -> Corridors and Lobby | B63: =B60 -> ResidentialCommon | C63: ElecEquipment | D63: T24 2022 - Appendix 5.4B, Residentialcommon | E63: Weekday | F63: 0.1 | G63: 0.1 | H63: 0.1 | I63: 0.1 | J63: 0.1 | K63: 0.3 | L63: 0.45 | M63: 0.45 | N63: 0.45 | O63: 0.45 | P63: 0.3 | Q63: 0.3 | R63: 0.3 | S63: 0.3 | T63: 0.3 | U63: 0.3 | V63: 0.3 | W63: 0.3 | X63: 0.6 | Y63: 0.8 | Z63: 0.9 | AA63: 0.8 | AB63: 0.6 | AC63: 0.3
E64: Saturday | F64: 0.1 | G64: 0.1 | H64: 0.1 | I64: 0.1 | J64: 0.1 | K64: 0.3 | L64: 0.45 | M64: 0.45 | N64: 0.45 | O64: 0.45 | P64: 0.3 | Q64: 0.3 | R64: 0.3 | S64: 0.3 | T64: 0.3 | U64: 0.3 | V64: 0.3 | W64: 0.3 | X64: 0.6 | Y64: 0.8 | Z64: 0.9 | AA64: 0.8 | AB64: 0.6 | AC64: 0.3
E65: Sunday | F65: 0.1 | G65: 0.1 | H65: 0.1 | I65: 0.1 | J65: 0.1 | K65: 0.3 | L65: 0.45 | M65: 0.45 | N65: 0.45 | O65: 0.45 | P65: 0.3 | Q65: 0.3 | R65: 0.3 | S65: 0.3 | T65: 0.3 | U65: 0.3 | V65: 0.3 | W65: 0.3 | X65: 0.6 | Y65: 0.8 | Z65: 0.9 | AA65: 0.8 | AB65: 0.6 | AC65: 0.3
A66: =A63 -> Corridors and Lobby | B66: =B63 -> ResidentialCommon | C66: ServiceHotWater | D66: T24 2022 - Appendix 5.4B, Residentialcommon | E66: Weekday | F66: 0 | G66: 0 | H66: 0 | I66: 0.05 | J66: 0.05 | K66: 0.05 | L66: 0.8 | M66: 0.7 | N66: 0.5 | O66: 0.4 | P66: 0.25 | Q66: 0.25 | R66: 0.25 | S66: 0.25 | T66: 0.5 | U66: 0.6 | V66: 0.7 | W66: 0.7 | X66: 0.4 | Y66: 0.25 | Z66: 0.2 | AA66: 0.2 | AB66: 0.05 | AC66: 0.05
E67: Saturday | F67: 0 | G67: 0 | H67: 0 | I67: 0.05 | J67: 0.05 | K67: 0.05 | L67: 0.8 | M67: 0.7 | N67: 0.5 | O67: 0.4 | P67: 0.25 | Q67: 0.25 | R67: 0.25 | S67: 0.25 | T67: 0.5 | U67: 0.6 | V67: 0.7 | W67: 0.7 | X67: 0.4 | Y67: 0.25 | Z67: 0.2 | AA67: 0.2 | AB67: 0.05 | AC67: 0.05
E68: Sunday | F68: 0 | G68: 0 | H68: 0 | I68: 0.05 | J68: 0.05 | K68: 0.05 | L68: 0.8 | M68: 0.7 | N68: 0.5 | O68: 0.4 | P68: 0.25 | Q68: 0.25 | R68: 0.25 | S68: 0.25 | T68: 0.5 | U68: 0.6 | V68: 0.7 | W68: 0.7 | X68: 0.4 | Y68: 0.25 | Z68: 0.2 | AA68: 0.2 | AB68: 0.05 | AC68: 0.05
A69: =A63 -> Corridors and Lobby | B69: =B63 -> ResidentialCommon | C69: HVACAvail | D69: T24 2022 - Appendix 5.4B, Residentialcommon | E69: Weekday | F69: 1 | G69: 1 | H69: 1 | I69: 1 | J69: 1 | K69: 1 | L69: 1 | M69: 1 | N69: 1 | O69: 1 | P69: 1 | Q69: 1 | R69: 1 | S69: 1 | T69: 1 | U69: 1 | V69: 1 | W69: 1 | X69: 1 | Y69: 1 | Z69: 1 | AA69: 1 | AB69: 1 | AC69: 1
E70: Saturday | F70: 1 | G70: 1 | H70: 1 | I70: 1 | J70: 1 | K70: 1 | L70: 1 | M70: 1 | N70: 1 | O70: 1 | P70: 1 | Q70: 1 | R70: 1 | S70: 1 | T70: 1 | U70: 1 | V70: 1 | W70: 1 | X70: 1 | Y70: 1 | Z70: 1 | AA70: 1 | AB70: 1 | AC70: 1
E71: Sunday | F71: 1 | G71: 1 | H71: 1 | I71: 1 | J71: 1 | K71: 1 | L71: 1 | M71: 1 | N71: 1 | O71: 1 | P71: 1 | Q71: 1 | R71: 1 | S71: 1 | T71: 1 | U71: 1 | V71: 1 | W71: 1 | X71: 1 | Y71: 1 | Z71: 1 | AA71: 1 | AB71: 1 | AC71: 1
A72: =A69 -> Corridors and Lobby | B72: =B69 -> ResidentialCommon | C72: Infiltration | D72: T24 2022 - Appendix 5.4B, Residentialcommon | E72: Weekday | F72: 0.25 | G72: 0.25 | H72: 0.25 | I72: 0.25 | J72: 0.25 | K72: 0.25 | L72: 0.25 | M72: 0.25 | N72: 0.25 | O72: 0.25 | P72: 0.25 | Q72: 0.25 | R72: 0.25 | S72: 0.25 | T72: 0.25 | U72: 0.25 | V72: 0.25 | W72: 0.25 | X72: 0.25 | Y72: 0.25 | Z72: 0.25 | AA72: 0.25 | AB72: 0.25 | AC72: 0.25
E73: Saturday | F73: 0.25 | G73: 0.25 | H73: 0.25 | I73: 0.25 | J73: 0.25 | K73: 0.25 | L73: 0.25 | M73: 0.25 | N73: 0.25 | O73: 0.25 | P73: 0.25 | Q73: 0.25 | R73: 0.25 | S73: 0.25 | T73: 0.25 | U73: 0.25 | V73: 0.25 | W73: 0.25 | X73: 0.25 | Y73: 0.25 | Z73: 0.25 | AA73: 0.25 | AB73: 0.25 | AC73: 0.25
E74: Sunday | F74: 0.25 | G74: 0.25 | H74: 0.25 | I74: 0.25 | J74: 0.25 | K74: 0.25 | L74: 0.25 | M74: 0.25 | N74: 0.25 | O74: 0.25 | P74: 0.25 | Q74: 0.25 | R74: 0.25 | S74: 0.25 | T74: 0.25 | U74: 0.25 | V74: 0.25 | W74: 0.25 | X74: 0.25 | Y74: 0.25 | Z74: 0.25 | AA74: 0.25 | AB74: 0.25 | AC74: 0.25
A75: =A72 -> Corridors and Lobby | B75: =B72 -> ResidentialCommon | C75: HtgSetpt | D75: T24 2022 - Appendix 5.4B, Residentialcommon | E75: Weekday | F75: =IF((F69=1),Thermostat!$B$7,Thermostat!$B$8) -> 68 | G75: =IF((G69=1),Thermostat!$B$7,Thermostat!$B$8) -> 68 | H75: =IF((H69=1),Thermostat!$B$7,Thermostat!$B$8) -> 68 | I75: =IF((I69=1),Thermostat!$B$7,Thermostat!$B$8) -> 68 | J75: =IF((J69=1),Thermostat!$B$7,Thermostat!$B$8) -> 68 | K75: =IF((K69=1),Thermostat!$B$7,Thermostat!$B$8) -> 68 | L75: =IF((L69=1),Thermostat!$B$7,Thermostat!$B$8) -> 68 | M75: =IF((M69=1),Thermostat!$B$7,Thermostat!$B$8) -> 68 | ... AC75: =IF((AC69=1),Thermostat!$B$7,Thermostat!$B$8) -> 68
E76: Saturday | F76: =IF((F70=1),Thermostat!$B$7,Thermostat!$B$8) -> 68 | G76: =IF((G70=1),Thermostat!$B$7,Thermostat!$B$8) -> 68 | H76: =IF((H70=1),Thermostat!$B$7,Thermostat!$B$8) -> 68 | I76: =IF((I70=1),Thermostat!$B$7,Thermostat!$B$8) -> 68 | J76: =IF((J70=1),Thermostat!$B$7,Thermostat!$B$8) -> 68 | K76: =IF((K70=1),Thermostat!$B$7,Thermostat!$B$8) -> 68 | L76: =IF((L70=1),Thermostat!$B$7,Thermostat!$B$8) -> 68 | M76: =IF((M70=1),Thermostat!$B$7,Thermostat!$B$8) -> 68 | ... AC76: =IF((AC70=1),Thermostat!$B$7,Thermostat!$B$8) -> 68
E77: Sunday | F77: =IF((F71=1),Thermostat!$B$7,Thermostat!$B$8) -> 68 | G77: =IF((G71=1),Thermostat!$B$7,Thermostat!$B$8) -> 68 | H77: =IF((H71=1),Thermostat!$B$7,Thermostat!$B$8) -> 68 | I77: =IF((I71=1),Thermostat!$B$7,Thermostat!$B$8) -> 68 | J77: =IF((J71=1),Thermostat!$B$7,Thermostat!$B$8) -> 68 | K77: =IF((K71=1),Thermostat!$B$7,Thermostat!$B$8) -> 68 | L77: =IF((L71=1),Thermostat!$B$7,Thermostat!$B$8) -> 68 | M77: =IF((M71=1),Thermostat!$B$7,Thermostat!$B$8) -> 68 | ... AC77: =IF((AC71=1),Thermostat!$B$7,Thermostat!$B$8) -> 68
A78: =A75 -> Corridors and Lobby | B78: =B75 -> ResidentialCommon | C78: ClgSetpt | D78: T24 2022 - Appendix 5.4B, Residentialcommon | E78: Weekday | F78: =IF((F69=1),Thermostat!$B$9,Thermostat!$B$10) -> 78 | G78: =IF((G69=1),Thermostat!$B$9,Thermostat!$B$10) -> 78 | H78: =IF((H69=1),Thermostat!$B$9,Thermostat!$B$10) -> 78 | I78: =IF((I69=1),Thermostat!$B$9,Thermostat!$B$10) -> 78 | J78: =IF((J69=1),Thermostat!$B$9,Thermostat!$B$10) -> 78 | K78: =IF((K69=1),Thermostat!$B$9,Thermostat!$B$10) -> 78 | L78: =IF((L69=1),Thermostat!$B$9,Thermostat!$B$10) -> 78 | M78: =IF((M69=1),Thermostat!$B$9,Thermostat!$B$10) -> 78 | ... AC78: =IF((AC69=1),Thermostat!$B$9,Thermostat!$B$10) -> 78
E79: Saturday | F79: =IF((F70=1),Thermostat!$B$9,Thermostat!$B$10) -> 78 | G79: =IF((G70=1),Thermostat!$B$9,Thermostat!$B$10) -> 78 | H79: =IF((H70=1),Thermostat!$B$9,Thermostat!$B$10) -> 78 | I79: =IF((I70=1),Thermostat!$B$9,Thermostat!$B$10) -> 78 | J79: =IF((J70=1),Thermostat!$B$9,Thermostat!$B$10) -> 78 | K79: =IF((K70=1),Thermostat!$B$9,Thermostat!$B$10) -> 78 | L79: =IF((L70=1),Thermostat!$B$9,Thermostat!$B$10) -> 78 | M79: =IF((M70=1),Thermostat!$B$9,Thermostat!$B$10) -> 78 | ... AC79: =IF((AC70=1),Thermostat!$B$9,Thermostat!$B$10) -> 78
E80: Sunday | F80: =IF((F71=1),Thermostat!$B$9,Thermostat!$B$10) -> 78 | G80: =IF((G71=1),Thermostat!$B$9,Thermostat!$B$10) -> 78 | H80: =IF((H71=1),Thermostat!$B$9,Thermostat!$B$10) -> 78 | I80: =IF((I71=1),Thermostat!$B$9,Thermostat!$B$10) -> 78 | J80: =IF((J71=1),Thermostat!$B$9,Thermostat!$B$10) -> 78 | K80: =IF((K71=1),Thermostat!$B$9,Thermostat!$B$10) -> 78 | L80: =IF((L71=1),Thermostat!$B$9,Thermostat!$B$10) -> 78 | M80: =IF((M71=1),Thermostat!$B$9,Thermostat!$B$10) -> 78 | ... AC80: =IF((AC71=1),Thermostat!$B$9,Thermostat!$B$10) -> 78
A81: ResidentialLiving
A82: Guest Rooms | B82: =Zones!E16 -> ResidentialLiving | C82: Occupancy | D82: T24 2022 - Appendix 5.4B, [ResidentialLiving] | E82: Weekday | F82: 0.9 | G82: 0.9 | H82: 0.9 | I82: 0.9 | J82: 0.9 | K82: 0.9 | L82: 0.7 | M82: 0.4 | N82: 0.4 | O82: 0.2 | P82: 0.2 | Q82: 0.2 | R82: 0.2 | S82: 0.2 | T82: 0.2 | U82: 0.3 | V82: 0.5 | W82: 0.5 | X82: 0.5 | Y82: 0.7 | Z82: 0.7 | AA82: 0.8 | AB82: 0.9 | AC82: 0.9
E83: Saturday | F83: 0.9 | G83: 0.9 | H83: 0.9 | I83: 0.9 | J83: 0.9 | K83: 0.9 | L83: 0.7 | M83: 0.4 | N83: 0.4 | O83: 0.2 | P83: 0.2 | Q83: 0.2 | R83: 0.2 | S83: 0.2 | T83: 0.2 | U83: 0.3 | V83: 0.5 | W83: 0.5 | X83: 0.5 | Y83: 0.7 | Z83: 0.7 | AA83: 0.8 | AB83: 0.9 | AC83: 0.9
E84: Sunday | F84: 0.9 | G84: 0.9 | H84: 0.9 | I84: 0.9 | J84: 0.9 | K84: 0.9 | L84: 0.7 | M84: 0.4 | N84: 0.4 | O84: 0.2 | P84: 0.2 | Q84: 0.2 | R84: 0.2 | S84: 0.2 | T84: 0.2 | U84: 0.3 | V84: 0.5 | W84: 0.5 | X84: 0.5 | Y84: 0.7 | Z84: 0.7 | AA84: 0.8 | AB84: 0.9 | AC84: 0.9
A85: =A82 -> Guest Rooms | B85: =B82 -> ResidentialLiving | C85: Lights | D85: T24 2022 - Appendix 5.4B, [ResidentialLiving] | E85: Weekday | F85: 0.1 | G85: 0.1 | H85: 0.1 | I85: 0.1 | J85: 0.1 | K85: 0.3 | L85: 0.45 | M85: 0.45 | N85: 0.45 | O85: 0.45 | P85: 0.3 | Q85: 0.3 | R85: 0.3 | S85: 0.3 | T85: 0.3 | U85: 0.3 | V85: 0.3 | W85: 0.3 | X85: 0.6 | Y85: 0.8 | Z85: 0.9 | AA85: 0.8 | AB85: 0.6 | AC85: 0.3
E86: Saturday | F86: 0.1 | G86: 0.1 | H86: 0.1 | I86: 0.1 | J86: 0.1 | K86: 0.3 | L86: 0.45 | M86: 0.45 | N86: 0.45 | O86: 0.45 | P86: 0.3 | Q86: 0.3 | R86: 0.3 | S86: 0.3 | T86: 0.3 | U86: 0.3 | V86: 0.3 | W86: 0.3 | X86: 0.6 | Y86: 0.8 | Z86: 0.9 | AA86: 0.8 | AB86: 0.6 | AC86: 0.3
E87: Sunday | F87: 0.1 | G87: 0.1 | H87: 0.1 | I87: 0.1 | J87: 0.1 | K87: 0.3 | L87: 0.45 | M87: 0.45 | N87: 0.45 | O87: 0.45 | P87: 0.3 | Q87: 0.3 | R87: 0.3 | S87: 0.3 | T87: 0.3 | U87: 0.3 | V87: 0.3 | W87: 0.3 | X87: 0.6 | Y87: 0.8 | Z87: 0.9 | AA87: 0.8 | AB87: 0.6 | AC87: 0.3
A88: =A85 -> Guest Rooms | B88: =B85 -> ResidentialLiving | C88: ElecEquipment | D88: Plug load and schedules project with CEC, 2025 | E88: Weekday | F88: 0.1 | G88: 0.1 | H88: 0.1 | I88: 0.1 | J88: 0.1 | K88: 0.3 | L88: 0.45 | M88: 0.45 | N88: 0.45 | O88: 0.45 | P88: 0.2 | Q88: 0.2 | R88: 0.2 | S88: 0.2 | T88: 0.2 | U88: 0.2 | V88: 0.2 | W88: 0.2 | X88: 0.4 | Y88: 0.5 | Z88: 0.6 | AA88: 0.5 | AB88: 0.4 | AC88: 0.25
E89: Saturday | F89: =F88 -> 0.1 | G89: =G88 -> 0.1 | H89: =H88 -> 0.1 | I89: =I88 -> 0.1 | J89: =J88 -> 0.1 | K89: =K88 -> 0.3 | L89: =L88 -> 0.45 | M89: =M88 -> 0.45 | ... AC89: =AC88 -> 0.25
E90: Sunday | F90: =F88 -> 0.1 | G90: =G88 -> 0.1 | H90: =H88 -> 0.1 | I90: =I88 -> 0.1 | J90: =J88 -> 0.1 | K90: =K88 -> 0.3 | L90: =L88 -> 0.45 | M90: =M88 -> 0.45 | ... AC90: =AC88 -> 0.25
A91: =A88 -> Guest Rooms | B91: =B88 -> ResidentialLiving | C91: HVACAvail | D91: T24 2022 - Appendix 5.4B, [ResidentialLiving] | E91: Weekday | F91: 1 | G91: 1 | H91: 1 | I91: 1 | J91: 1 | K91: 1 | L91: 1 | M91: 1 | N91: 1 | O91: 1 | P91: 1 | Q91: 1 | R91: 1 | S91: 1 | T91: 1 | U91: 1 | V91: 1 | W91: 1 | X91: 1 | Y91: 1 | Z91: 1 | AA91: 1 | AB91: 1 | AC91: 1
E92: Saturday | F92: 1 | G92: 1 | H92: 1 | I92: 1 | J92: 1 | K92: 1 | L92: 1 | M92: 1 | N92: 1 | O92: 1 | P92: 1 | Q92: 1 | R92: 1 | S92: 1 | T92: 1 | U92: 1 | V92: 1 | W92: 1 | X92: 1 | Y92: 1 | Z92: 1 | AA92: 1 | AB92: 1 | AC92: 1
E93: Sunday | F93: 1 | G93: 1 | H93: 1 | I93: 1 | J93: 1 | K93: 1 | L93: 1 | M93: 1 | N93: 1 | O93: 1 | P93: 1 | Q93: 1 | R93: 1 | S93: 1 | T93: 1 | U93: 1 | V93: 1 | W93: 1 | X93: 1 | Y93: 1 | Z93: 1 | AA93: 1 | AB93: 1 | AC93: 1
A94: =A91 -> Guest Rooms | B94: =B91 -> ResidentialLiving | C94: ServiceHotWater | D94: T24 2022 - Appendix 5.4B, [ResidentialLiving] | E94: Weekday | F94: 0.131 | G94: 0.075 | H94: 0.084 | I94: 0.103 | J94: 0.187 | K94: 0.411 | L94: 0.832 | M94: 1 | N94: 0.832 | O94: 0.617 | P94: 0.486 | Q94: 0.355 | R94: 0.336 | S94: 0.308 | T94: 0.299 | U94: 0.243 | V94: 0.393 | W94: 0.449 | X94: 0.486 | Y94: 0.439 | Z94: 0.393 | AA94: 0.364 | AB94: 0.336 | AC94: 0.206
E95: Saturday | F95: 0.217 | G95: 0.12 | H95: 0.108 | I95: 0.096 | J95: 0.181 | K95: 0.277 | L95: 0.313 | M95: 0.566 | N95: 0.928 | O95: 1 | P95: 0.892 | Q95: 0.735 | R95: 0.614 | S95: 0.518 | T95: 0.47 | U95: 0.47 | V95: 0.627 | W95: 0.699 | X95: 0.675 | Y95: 0.627 | Z95: 0.566 | AA95: 0.53 | AB95: 0.482 | AC95: 0.337
E96: Sunday | F96: 0.217 | G96: 0.12 | H96: 0.108 | I96: 0.096 | J96: 0.181 | K96: 0.277 | L96: 0.313 | M96: 0.566 | N96: 0.928 | O96: 1 | P96: 0.892 | Q96: 0.735 | R96: 0.614 | S96: 0.518 | T96: 0.47 | U96: 0.47 | V96: 0.627 | W96: 0.699 | X96: 0.675 | Y96: 0.627 | Z96: 0.566 | AA96: 0.53 | AB96: 0.482 | AC96: 0.337
A97: =A94 -> Guest Rooms | B97: =B94 -> ResidentialLiving | C97: Infiltration | D97: T24 2022 - Appendix 5.4B, [ResidentialLiving] | E97: Weekday | F97: 1 | G97: 1 | H97: 1 | I97: 1 | J97: 1 | K97: 1 | L97: 1 | M97: 1 | N97: 1 | O97: 1 | P97: 1 | Q97: 1 | R97: 1 | S97: 1 | T97: 1 | U97: 1 | V97: 1 | W97: 1 | X97: 1 | Y97: 1 | Z97: 1 | AA97: 1 | AB97: 1 | AC97: 1
E98: Saturday | F98: 1 | G98: 1 | H98: 1 | I98: 1 | J98: 1 | K98: 1 | L98: 1 | M98: 1 | N98: 1 | O98: 1 | P98: 1 | Q98: 1 | R98: 1 | S98: 1 | T98: 1 | U98: 1 | V98: 1 | W98: 1 | X98: 1 | Y98: 1 | Z98: 1 | AA98: 1 | AB98: 1 | AC98: 1
E99: Sunday | F99: 1 | G99: 1 | H99: 1 | I99: 1 | J99: 1 | K99: 1 | L99: 1 | M99: 1 | N99: 1 | O99: 1 | P99: 1 | Q99: 1 | R99: 1 | S99: 1 | T99: 1 | U99: 1 | V99: 1 | W99: 1 | X99: 1 | Y99: 1 | Z99: 1 | AA99: 1 | AB99: 1 | AC99: 1
A100: =A97 -> Guest Rooms | B100: =B97 -> ResidentialLiving | C100: HtgSetpt | D100: Honeywell-INNCOM e7 Thermostat User Guide & Engineering Judgement | E100: Weekday | F100: =IF((F91=1),Thermostat!$B$11,Thermostat!$B$12) -> 70 | G100: =IF((G91=1),Thermostat!$B$11,Thermostat!$B$12) -> 70 | H100: =IF((H91=1),Thermostat!$B$11,Thermostat!$B$12) -> 70 | I100: =IF((I91=1),Thermostat!$B$11,Thermostat!$B$12) -> 70 | J100: =IF((J91=1),Thermostat!$B$11,Thermostat!$B$12) -> 70 | K100: =IF((K91=1),Thermostat!$B$11,Thermostat!$B$12) -> 70 | L100: =IF((L91=1),Thermostat!$B$11,Thermostat!$B$12) -> 70 | M100: =IF((M91=1),Thermostat!$B$11,Thermostat!$B$12) -> 70 | ... AC100: =IF((AC91=1),Thermostat!$B$11,Thermostat!$B$12) -> 70
...

Sheet Energy Usage
A1: CalBEM Energy Consumption - HotelLarge | O1: Energy Consumption - Lodging
A2: Prototype | B2: CZ | C2: CalBEM Electricity EUI (KBTU/ft²) | D2: CalBEM Gas EUI (KBTU/ft²) | E2: CalBEM Total EUI (KBTU/ft²) | F2: New Construction Electricity EUI (KBTU/ft²) | G2: New Construction Gas EUI (KBTU/ft²) | H2: New Construction Total EUI (KBTU/ft²) | I2: National Average | J2: Acceptable Range (25% Higher) | K2: Acceptable Range (25% Lower) | L2: National Average Acceptable EUI Range | M2: National Average Acceptable EUI Range | O2: Prototype | P2: CZ | Q2: Total Floorspace (Thousand of ft²) | R2: Electric Energy Intensity (kWh/ft²) | S2: Annual Gas Intensity (kWh/ft²) | T2: CEUS 2023 Total EUI (kBtu/ft²) | U2: Acceptable Range (25% Higher) | V2: Acceptable Range (25% Lower) | W2: CEUS 2022 Acceptable EUI Range
A3: HotelLarge | B3: 1 | I3: 88.8 | J3: =(I3*1.25) -> 111 | K3: =(I3*0.75) -> 66.6 | L3: =J3-K3 -> 44.4 | M3: =J3-K3 -> 44.4 | O3: Lodging | P3: 1 | Q3: 9588 | R3: 10.1 | S3: 6.4 | T3: 56.2 | U3: 70.3 | V3: 42.2 | W3: 28.1
B4: 2 | I4: 84.2 | J4: =(I4*1.25) -> 105.25 | K4: =(I4*0.75) -> 63.15 | L4: =J4-K4 -> 42.1 | M4: =J4-K4 -> 42.1 | P4: 2 | Q4: 42372 | R4: 9.1 | S4: 5.4 | T4: 49.6 | U4: 62 | V4: 37.2 | W4: 24.8
B5: 3 | I5: 82.2 | J5: =(I5*1.25) -> 102.75 | K5: =(I5*0.75) -> 61.65 | L5: =J5-K5 -> 41.1 | M5: =J5-K5 -> 41.1 | P5: 3 | Q5: 61013 | R5: 8.1 | S5: 8.4 | T5: 56 | U5: 70 | V5: 42 | W5: 28
B6: 4 | I6: 86.2 | J6: =(I6*1.25) -> 107.75 | K6: =(I6*0.75) -> 64.65 | L6: =J6-K6 -> 43.1 | M6: =J6-K6 -> 43.1 | P6: 4 | Q6: 28798 | R6: 7.9 | S6: 7.8 | T6: 53.8 | U6: 67.3 | V6: 40.4 | W6: 26.9
B7: 5 | I7: 81.3 | J7: =(I7*1.25) -> 101.625 | K7: =(I7*0.75) -> 60.975 | L7: =J7-K7 -> 40.65 | M7: =J7-K7 -> 40.65 | P7: 5 | Q7: 9409 | R7: 7.9 | S7: 11.9 | T7: 67.6 | U7: 84.4 | V7: 50.7 | W7: 33.8
B8: 6 | I8: 80.6 | J8: =(I8*1.25) -> 100.75 | K8: =(I8*0.75) -> 60.45 | L8: =J8-K8 -> 40.3 | M8: =J8-K8 -> 40.3 | P8: 6 | Q8: 34023 | R8: 9 | S8: 10.6 | T8: 67 | U8: 83.7 | V8: 50.2 | W8: 33.5
B9: 7 | I9: 80.8 | J9: =(I9*1.25) -> 101 | K9: =(I9*0.75) -> 60.6 | L9: =J9-K9 -> 40.4 | M9: =J9-K9 -> 40.4 | P9: 7 | Q9: 37336 | R9: 11.7 | S9: 9 | T9: 70.5 | U9: 88.2 | V9: 52.9 | W9: 35.3
B10: 8 | I10: 83.4 | J10: =(I10*1.25) -> 104.25 | K10: =(I10*0.75) -> 62.55 | L10: =J10-K10 -> 41.7 | M10: =J10-K10 -> 41.7 | P10: 8 | Q10: 50599 | R10: 8.9 | S10: 10.4 | T10: 65.8 | U10: 82.3 | V10: 49.4 | W10: 32.9
B11: 9 | I11: 83.8 | J11: =(I11*1.25) -> 104.75 | K11: =(I11*0.75) -> 62.85 | L11: =J11-K11 -> 41.9 | M11: =J11-K11 -> 41.9 | P11: 9 | Q11: 56761 | R11: 8.9 | S11: 10 | T11: 64.6 | U11: 80.7 | V11: 48.4 | W11: 32.3
B12: 10 | I12: 85.5 | J12: =(I12*1.25) -> 106.875 | K12: =(I12*0.75) -> 64.125 | L12: =J12-K12 -> 42.75 | M12: =J12-K12 -> 42.75 | P12: 10 | Q12: 48383 | R12: 10.6 | S12: 13.1 | T12: 80.7 | U12: 100.9 | V12: 60.5 | W12: 40.4
B13: 11 | I13: 89.7 | J13: =(I13*1.25) -> 112.125 | K13: =(I13*0.75) -> 67.275 | L13: =J13-K13 -> 44.85 | M13: =J13-K13 -> 44.85 | P13: 11 | Q13: 13807 | R13: 13.4 | S13: 12.1 | T13: 86.9 | U13: 108.7 | V13: 65.2 | W13: 43.5
B14: 12 | I14: 86.9 | J14: =(I14*1.25) -> 108.625 | K14: =(I14*0.75) -> 65.175 | L14: =J14-K14 -> 43.45 | M14: =J14-K14 -> 43.45 | P14: 12 | Q14: 54244 | R14: 11.8 | S14: 11.5 | T14: 79.5 | U14: 99.3 | V14: 59.6 | W14: 39.7
B15: 13 | I15: 90.1 | J15: =(I15*1.25) -> 112.625 | K15: =(I15*0.75) -> 67.575 | L15: =J15-K15 -> 45.05 | M15: =J15-K15 -> 45.05 | P15: 13 | Q15: 16296 | R15: 11.8 | S15: 9 | T15: 71 | U15: 88.8 | V15: 53.3 | W15: 35.5
... B18: 16 | I18: 91.5 | J18: =(I18*1.25) -> 114.375 | K18: =(I18*0.75) -> 68.625 | L18: =J18-K18 -> 45.75 | M18: =J18-K18 -> 45.75 | P18: 16 | Q18: 33483 | R18: 12.3 | S18: 13.6 | T18: 88.4 | U18: 110.5 | V18: 66.3 | W18: 44.2
Q21: Ref: CEUS 2022 Report
Q22: And converted FZ level data to CZ level
Q23: CEUS has only one category for Lodging buildings
Q26: Background Data [To be deleted prior to publication]

Sheet Weights
A1: % of Floor Area per CZ and Vintage Bin - Lodging | J1: % of Floor Area per CZ and Vintage Bin - Lodging
A2: Prototype | B2: CZ | C2: Vintage Bin | J2: Prototype | K2: Vintage Bin | L2: CZ
C3: Pre-1978 | D3: 1978-1997 | E3: 1998-2007 | F3: 2008-2018 | L3: 1 | M3: 2 | N3: 3 | O3: 4 | P3: 5 | Q3: 6 | R3: 7 | S3: 8 | T3: 9 | U3: 10 | V3: 11 | W3: 12 | X3: 13 | Y3: 14 | Z3: 15 | AA3: 16
A4: Hotel | B4: 1 | H4: =SUM(C4:G4) -> 0 | J4: Hotel | K4: Pre-1978 | AB4: =SUM(L4:AA4) -> 0
B5: 2 | H5: =SUM(C5:G5) -> 0 | K5: 1978-1997 | AB5: =SUM(L5:AA5) -> 0
B6: 3 | H6: =SUM(C6:G6) -> 0 | K6: 1998-2007 | AB6: =SUM(L6:AA6) -> 0
B7: 4 | H7: =SUM(C7:G7) -> 0 | I7: =I3*Weights!C4 -> 0 | K7: 2008-2018 | AB7: =SUM(L7:AA7) -> 0
B8: 5 | H8: =SUM(C8:G8) -> 0 | K8: Not available | AB8: =SUM(L8:AA8) -> 0
B9: 6 | H9: =SUM(C9:G9) -> 0 | K9: Total
B10: 7 | H10: =SUM(C10:G10) -> 0
B11: 8 | H11: =SUM(C11:G11) -> 0
B12: 9 | H12: =SUM(C12:G12) -> 0
B13: 10 | H13: =SUM(C13:G13) -> 0
B14: 11 | H14: =SUM(C14:G14) -> 0
B15: 12 | H15: =SUM(C15:G15) -> 0
B16: 13 | H16: =SUM(C16:G16) -> 0
B17: 14 | H17: =SUM(C17:G17) -> 0
B18: 15 | H18: =SUM(C18:G18) -> 0
B19: 16 | H19: =SUM(C19:G19) -> 0
B20: Statewide
A22: Ref: CEUS 2022 dataset
A23: And converted FZ level data to CZ level
A24: CEUS has only one category for Lodging buildings

Sheet PV
A1: ="PV - "&Prototype!A2 -> PV - HotelLarge
A2: TBD

Sheet EV Charger
A1: ="EV Charger - "&Prototype!A2 -> EV Charger - HotelLarge
A2: TBD
A11: Background Data [To be deleted prior to publication]

Sheet Data
A1: Space Function | B1: Exhaust Required? | C1: Total cfm Driven by People | D1: Total cfm Driven by Area | E1: Total cfm Driven by Exhaust | F1: Plug load Power Density (W/ft²) | G1: Gas Power Density (Btu/hr-ft²) | H1: Refrigeration Power Density (W/ft²) | I1: LPD (W/ft²) 2025 | J1: LPD (W/ft²) 2019 | K1: LPD (W/ft²) 2016 | L1: Hot Water Usage Specification (gal/hr per person) [T24, 2022, Appendix 5.4A , sheet: "2022 SpaceFuncData-Input"] | AG1: Exhaust Required? | AS1: Ventilation in T24
A2: Aging Eye/Low-vision (Corridor Area) | AS2: 2025 | AZ2: 2013 | BB2: 2008
A3: Aging Eye/Low-vision (Dining) | AS3: TABLE 120.1-A– Minimum Ventilation Rates | AZ3: TABLE 120.1-A MINIMUM VENTILATION RATES | BB3: TABLE 121-A MINIMUM VENTILATION RATES
A4: Aging Eye/Low-vision (Lobby, Main Entry) | AS4: Building Category | AT4: Occupancy Category | AU4: Minimum Occupant Load Density (persons / 1000 ft²) | AV4: Area-Based Minimum Ventilation Ra (cfm/ft²) | AW4: Air Class | AX4: Notes | AZ4: Type of Use | BA4: CFM per Square Foot of Conditioned Floor Area | BB4: CFM per Square Foot of Conditioned Floor Area
A5: Aging Eye/Low-vision (Lounge/Waiting Area) | AS5: Educational Facilities | AT5: Daycare (through age 4) | AU5: 14 | AV5: 0.15 | AW5: 2 | AX5: -- | AZ5: Auto repair workshops | BA5: 1.5 | BB5: 1.5
A6: Aging Eye/Low-vision (Multipurpose Room) | AS6: Educational Facilities | AT6: Daycare sickroom | AU6: 5 | AV6: 0.15 | AW6: 3 | AX6: -- | AZ6: Barber shops | BA6: 0.4 | BB6: 0.4
A7: Aging Eye/Low-vision (Religious Worship Area) | AS7: Educational Facilities | AT7: Classrooms (ages 5–8) | AU7: 25 | AV7: 0.15 | AW7: 1 | AX7: -- | AZ7: Bars, cocktail lounges, and casinos | BA7: 0.2 | BB7: 0.2
A8: Aging Eye/Low-vision (Restroom) | AS8: Educational Facilities | AT8: Classrooms (age 9–18) | AU8: 25 | AV8: 0.15 | AW8: 1 | AX8: -- | AZ8: Beauty shops | BA8: 0.4 | BB8: 0.4
A9: Aging Eye/Low-vision (Stairwell) | AS9: Educational Facilities | AT9: Lecture / postsecondary classroom | AU9: 25 | AV9: 0.15 | AW9: 1 | AX9: F | AZ9: Coin-operated dry cleaning | BA9: 0.3 | BB9: 0.3
A10: Audience Seating Area | AS10: Educational Facilities | AT10: Lecture hall (fixed seats) | AU10: 71 | AV10: 0.15 | AW10: 1 | AX10: F | AZ10: Commercial dry cleaning | BA10: 0.45 | BB10: 0.45
A11: Auditorium Area | AS11: Educational Facilities | AT11: Art classroom | AU11: 25 | AV11: 0.15 | AW11: 2 | AX11: -- | AZ11: High-rise residential Ventilation Rates (CBC) | BA11: Ventilation Rates Specified by the CBC | BB11: —
A12: Auto Repair / Maintenance Area | AS12: Educational Facilities | AT12: Science laboratories | AU12: 25 | AV12: 0.15 | AW12: 2 | AX12: -- | AZ12: Hotel guest rooms (<500 ft²) | BA12: 30 cfm/guest room | BB12: 30 cfm/guest room
A13: Barber, Beauty Salon, Spa Area | AS13: Educational Facilities | AT13: University / college laboratories | AU13: 25 | AV13: 0.15 | AW13: 2 | AX13: -- | AZ13: Hotel guest rooms (≥500 ft²) | BA13: 0.15 | BB13: 0.15
A14: Civic Meeting Place Area | AS14: Educational Facilities | AT14: Wood / metal shop | AU14: 10 | AV14: 0.15 | AW14: 2 | AX14: -- | AZ14: Retail stores | BA14: 0.2 | BB14: 0.2
A15: Classroom, Lecture, Training, Vocational Areas | AS15: Educational Facilities | AT15: Computer lab | AU15: 25 | AV15: 0.15 | AW15: 1 | AX15: -- | AZ15: All others | BA15: 0.15 | BB15: 0.15
A16: Concourse and Atria Area | AS16: Educational Facilities | AT16: Media center | AU16: 25 | AV16: 0.15 | AW16: 1 | AX16: A
A17: Convention, Conference, Multipurpose and Meeting Area | AS17: Educational Facilities | AT17: Music / theater / dance | AU17: 33 | AV17: 0.15 | AW17: 1 | AX17: F
A18: Copy Room | AS18: Educational Facilities | AT18: Multiuse assembly | AU18: 33 | AV18: 0.15 | AW18: 1 | AX18: F
A19: Corridor Area | AS19: Food and Beverage Service | AT19: Restaurant dining rooms | AU19: 33 | AV19: 0.15 | AW19: 2 | AX19: --
A20: Dining Area (Bar/Lounge and Fine Dining) | AS20: Food and Beverage Service | AT20: Cafeteria / fast-food dining | AU20: 33 | AV20: 0.15 | AW20: 2 | AX20: --
A21: Dining Area (Cafeteria/Fast Food) | AS21: Food and Beverage Service | AT21: Bars, cocktail lounges | AU21: 33 | AV21: 0.2 | AW21: 2 | AX21: --
A22: Dining Area (Family and Leisure) | AS22: Food and Beverage Service | AT22: Kitchen (cooking) | AU22: 3 | AV22: 0.15 | AW22: 2 | AX22: --
A23: Electrical, Mechanical, Telephone Rooms | AS23: General | AT23: Break rooms | AU23: 33 | AV23: 0.15 | AW23: 1 | AX23: F
A24: Exercise/Fitness Center and Gymnasium Areas | AS24: General | AT24: Coffee stations | AU24: 33 | AV24: 0.15 | AW24: 1 | AX24: F
A25: Financial Transaction Area | AS25: General | AT25: Conference / meeting | AU25: 33 | AV25: 0.15 | AW25: 1 | AX25: F
A26: Healthcare Facility and Hospitals (Exam/Treatment Room) | AS26: General | AT26: Corridors | AU26: 5 | AV26: 0.15 | AW26: 1 | AX26: F
A27: Healthcare Facility and Hospitals (Imaging Room) | AS27: General | AT27: Occupiable storage rooms for liquids or gels | AU27: 2 | AV27: 0.15 | AW27: 2 | AX27: B
... A72: Transportation Function (Ticketing Area) | AS72: Public Assembly Spaces | AT72: Common corridors | AU72: 5 | AV72: 0.15 | AW72: 1 | AX72: F
A73: Videoconferencing Studio
A74: High-Rise Residential Living Spaces | AS74: General footnotes for Table 120.1-A:
A75: Hotel/Motel Guest Room | AS75: 1 The minimum occupant density is one half of the maximum occupant load assumed for egress
A76: All other | AS76: purposes in the CBC.
A77: Attic | AS77: Specific Notes:
A78: Reception Area | AS78: A – For high-school and college libraries, the values shown for “Public Assembly Spaces – Libraries” shall
A79: Elevator | AS79: be used.
A80: Plenum | AS80: B – Rate may not be sufficient where stored materials include those having potentially harmful
A81: IT Room (EPD 12) | AS81: emissions.
A82: Computer Room (EPD 20) | AS82: C – Rate does not allow for humidity control. “Deck area” refers to the area surrounding the pool that is
A83: Server Room (EPD 45) | O83: =A84 -> Basement of Large Hotel | AS83: capable of being wetted during pool use or when the pool is occupied. Deck area that is not expected to
A84: Basement of Large Hotel | C84: =SUMPRODUCT($Q$85:$Q$88,W85:W88) -> 13.45 | D84: =SUMPRODUCT($Q$85:$Q$88,X85:X88) -> 307.51616 | E84: =SUMPRODUCT($Q$85:$Q$88,Y85:Y88) -> 49 | F84: =SUMPRODUCT($Q$85:$Q$88,Z85:Z88) -> 1.235 | G84: =SUMPRODUCT($Q$85:$Q$88,AA85:AA88) -> 0 | H84: =SUMPRODUCT($Q$85:$Q$88,AB85:AB88) -> 0 | I84: =SUMPRODUCT($Q$85:$Q$88,AC85:AC88) -> 0.7275 | J84: =SUMPRODUCT($Q$85:$Q$88,AD85:AD88) -> 0.7725 | ... L84: =SUMPRODUCT($Q$85:$Q$88,AF85:AF88) -> 0.2724 | O84: Space considered in Basement | P84: Space Type | Q84: Share | R84: People (Persons/1,000 ft²) Ref: T24, 2025, Table 120.1-A | S84: Floor Area (ft²) | T84: cfm/person (T24, 2025, Equation 120.1-F and Table 120.1-A) | U84: cfm/ft² (T24, 2025, Equation 120.1-F and Table 120.1-A) | V84: Required Exhaust Rate (T24, 2025, Table 120.1-B – Minimum Exhaust Rates) | W84: Total cfm Driven by People | X84: Total cfm Driven by Area | Y84: Total cfm Driven by Exhaust | Z84: Plug load Power Density (W/ft²) | AA84: Gas Power Density (Btu/hr-ft²) | AB84: Refrigeration Power Density (W/ft²) | AC84: LPD 2025 | AD84: LPD 2019 | AE84: LPD 2016 | AF84: Hot Water [Gal/h per Person] | AG84: Internal Mass ft2 (2 ft2 mass per 1 ft2 of floor area) | AS84: be wetted shall be designated as an occupancy category.
A85: BasementService | O85: Conference | P85: Convention, Conference, Multipurpose and Meeting Area | Q85: 0.35 | R85: 33 | S85: =Q85*Zones!$H$3 -> 2609.228 | T85: 15 | U85: 0.15 | V85: 2*50/70 per unit | W85: =R85 -> 33 | X85: =U85*S85 -> 391.3842 | Y85: =2*70 -> 140 | Z85: 1.5 | AC85: 0.75 | AD85: 0.85 | AE85: 1.2 | AF85: 0.18 | AG85: =Q85*SUM($S$85:$S$88)*2 -> 5218.456 | AS85: D – Rate does not include special exhaust for stage effects such as dry ice vapors and smoke.
O86: Office | P86: Office Area (>250 square feet) | Q86: 0.2 | R86: 5 | S86: =Q86*Zones!$H$3 -> 1490.9874 | T86: 15 | U86: 0.15 | W86: =R86 -> 5 | X86: =U86*S86 -> 223.64811 | Z86: 1 | AC86: 0.6 | AD86: 0.65 | AE86: 0.75 | AF86: 0.18 | AG86: =Q86*SUM($S$85:$S$88)*2 -> 2981.9749 | AS86: E – Where combustion equipment is intended to be used on the playing surface or in the space,
O87: Service and back up prep | P87: Kitchen/Food Preparation Area | Q87: 0.3 | R87: 3 | S87: =Q87*Zones!$H$3 -> 2236.4811 | T87: 15 | U87: 0.15 | V87: 0.7 cfm/ft2 | W87: =R87 -> 3 | X87: =U87*S87 -> 335.47217 | Z87: 1.5 | AC87: 0.95 | AD87: 0.95 | AE87: 1.2 | AF87: 0.578 | AG87: =Q87*SUM($S$85:$S$88)*2 -> 4472.9623 | AS87: additional dilution ventilation, source control, or both shall be provided.
O88: Storage | P88: Storage (General) | Q88: 0.15 | R88: 0 | S88: =Q88*Zones!$H$3 -> 1118.2406 | T88: 15 | U88: 0.15 | W88: =R88 -> 0 | X88: =U88*S88 -> 167.73609 | Z88: 0.4 | AC88: 0.4 | AD88: 0.4 | AE88: 0.5 | AF88: 0 | AG88: =Q88*SUM($S$85:$S$88)*2 -> 2236.4811 | AS88: F – Ventilation air for this occupancy category shall be permitted to be reduced to zero when the space
AS89: is in occupied-standby mode.
AS91: Table 120.1-B – Minimum Exhaust Rates [ASHRAE 62.1: Table 6-2]
AS92: Occupancy Category | AT92: Exhaust Rate (cfm/unit) | AU92: Exhaust Rate (cfm/ft²) | AV92: Air Class | AW92: Notes
AS93: Animal imaging (MRI/CT/PET) | AT93: — | AU93: 0.9 | AV93: 3 | AW93: —
AS94: Animal operating rooms | AT94: — | AU94: 3 | AV94: 3 | AW94: —
AS95: Animal postoperative recovery room | AT95: — | AU95: 1.5 | AV95: 3 | AW95: —
AS96: Animal preparation rooms | AT96: — | AU96: 1.5 | AV96: 3 | AW96: —
AS97: Animal procedure room | AT97: — | AU97: 2.25 | AV97: 3 | AW97: —
AS98: Animal surgery scrub | AT98: — | AU98: 1.5 | AV98: 3 | AW98: —
AS99: Large-animal holding room | AT99: — | AU99: 2.25 | AV99: 3 | AW99: —
AS100: Animal necropsy | AT100: — | AU100: 2.25 | AV100: 3 | AW100: —
AS101: Small-animal-cage room (static cages) | AT101: — | AU101: 2.25 | AV101: 3 | AW101: —
AS102: Small-animal-cage room (ventilated cages) | AT102: — | AU102: 1.5 | AV102: 3 | AW102: —
AS103: Arenas | AT103: — | AU103: 0.5 | AV103: 1 | AW103: B
AS104: Art classrooms | AT104: — | AU104: 0.7 | AV104: 2 | AW104: —
... AS116: All other locker rooms | AT116: — | AU116: 0.25 | AV116: 2 | AW116: —
AS117: Shower rooms 20/50 | AT117: — | AU117: 2 | AV117: G,H | AW117: —
AS118: Paint spray booths | AT118: — | AU118: — | AV118: 4 | AW118: F
AS119: Parking garages | AT119: — | AU119: 0.75 | AV119: 2 | AW119: C
AS120: Pet shops (animal areas) | AT120: — | AU120: 0.9 | AV120: 2 | AW120: —
AS121: Refrigerating machinery rooms | AT121: — | AU121: — | AV121: 3 | AW121: F
AS122: Soiled laundry storage rooms | AT122: — | AU122: 1 | AV122: 3 | AW122: F
AS123: Storage rooms, chemical | AT123: — | AU123: 1.5 | AV123: 4 | AW123: F
AS124: Toilets – private 25/50 | AT124: — | AU124: 2 | AV124: E | AW124: —
AS125: Toilets – public 50/70 | AT125: — | AU125: 2 | AV125: D | AW125: —
AS126: Woodwork shop/classrooms | AT126: — | AU126: 0.5 | AV126: 2 | AW126: —
AS130: Notes:
AS131: A – Stands where engines are run shall have exhaust systems that directly connect to the engine exhaust and
AS132: prevent escape of fumes.
AS133: B – Where combustion equipment is intended to be used on the playing surface, additional dilution
AS134: ventilation, source control, or both shall be provided.
AS135: C – Exhaust shall not be required where two or more sides comprise walls that are at least 50% open to the
AS136: outside.
AS137: D – Rate is per water closet, urinal, or both. Provide the higher rate where periods of heavy use are expected
AS138: to occur. The lower rate shall be permitted to be used otherwise.
AS139: E – Rate is for a toilet room intended to be occupied by one person at a time. For continuous systems
AS140: operation during hours of use, the lower rate shall be permitted to be used. Otherwise the higher rate
AS141: shall be used.
... AS144: shall be used.
